Workbook

Sheet Model Assumptions
A1: MODEL DESCRIPTION:
A2: Client: | B2: IWC
A3: Property: | B3: Boot Hill
A4: Run Date: | B4: 46048.485
A5: Description: | B5: IWC - Boothill - HSM
A6: Scenario Name: | B6: IWC_2025_BTHILL_HSM
A7: Length of Horizon: | B7: =CONCATENATE(B18, " years") -> 50 years
A8: Objective Function: | B8: Max: Net Present Value from Operating Cash Flow
A9: Gross Acres: | B9: 12404.89
A10: G&Y Models: | B10: Stand-table Projection, FastLob & PMRC
A11: Woodstock RSPS File: | B11: Z:\Harvest_Schedules\IWC\IWC_2025_BTHILL_HSM\REPORTS\IWC_2025_BTHILL_HSM_DRAFT6.rsps
A13: MODEL ASSUMPTIONS:
A15: Model Year 1: | B15: 2026
A16: Discount Rate: | B16: 0.05
A17: Inflation Rate: | B17: 1e-07
A18: Planning Period Length: | B18: 50
A19: Plantation Merch Age: | B19: 12
A21: MODEL CONSTRAINTS: | B21: Includes 2026 budgeted stands
B22: Existing Unthinned stands age >20 schedule for clearcut when elligable at age 24
B23: All future stands are thinned at least once and no later than 16 years of age
B24: Max clearcut acres <= 1,500
B25: Natural Non-Convertible stands havrested <= 2% of Plantation harvests annually
A47: PRODUCT PRICES: | B47: =$B$15 -> 2026 | C47: =B47+1 -> 2027 | D47: =C47+1 -> 2028 | E47: =D47+1 -> 2029 | F47: =E47+1 -> 2030 | G47: =F47+1 -> 2031 | H47: =G47+1 -> 2032 | I47: =H47+1 -> 2033 | J47: =I47+1 -> 2034 | ... P47: =O47+1 -> 2040
A48: Pine Pulpwood | B48: 3 | C48: 3.0849 | D48: 3.1592 | E48: 3.2193 | F48: 3.2689 | G48: 3.3113 | H48: 3.3467 | I48: 3.375 | J48: 3.3962 | K48: 3.4175 | L48: 3.4351 | M48: 3.4458 | N48: 3.4599 | O48: 3.4634 | P48: 3.4741
A49: Pine Chipnsaw | B49: 13 | C49: 13.3464 | D49: 13.6474 | E49: 13.9144 | F49: 14.1415 | G49: 14.3346 | H49: 14.4993 | I49: 14.6413 | J49: 14.7549 | K49: 14.8515 | L49: 14.9367 | M49: 15.0105 | N49: 15.0616 | O49: 15.1127 | P49: 15.1525
A50: Pine Sawlog | B50: 19 | C50: 20.042 | D50: 20.978 | E50: 21.7829 | F50: 22.488 | G50: 23.0745 | H50: 23.5737 | I50: 23.998 | J50: 24.3537 | K50: 24.6532 | L50: 24.9028 | M50: 25.1149 | N50: 25.2897 | O50: 25.4456 | P50: 27.2926
A51: Pine Large Sawlog | B51: 29 | C51: 29 | D51: 29 | E51: 29 | F51: 29 | G51: 29 | H51: 29 | I51: 29 | J51: 29 | K51: 29 | L51: 29 | M51: 29 | N51: 29 | O51: 29 | P51: 29
A52: Hardwood Pulp | B52: 8 | C52: 8 | D52: 8 | E52: 8 | F52: 8 | G52: 8 | H52: 8 | I52: 8 | J52: 8 | K52: 8 | L52: 8 | M52: 8 | N52: 8 | O52: 8 | P52: 8
A53: Hardwood Sawlog | B53: 30 | C53: 30 | D53: 30 | E53: 30 | F53: 30 | G53: 30 | H53: 30 | I53: 30 | J53: 30 | K53: 30 | L53: 30 | M53: 30 | N53: 30 | O53: 30 | P53: 30
A55: ZONE 2 PRODUCT PRICES: | B55: =$B$15 -> 2026 | C55: =B55+1 -> 2027 | D55: =C55+1 -> 2028 | E55: =D55+1 -> 2029 | F55: =E55+1 -> 2030 | G55: =F55+1 -> 2031 | H55: =G55+1 -> 2032 | I55: =H55+1 -> 2033 | J55: =I55+1 -> 2034 | ... P55: =O55+1 -> 2040
A56: Pine Pulpwood | B56: 5 | C56: 5.1415 | D56: 5.2653 | E56: 5.3656 | F56: 5.4481 | G56: 5.5189 | H56: 5.5778 | I56: 5.625 | J56: 5.6604 | K56: 5.6958 | L56: 5.7252 | M56: 5.7429 | N56: 5.7665 | O56: 5.7724 | P56: 5.7901
A57: Pine Chipnsaw | B57: 20 | C57: 20.533 | D57: 20.9961 | E57: 21.4067 | F57: 21.7562 | G57: 22.0533 | H57: 22.3067 | I57: 22.5251 | J57: 22.6999 | K57: 22.8484 | L57: 22.9795 | M57: 23.0931 | N57: 23.1717 | O57: 23.2503 | P57: 23.3115
A58: Pine Sawlog | B58: 30 | C58: 31.6453 | D58: 33.1232 | E58: 34.3941 | F58: 35.5074 | G58: 36.4335 | H58: 37.2217 | I58: 37.8916 | J58: 38.4532 | K58: 38.9261 | L58: 39.3202 | M58: 39.6552 | N58: 39.931 | O58: 40.1773 | P58: 43.0936
A59: Pine Large Sawlog | B59: 0 | C59: 0 | D59: 0 | E59: 0 | F59: 0 | G59: 0 | H59: 0 | I59: 0 | J59: 0 | K59: 0 | L59: 0 | M59: 0 | N59: 0 | O59: 0 | P59: 0
A60: Hardwood Pulp | B60: 8 | C60: 8 | D60: 8 | E60: 8 | F60: 8 | G60: 8 | H60: 8 | I60: 8 | J60: 8 | K60: 8 | L60: 8 | M60: 8 | N60: 8 | O60: 8 | P60: 8
A61: Hardwood Sawlog | B61: 30 | C61: 30 | D61: 30 | E61: 30 | F61: 30 | G61: 30 | H61: 30 | I61: 30 | J61: 30 | K61: 30 | L61: 30 | M61: 30 | N61: 30 | O61: 30 | P61: 30
B63: Zone 1 PRODUCT SPECS: | C63: Min DBH | D63: Top DOB | E63: Merch Length | F63: % Degrade to pulp | H63: Zone 2 PRODUCT SPECS: | I63: Min DBH | J63: Top DOB | K63: Merch Length | L63: % Degrade to pulp
B64: Pine Pulpwood | C64: 4.6 | D64: 3 | E64: 20 | H64: Pine Pulpwood | I64: 4.6 | J64: 3 | K64: 20
B65: Pine Chipnsaw | C65: 8.6 | D65: 6 | E65: 24 | F65: 10 | H65: Pine Chipnsaw | I65: 8.6 | J65: 6 | K65: 16 | L65: 10
B66: Pine Sawlog | C66: 13.6 | D66: 10 | E66: 16 | F66: 10 | H66: Pine Sawlog | I66: 13.6 | J66: 8 | K66: 0 | L66: 10
B67: Pine Large Sawlog | C67: 13.6 | D67: 12 | E67: 16 | F67: 10 | H67: Pine Large Sawlog
B68: Hardwood Pulp | C68: 5.6 | D68: 3 | E68: 20 | H68: Hardwood Pulp | I68: 5.6 | J68: 3 | K68: 20
B69: Hardwood Sawlog | C69: 13.6 | D69: 10 | E69: 18 | H69: Hardwood Sawlog | I69: 13.6 | J69: 10 | K69: 18
A71: OTHER INCOME / ASSET VALUES:
C72: $/acre | D72: Apprec. Rate (%)
B73: Miscellaneous Income | C73: 0 | D73: 1e-07
B74: Hunt Lease Income | C74: 10.83 | D74: 1e-07
B75: Bare Land value (convertible) | C75: 1761.6511 | D75: 1e-07
B76: Bare Land value (non-convertible) | C76: 706.2702 | D76: 1e-07
A77: CAPEX/OPEX:
C78: USD | E78: Apprec. Rate (%)
B79: Site Prep | C79: 122.5
B80: Planting | C80: 120.4
B81: Herb Weed Control | C81: 44.27
B82: Fertilizer (early, mid, late) | C82: $150, $160, $150
B83: Property Tax | C83: 2.51 | E83: 1e-07
B84: Management Fee | C84: 8 | E84: 1e-07
B85: Harvest Commission - Clearcut | C85: 0.03
B86: Harvest Commission - Thins | C86: 0.03
B87: Hunt Lease Commission | C87: 0.09
B88: Misc. Expense | C88: 0.35 | E88: 1e-07
A90: SILVICULTURE:
A92: Plantation Regen. Assumptions: | B92: Stems/Acre - Survival @ Age 1 | C92: 405
B93: Retain Current Species | C93: Yes
A95: First Thin: | B95: Thin1 Ages/TPA Target/Min Vol | C95: 14 to 17 | D95: 190 | E95: 0
A96: Second Thin: | B96: Thin2 Ages/BA Target/Min Vol | C96: 19 to 21 | D96: 70 | E96: 0
A97: Final Harvest: | B97: Plantation age range | C97: 24 to 29
A99: PLANTATION PREMERCH VALUES: | B99: Age | C99: value/acre
B100: 0 | C100: 238.9447
B101: 1 | C101: 360.0569
B102: 2 | C102: 416.7104
B103: 3 | C103: 482.278
B104: 4 | C104: 558.1624
B105: 5 | C105: 645.987
B106: 6 | C106: 747.6303
B107: 7 | C107: 865.2668
B108: 8 | C108: 1001.4129
B109: 9 | C109: 1158.981
B110: 10 | C110: 1341.3418
B111: 11 | C111: 1552.3963
B112: 12
B113: 13
B114: 14
A116: SPATIAL CONSTRAINTS:
B117: Green up delay (years):
B118: Adjacency (feet):
B119: Max Opening Size (acres):
B120: Min Opening Size (acres):
B121: Proximal Distance (feet):
B122: Target Harvest Block Size (acres):

Sheet Finance Report
A1: DISCOUNTED CASH FLOW ANALYSIS
A2: Finance Report
A3: =CONCATENATE('Model Assumptions'!B2, " - ",'Model Assumptions'!B3 ) -> IWC - Boot Hill
A4: ='Model Assumptions'!B5 -> IWC - Boothill - HSM
A6: Calendar Year >> | B6: Model Year 0 | C6: 2026 | D6: =C6+1 -> 2027 | E6: =D6+1 -> 2028 | F6: =E6+1 -> 2029 | G6: =F6+1 -> 2030 | H6: =G6+1 -> 2031 | I6: =H6+1 -> 2032 | J6: =I6+1 -> 2033 | K6: =J6+1 -> 2034 | ... AZ6: =AY6+1 -> 2075
A7: Model Discount Period >> | B7: 0 | C7: 1 | D7: =C7+1 -> 2 | E7: =D7+1 -> 3 | F7: =E7+1 -> 4 | G7: =F7+1 -> 5 | H7: =G7+1 -> 6 | I7: =H7+1 -> 7 | J7: =I7+1 -> 8 | K7: =J7+1 -> 9 | ... AZ7: =AY7+1 -> 50
A9: Total Acres | B9: 12404.89 | C9: 12404.89 | D9: 12404.89 | E9: 12404.89 | F9: 12404.89 | G9: 12404.89 | H9: 12404.89 | I9: 12404.89 | J9: 12404.89 | K9: 12404.89 | L9: 12404.89 | M9: 12404.89 | N9: 12404.89 | O9: 12404.89 | P9: 12404.89 | Q9: 12404.89 | R9: 12404.89 | S9: 12404.89 | T9: 12404.89 | U9: 12404.89 | V9: 12404.89 | W9: 12404.89 | X9: 12404.89 | Y9: 12404.89 | Z9: 12404.89 | AA9: 12404.89 | AB9: 12404.89 | AC9: 12404.89 | AD9: 12404.89 | AE9: 12404.89 | AF9: 12404.89 | AG9: 12404.89 | AH9: 12404.89 | AI9: 12404.89 | AJ9: 12404.89 | AK9: 12404.89 | AL9: 12404.89 | AM9: 12404.89 | AN9: 12404.89 | AO9: 12404.89 | AP9: 12404.89 | AQ9: 12404.89 | AR9: 12404.89 | AS9: 12404.89 | AT9: 12404.89 | AU9: 12404.89 | AV9: 12404.89 | AW9: 12404.89 | AX9: 12404.89 | AY9: 12404.89 | AZ9: 12404.89
A10: Productive Plantation Acres | B10: 8762.98 | C10: 8762.98 | D10: 8762.98 | E10: 8762.98 | F10: 8762.98 | G10: 8762.98 | H10: 8762.98 | I10: 8762.98 | J10: 8762.98 | K10: 8762.98 | L10: 8762.98 | M10: 8762.98 | N10: 8762.98 | O10: 8762.98 | P10: 8762.98 | Q10: 8762.98 | R10: 8762.98 | S10: 8762.98 | T10: 8762.98 | U10: 8762.98 | V10: 8762.98 | W10: 8762.98 | X10: 8762.98 | Y10: 8762.98 | Z10: 8762.98 | AA10: 8762.98 | AB10: 8762.98 | AC10: 8762.98 | AD10: 8762.98 | AE10: 8762.98 | AF10: 8762.98 | AG10: 8762.98 | AH10: 8762.98 | AI10: 8762.98 | AJ10: 8762.98 | AK10: 8762.98 | AL10: 8762.98 | AM10: 8762.98 | AN10: 8762.98 | AO10: 8762.98 | AP10: 8762.98 | AQ10: 8762.98 | AR10: 8762.98 | AS10: 8762.98 | AT10: 8762.98 | AU10: 8762.98 | AV10: 8762.98 | AW10: 8762.98 | AX10: 8762.98 | AY10: 8762.98 | AZ10: 8762.98
A11: Natural Convertible Acres | B11: 611.17 | C11: 611.17 | D11: 611.17 | E11: 611.17 | F11: 611.17 | G11: 611.17 | H11: 611.17 | I11: 611.17 | J11: 611.17 | K11: 611.17 | L11: 611.17 | M11: 611.17 | N11: 611.17 | O11: 611.17 | P11: 611.17 | Q11: 611.17 | R11: 611.17 | S11: 611.17 | T11: 611.17 | U11: 611.17 | V11: 611.17 | W11: 611.17 | X11: 611.17 | Y11: 611.17 | Z11: 611.17 | AA11: 611.17 | AB11: 611.17 | AC11: 611.17 | AD11: 611.17 | AE11: 611.17 | AF11: 611.17 | AG11: 611.17 | AH11: 611.17 | AI11: 611.17 | AJ11: 611.17 | AK11: 611.17 | AL11: 611.17 | AM11: 611.17 | AN11: 611.17 | AO11: 611.17 | AP11: 611.17 | AQ11: 611.17 | AR11: 611.17 | AS11: 611.17 | AT11: 611.17 | AU11: 611.17 | AV11: 611.17 | AW11: 611.17 | AX11: 611.17 | AY11: 611.17 | AZ11: 611.17
A12: Non-Converitble Acres | B12: 3030.74 | C12: 3030.74 | D12: 3030.74 | E12: 3030.74 | F12: 3030.74 | G12: 3030.74 | H12: 3030.74 | I12: 3030.74 | J12: 3030.74 | K12: 3030.74 | L12: 3030.74 | M12: 3030.74 | N12: 3030.74 | O12: 3030.74 | P12: 3030.74 | Q12: 3030.74 | R12: 3030.74 | S12: 3030.74 | T12: 3030.74 | U12: 3030.74 | V12: 3030.74 | W12: 3030.74 | X12: 3030.74 | Y12: 3030.74 | Z12: 3030.74 | AA12: 3030.74 | AB12: 3030.74 | AC12: 3030.74 | AD12: 3030.74 | AE12: 3030.74 | AF12: 3030.74 | AG12: 3030.74 | AH12: 3030.74 | AI12: 3030.74 | AJ12: 3030.74 | AK12: 3030.74 | AL12: 3030.74 | AM12: 3030.74 | AN12: 3030.74 | AO12: 3030.74 | AP12: 3030.74 | AQ12: 3030.74 | AR12: 3030.74 | AS12: 3030.74 | AT12: 3030.74 | AU12: 3030.74 | AV12: 3030.74 | AW12: 3030.74 | AX12: 3030.74 | AY12: 3030.74 | AZ12: 3030.74
A14: Total Available Acres | B14: 11874.6 | C14: 11874.6 | D14: 11874.6 | E14: 11874.6 | F14: 11874.6 | G14: 11874.6 | H14: 11874.6 | I14: 11874.6 | J14: 11874.6 | K14: 11874.6 | L14: 11874.6 | M14: 11874.6 | N14: 11874.6 | O14: 11874.6 | P14: 11874.6 | Q14: 11874.6 | R14: 11874.6 | S14: 11874.6 | T14: 11874.6 | U14: 11874.6 | V14: 11874.6 | W14: 11874.6 | X14: 11874.6 | Y14: 11874.6 | Z14: 11874.6 | AA14: 11874.6 | AB14: 11874.6 | AC14: 11874.6 | AD14: 11874.6 | AE14: 11874.6 | AF14: 11874.6 | AG14: 11874.6 | AH14: 11874.6 | AI14: 11874.6 | AJ14: 11874.6 | AK14: 11874.6 | AL14: 11874.6 | AM14: 11874.6 | AN14: 11874.6 | AO14: 11874.6 | AP14: 11874.6 | AQ14: 11874.6 | AR14: 11874.6 | AS14: 11874.6 | AT14: 11874.6 | AU14: 11874.6 | AV14: 11874.6 | AW14: 11874.6 | AX14: 11874.6 | AY14: 11874.6 | AZ14: 11874.6
A15: Growth - Total Volume | B15: 616852.08 | C15: 67430.277 | D15: 62119.332 | E15: 56728.523 | F15: 54309.616 | G15: 53194.82 | H15: 51978.589 | I15: 46836.864 | J15: 41172.279 | K15: 43513.89 | L15: 36082.925 | M15: 54512.169 | N15: 75970.046 | O15: 100219.13 | P15: 50849.684 | Q15: 33243.495 | R15: 68481.107 | S15: 35498.138 | T15: 40248.505 | U15: 34024.735 | V15: 75639.462 | W15: 95963.804 | X15: 39001.232 | Y15: 55823.519 | Z15: 49482.356 | AA15: 87161.472 | AB15: 34513.631 | AC15: 57182.297 | AD15: 86135.457 | AE15: 37810.579 | AF15: 35215.558 | AG15: 43537.085 | AH15: 46223.153 | AI15: 43090.038 | AJ15: 33262.063 | AK15: 47488.787 | AL15: 72909.334 | AM15: 107708.85 | AN15: 46058.733 | AO15: 38907.705 | AP15: 37193.475 | AQ15: 34996.877 | AR15: 48017.018 | AS15: 27730.356 | AT15: 32034.473 | AU15: 34937.333 | AV15: 22212.194 | AW15: 61482.769 | AX15: 26118.376 | AY15: 22244.457 | AZ15: 9133.5185
A16: Average Growth (vol/ac) | B16: =IF(B15=0,0,B15/B14) -> 51.947188 | C16: =IF(C15=0,0,C15/C14) -> 5.6785304 | D16: =IF(D15=0,0,D15/D14) -> 5.2312779 | E16: =IF(E15=0,0,E15/E14) -> 4.7772997 | F16: =IF(F15=0,0,F15/F14) -> 4.5735954 | G16: =IF(G15=0,0,G15/G14) -> 4.4797147 | H16: =IF(H15=0,0,H15/H14) -> 4.3772918 | I16: =IF(I15=0,0,I15/I14) -> 3.9442899 | ... AZ16: =IF(AZ15=0,0,AZ15/AZ14) -> 0.76916431
A19: Harvest Acres | B19: 0 | C19: 919.96 | D19: 193.34 | E19: 699.1804 | F19: 576.8 | G19: 421.71 | H19: 119.68 | I19: 645.2214 | J19: 1479.316 | K19: 817.0594 | L19: 703.2174 | M19: 459.6524 | N19: 1242.6004 | O19: 662.5206 | P19: 1338.2898 | Q19: 929.28 | R19: 809.49 | S19: 453.22 | T19: 213.74 | U19: 981.9564 | V19: 273.6928 | W19: 365.9684 | X19: 254.00407 | Y19: 1626.1983 | Z19: 2098.8264 | AA19: 251.34 | AB19: 664.15 | AC19: 345.62 | AD19: 1058.01 | AE19: 251.9736 | AF19: 1081.33 | AG19: 1402.99 | AH19: 347.19 | AI19: 215.14 | AJ19: 984.0868 | AK19: 858.55 | AL19: 412.0532 | AM19: 337.29 | AN19: 1312.085 | AO19: 1667.4954 | AP19: 1326.6564 | AQ19: 681.69 | AR19: 558.9724 | AS19: 1125.025 | AT19: 207.81 | AU19: 1193.5536 | AV19: 577.3024 | AW19: 186.6002 | AX19: 330.6838 | AY19: 1501.39 | AZ19: 2222.5636
A20: Total Harvest Volume (tons) | B20: 0 | C20: 47414.973 | D20: 4751.7809 | E20: 61308.341 | F20: 19745.034 | G20: 23397.271 | H20: 2857.348 | I20: 66441.282 | J20: 89801.794 | K20: 56532.3 | L20: 57588.441 | M20: 45747.972 | N20: 132949.63 | O20: 26330.913 | P20: 96057.543 | Q20: 81707.906 | R20: 45318.094 | S20: 16359.018 | T20: 17890.641 | U20: 53193.448 | V20: 23838.226 | W20: 13810.017 | X20: 38950.185 | Y20: 133120.2 | Z20: 238627.42 | AA20: 14458.257 | AB20: 21431.415 | AC20: 13415.615 | AD20: 42202.378 | AE20: 26087.256 | AF20: 40687.067 | AG20: 79747.543 | AH20: 27593.294 | AI20: 12223.322 | AJ20: 74817.252 | AK20: 32247.983 | AL20: 21118.63 | AM20: 9643.3586 | AN20: 102286.55 | AO20: 106829.67 | AP20: 44890.272 | AQ20: 45470.353 | AR20: 46208.697 | AS20: 111441.86 | AT20: 9743.998 | AU20: 81938.098 | AV20: 69260.061 | AW20: 5312.4927 | AX20: 7471.1763 | AY20: 133175 | AZ20: 166268.65
A21: Clearcut Volume (tons) | B21: 0 | C21: 37455.666 | D21: 0 | E21: 54471.547 | F21: 0 | G21: 17966.618 | H21: 0 | I21: 64209.521 | J21: 56261.418 | K21: 3859.4274 | L21: 44501.014 | M21: 43464.637 | N21: 122529.02 | O21: 3686.5475 | P21: 54169.616 | Q21: 63160.981 | R21: 2687.1203 | S21: 1091.2788 | T21: 16164.753 | U21: 21294.946 | V21: 19479.514 | W21: 6447.4673 | X21: 38950.185 | Y21: 105263.92 | Z21: 201762.89 | AA21: 0 | AB21: 0 | AC21: 0 | AD21: 7027.4114 | AE21: 24139.354 | AF21: 0 | AG21: 15710.97 | AH21: 27147.075 | AI21: 0 | AJ21: 55693.603 | AK21: 0 | AL21: 14785.753 | AM21: 0 | AN21: 66449.298 | AO21: 82539.097 | AP21: 2679.9429 | AQ21: 43101.993 | AR21: 38441.187 | AS21: 107267.6 | AT21: 4000.4675 | AU21: 56309.915 | AV21: 69260.061 | AW21: 2104.4252 | AX21: 1122.9453 | AY21: 133165.4 | AZ21: 136551.59
A22: Pine Large Saw Timber | B22: 0 | C22: 1498.1175 | D22: 0 | E22: 2955.033 | F22: 0 | G22: 332.31952 | H22: 0 | I22: 2170.11 | J22: 391.68203 | K22: 0 | L22: 0 | M22: 153.24998 | N22: 8943.018 | O22: 17.180887 | P22: 273.91626 | Q22: 214.47303 | R22: 0 | S22: 0 | T22: 40.363068 | U22: 2810.4066 | V22: 625.60038 | W22: 0 | X22: 0 | Y22: 0 | Z22: 33431.298 | AA22: 0 | AB22: 0 | AC22: 0 | AD22: 1735.1599 | AE22: 5042.629 | AF22: 0 | AG22: 1256.1003 | AH22: 2402.3533 | AI22: 0 | AJ22: 16547.826 | AK22: 0 | AL22: 961.25851 | AM22: 0 | AN22: 12587.13 | AO22: 6100.3956 | AP22: 0 | AQ22: 0 | AR22: 0 | AS22: 9459.3367 | AT22: 0 | AU22: 1141.8714 | AV22: 139.81642 | AW22: 10.319764 | AX22: 4.1222422 | AY22: 4668.9147 | AZ22: 4315.5272
A23: Pine Saw Timber | B23: 0 | C23: 663.581 | D23: 0 | E23: 1163.5334 | F23: 0 | G23: 192.19891 | H23: 0 | I23: 1989.4187 | J23: 1730.5547 | K23: 127.45038 | L23: 2176.8839 | M23: 6408.3695 | N23: 8890.6326 | O23: 426.09889 | P23: 7186.1485 | Q23: 18212.207 | R23: 899.35563 | S23: 126.48941 | T23: 1919.8263 | U23: 1293.6365 | V23: 1766.8829 | W23: 2562.2422 | X23: 17001.716 | Y23: 17988.442 | Z23: 29972.563 | AA23: 0 | AB23: 0 | AC23: 0 | AD23: 0 | AE23: 3168.2347 | AF23: 0 | AG23: 463.4481 | AH23: 1642.4434 | AI23: 0 | AJ23: 428.12452 | AK23: 0 | AL23: 31.152279 | AM23: 0 | AN23: 8520.5548 | AO23: 30561.883 | AP23: 25.055394 | AQ23: 13771.544 | AR23: 12713.628 | AS23: 12149.188 | AT23: 1263.041 | AU23: 5440.4405 | AV23: 33216.445 | AW23: 64.43744 | AX23: 104.99762 | AY23: 10153.318 | AZ23: 6072.6358
A24: Pine Chip-N-Saw | B24: 0 | C24: 23600.409 | D24: 0 | E24: 29844.624 | F24: 0 | G24: 9727.0556 | H24: 0 | I24: 44358.55 | J24: 38176.231 | K24: 2504.7641 | L24: 30810.619 | M24: 27446.956 | N24: 70876.611 | O24: 2387.1885 | P24: 33814.524 | Q24: 33029.622 | R24: 1226.6657 | S24: 726.36945 | T24: 10410.352 | U24: 11570.18 | V24: 11834.755 | W24: 2667.7183 | X24: 14744.306 | Y24: 62565.553 | Z24: 80103.406 | AA24: 0 | AB24: 0 | AC24: 0 | AD24: 2767.2949 | AE24: 8355.2488 | AF24: 0 | AG24: 10537.282 | AH24: 14650.159 | AI24: 0 | AJ24: 18377.534 | AK24: 0 | AL24: 9794.2502 | AM24: 0 | AN24: 26042.093 | AO24: 29488.806 | AP24: 2183.2407 | AQ24: 21494.697 | AR24: 20341.845 | AS24: 62966.218 | AT24: 2227.4474 | AU24: 40925.319 | AV24: 25631.27 | AW24: 1614.8396 | AX24: 839.00988 | AY24: 89222.802 | AZ24: 99790.039
A25: Pine Pulpwood | B25: 0 | C25: 9481.8658 | D25: 0 | E25: 15776.841 | F25: 0 | G25: 7113.8146 | H25: 0 | I25: 13492.006 | J25: 15248.126 | K25: 1097.3081 | L25: 11232.778 | M25: 8778.7163 | N25: 29702.46 | O25: 807.33567 | P25: 12071.431 | Q25: 11571.224 | R25: 515.13311 | S25: 238.41994 | T25: 3621.9893 | U25: 5620.7235 | V25: 4606.1173 | W25: 1203.9644 | X25: 7128.2433 | Y25: 24597.548 | Z25: 58255.623 | AA25: 0 | AB25: 0 | AC25: 0 | AD25: 2524.9565 | AE25: 7573.2416 | AF25: 0 | AG25: 3454.1396 | AH25: 8452.119 | AI25: 0 | AJ25: 20334.791 | AK25: 0 | AL25: 3979.6706 | AM25: 0 | AN25: 19020.547 | AO25: 16298.475 | AP25: 471.64672 | AQ25: 7835.7517 | AR25: 5188.7612 | AS25: 22286.18 | AT25: 509.979 | AU25: 8802.2842 | AV25: 9831.6612 | AW25: 382.2881 | AX25: 161.81733 | AY25: 27428.353 | AZ25: 26373.389
A26: HW Saw Timber | B26: 0 | C26: 335.78893 | D26: 0 | E26: 569.44043 | F26: 0 | G26: 72.061585 | H26: 0 | I26: 252.34545 | J26: 52.68087 | K26: 9.5890075 | L26: 21.766297 | M26: 203.87142 | N26: 538.59126 | O26: 20.243075 | P26: 335.95217 | Q26: 32.964104 | R26: 2.480963 | S26: 0 | T26: 58.357762 | U26: 0 | V26: 47.936062 | W26: 0.57452828 | X26: 3.2208712 | Y26: 4.7674258 | Z26: 0 | AA26: 0 | AB26: 0 | AC26: 0 | AD26: 0 | AE26: 0 | AF26: 0 | AG26: 0 | AH26: 0 | AI26: 0 | AJ26: 0.9684287 | AK26: 0 | AL26: 3.5958789 | AM26: 0 | AN26: 19.058427 | AO26: 0 | AP26: 0 | AQ26: 0 | AR26: 14.801522 | AS26: 26.536905 | AT26: 0 | AU26: 0 | AV26: 163.21766 | AW26: 12.046995 | AX26: 4.8121867 | AY26: 646.75535 | AZ26: 0
A27: HW Pulpwood | B27: 0 | C27: 1875.9037 | D27: 0 | E27: 4162.076 | F27: 0 | G27: 529.16745 | H27: 0 | I27: 1947.0905 | J27: 662.14328 | K27: 120.31581 | L27: 258.96642 | M27: 473.47431 | N27: 3577.7072 | O27: 28.500461 | P27: 487.6436 | Q27: 100.49091 | R27: 43.484844 | S27: 0 | T27: 113.8638 | U27: 0 | V27: 598.2232 | W27: 12.967975 | X27: 72.69995 | Y27: 107.60803 | Z27: 0 | AA27: 0 | AB27: 0 | AC27: 0 | AD27: 0 | AE27: 0 | AF27: 0 | AG27: 0 | AH27: 0 | AI27: 0 | AJ27: 4.3585918 | AK27: 0 | AL27: 15.825895 | AM27: 0 | AN27: 259.91388 | AO27: 89.538024 | AP27: 0 | AQ27: 0 | AR27: 182.15142 | AS27: 380.13809 | AT27: 0 | AU27: 0 | AV27: 277.65106 | AW27: 20.493254 | AX27: 8.186055 | AY27: 1045.2601 | AZ27: 0
A28: First Thin Volume (tons) | B28: =SUM(B29:B32) -> 0 | C28: =SUM(C29:C32) -> 9959.3071 | D28: =SUM(D29:D32) -> 4751.7809 | E28: =SUM(E29:E32) -> 2563.1304 | F28: =SUM(F29:F32) -> 12686.801 | G28: =SUM(G29:G32) -> 5130.8191 | H28: =SUM(H29:H32) -> 0 | I28: =SUM(I29:I32) -> 0 | ... AZ28: =SUM(AZ29:AZ32) -> 20622.732
A29: Pine Large Saw Timber | B29: 0 | C29: 0 | D29: 0 | E29: 0 | F29: 2.461212 | G29: 0 | H29: 0 | I29: 0 | J29: 0 | K29: 0 | L29: 0 | M29: 0 | N29: 0 | O29: 0 | P29: 0 | Q29: 0 | R29: 0 | S29: 0 | T29: 0 | U29: 0 | V29: 0 | W29: 0 | X29: 0 | Y29: 0 | Z29: 0 | AA29: 0 | AB29: 0 | AC29: 0 | AD29: 0 | AE29: 0 | AF29: 0 | AG29: 0 | AH29: 0 | AI29: 0 | AJ29: 0 | AK29: 0 | AL29: 0 | AM29: 0 | AN29: 0 | AO29: 0 | AP29: 0 | AQ29: 0 | AR29: 0 | AS29: 0 | AT29: 0 | AU29: 0 | AV29: 0 | AW29: 0 | AX29: 0 | AY29: 0 | AZ29: 0
A30: Pine Saw Timber | B30: 0 | C30: 14.537703 | D30: 22.062283 | E30: 19.640917 | F30: 0 | G30: 7.3932 | H30: 0 | I30: 0 | J30: 0 | K30: 0 | L30: 0 | M30: 0 | N30: 0 | O30: 0 | P30: 0 | Q30: 0 | R30: 0 | S30: 0 | T30: 0 | U30: 0 | V30: 0 | W30: 0 | X30: 0 | Y30: 0 | Z30: 0 | AA30: 0 | AB30: 0 | AC30: 0 | AD30: 0 | AE30: 0 | AF30: 0 | AG30: 0 | AH30: 0 | AI30: 0 | AJ30: 0 | AK30: 0 | AL30: 0 | AM30: 0 | AN30: 0 | AO30: 0 | AP30: 0 | AQ30: 0 | AR30: 0 | AS30: 0 | AT30: 0 | AU30: 0 | AV30: 0 | AW30: 0 | AX30: 0 | AY30: 0 | AZ30: 0
A31: Pine Chip-N-Saw | B31: 0 | C31: 4579.5133 | D31: 1552.6814 | E31: 529.89649 | F31: 2057.1727 | G31: 363.84031 | H31: 0 | I31: 0 | J31: 7915.9029 | K31: 17200.412 | L31: 3946.5599 | M31: 0 | N31: 1382.2862 | O31: 2401.1385 | P31: 11696.285 | Q31: 0 | R31: 935.70432 | S31: 3517.1739 | T31: 0 | U31: 10507.889 | V31: 0 | W31: 541.63643 | X31: 0 | Y31: 10882.776 | Z31: 18852.184 | AA31: 1.373302 | AB31: 7156.4577 | AC31: 5644.838 | AD31: 10696.078 | AE31: 487.30812 | AF31: 2398.3382 | AG31: 16737.544 | AH31: 24.656528 | AI31: 31.857541 | AJ31: 2125.64 | AK31: 2714.6567 | AL31: 837.73436 | AM31: 602.504 | AN31: 2682.092 | AO31: 1533.6055 | AP31: 11368.632 | AQ31: 0 | AR31: 0 | AS31: 0 | AT31: 803.65515 | AU31: 4758.2287 | AV31: 0 | AW31: 308.98801 | AX31: 1595.8265 | AY31: 0 | AZ31: 10617.111
A32: Pine Pulpwood | B32: 0 | C32: 5365.256 | D32: 3177.0371 | E32: 2013.593 | F32: 10627.167 | G32: 4759.5856 | H32: 0 | I32: 0 | J32: 16262.987 | K32: 35342.669 | L32: 9140.868 | M32: 0 | N32: 9038.3202 | O32: 20243.227 | P32: 14689.298 | Q32: 0 | R32: 4135.8166 | S32: 5850.2918 | T32: 9.595031 | U32: 9726.6187 | V32: 0 | W32: 2402.3859 | X32: 0 | Y32: 12550.853 | Z32: 14545.626 | AA32: 606.47786 | AB32: 6516.5588 | AC32: 7770.7774 | AD32: 22812.89 | AE32: 865.03332 | AF32: 13217.409 | AG32: 12459.355 | AH32: 421.5625 | AI32: 257.87178 | AJ32: 3946.0815 | AK32: 5115.8001 | AL32: 4221.1038 | AM32: 1100.5988 | AN32: 6145.7388 | AO32: 22618.262 | AP32: 27013.856 | AQ32: 1177.0135 | AR32: 0 | AS32: 0 | AT32: 1468.0432 | AU32: 4538.6871 | AV32: 0 | AW32: 2899.0795 | AX32: 4752.4045 | AY32: 9.595031 | AZ32: 10005.621
A33: Second Thin Volume (tons) | B33: =SUM(B34:B37) -> 0 | C33: =SUM(C34:C37) -> 0 | D33: =SUM(D34:D37) -> 0 | E33: =SUM(E34:E37) -> 4273.6633 | F33: =SUM(F34:F37) -> 7058.233 | G33: =SUM(G34:G37) -> 299.8344 | H33: =SUM(H34:H37) -> 2857.348 | I33: =SUM(I34:I37) -> 2231.7607 | ... AZ33: =SUM(AZ34:AZ37) -> 9094.3261
A34: Pine Large Saw Timber | B34: 0 | C34: 0 | D34: 0 | E34: 9.91116 | F34: 160.34929 | G34: 0 | H34: 0 | I34: 0 | J34: 0 | K34: 0 | L34: 0 | M34: 23.667807 | N34: 0 | O34: 0 | P34: 0 | Q34: 0 | R34: 692.74119 | S34: 264.97248 | T34: 0 | U34: 9.792384 | V34: 0 | W34: 14.94796 | X34: 0 | Y34: 23.949768 | Z34: 11.677051 | AA34: 100.29704 | AB34: 28.597095 | AC34: 0 | AD34: 5.193252 | AE34: 4.325148 | AF34: 85.851185 | AG34: 47.985616 | AH34: 0 | AI34: 0 | AJ34: 0 | AK34: 77.506328 | AL34: 0 | AM34: 6.169023 | AN34: 0 | AO34: 0 | AP34: 0 | AQ34: 3.992679 | AR34: 16.884585 | AS34: 0 | AT34: 0 | AU34: 22.178584 | AV34: 0 | AW34: 0 | AX34: 0 | AY34: 0 | AZ34: 4.507696
A35: Pine Saw Timber | B35: 0 | C35: 0 | D35: 0 | E35: 4.493424 | F35: 0 | G35: 1.007624 | H35: 11.273856 | I35: 107.02169 | J35: 76.995358 | K35: 0.488628 | L35: 0 | M35: 0.208408 | N35: 0 | O35: 0 | P35: 409.01862 | Q35: 600.02363 | R35: 363.34979 | S35: 0 | T35: 0 | U35: 0 | V35: 0 | W35: 4.665245 | X35: 0 | Y35: 0 | Z35: 0 | AA35: 0 | AB35: 0 | AC35: 0 | AD35: 0.544752 | AE35: 0 | AF35: 0 | AG35: 144.82022 | AH35: 0 | AI35: 125.28598 | AJ35: 22.509432 | AK35: 0.614592 | AL35: 0 | AM35: 0 | AN35: 266.62817 | AO35: 0 | AP35: 0 | AQ35: 0 | AR35: 0 | AS35: 0 | AT35: 0 | AU35: 0 | AV35: 0 | AW35: 0 | AX35: 0 | AY35: 0 | AZ35: 4.665245
A36: Pine Chip-N-Saw | B36: 0 | C36: 0 | D36: 0 | E36: 2785.7437 | F36: 5157.3315 | G36: 224.12027 | H36: 2250.1516 | I36: 1404.5737 | J36: 6374.8437 | K36: 82.369274 | L36: 0 | M36: 1370.1911 | N36: 0 | O36: 0 | P36: 9384.4496 | Q36: 11640.975 | R36: 24419.809 | S36: 3747.0585 | T36: 1343.6328 | U36: 9341.9275 | V36: 3625.8462 | W36: 3587.4547 | X36: 0 | Y36: 3579.6525 | Z36: 2838.7443 | AA36: 11504.049 | AB36: 6388.9731 | AC36: 0 | AD36: 1344.4835 | AE36: 494.81291 | AF36: 20556.692 | AG36: 28693.698 | AH36: 0 | AI36: 9875.0998 | AJ36: 10123.344 | AK36: 19253.194 | AL36: 955.82531 | AM36: 5823.6615 | AN36: 22156.589 | AO36: 99.4798 | AP36: 2857.5425 | AQ36: 966.80018 | AR36: 6223.7518 | AS36: 3063.4569 | AT36: 2613.5894 | AU36: 12730.194 | AV36: 0 | AW36: 0 | AX36: 0 | AY36: 0 | AZ36: 7070.3958
A37: Pine Pulpwood | B37: 0 | C37: 0 | D37: 0 | E37: 1473.515 | F37: 1740.5522 | G37: 74.706503 | H37: 595.92262 | I37: 720.16529 | J37: 2909.6463 | K37: 46.933218 | L37: 0 | M37: 889.26783 | N37: 0 | O37: 0 | P37: 5708.8764 | Q37: 6305.9264 | R37: 12083.553 | S37: 1888.2425 | T37: 372.66028 | U37: 2312.2745 | V37: 732.86558 | W37: 811.45916 | X37: 0 | Y37: 819.05483 | Z37: 616.30091 | AA37: 2246.0595 | AB37: 1340.8283 | AC37: 0 | AD37: 315.77689 | AE37: 96.422841 | AF37: 4428.7775 | AG37: 5953.1709 | AH37: 0 | AI37: 1933.2069 | AJ37: 2906.0738 | AK37: 5086.212 | AL37: 318.21345 | AM37: 2110.4253 | AN37: 4586.2049 | AO37: 39.223271 | AP37: 970.29929 | AQ37: 220.55397 | AR37: 1526.8739 | AS37: 1110.8082 | AT37: 858.24279 | AU37: 3578.8941 | AV37: 0 | AW37: 0 | AX37: 0 | AY37: 0 | AZ37: 2014.7574
A38: Selection Thinning Volume (tons) | B38: =SUM(B39:B42) -> 0 | C38: =SUM(C39:C42) -> 0 | D38: =SUM(D39:D42) -> 0 | E38: =SUM(E39:E42) -> 0 | F38: =SUM(F39:F42) -> 0 | G38: =SUM(G39:G42) -> 0 | H38: =SUM(H39:H42) -> 0 | I38: =SUM(I39:I42) -> 0 | ... AZ38: =SUM(AZ39:AZ42) -> 0
A39: Pine Large Saw Timber | B39: 0 | C39: 0 | D39: 0 | E39: 0 | F39: 0 | G39: 0 | H39: 0 | I39: 0 | J39: 0 | K39: 0 | L39: 0 | M39: 0 | N39: 0 | O39: 0 | P39: 0 | Q39: 0 | R39: 0 | S39: 0 | T39: 0 | U39: 0 | V39: 0 | W39: 0 | X39: 0 | Y39: 0 | Z39: 0 | AA39: 0 | AB39: 0 | AC39: 0 | AD39: 0 | AE39: 0 | AF39: 0 | AG39: 0 | AH39: 0 | AI39: 0 | AJ39: 0 | AK39: 0 | AL39: 0 | AM39: 0 | AN39: 0 | AO39: 0 | AP39: 0 | AQ39: 0 | AR39: 0 | AS39: 0 | AT39: 0 | AU39: 0 | AV39: 0 | AW39: 0 | AX39: 0 | AY39: 0 | AZ39: 0
A40: Pine Saw Timber | B40: 0 | C40: 0 | D40: 0 | E40: 0 | F40: 0 | G40: 0 | H40: 0 | I40: 0 | J40: 0 | K40: 0 | L40: 0 | M40: 0 | N40: 0 | O40: 0 | P40: 0 | Q40: 0 | R40: 0 | S40: 0 | T40: 0 | U40: 0 | V40: 0 | W40: 0 | X40: 0 | Y40: 0 | Z40: 0 | AA40: 0 | AB40: 0 | AC40: 0 | AD40: 0 | AE40: 0 | AF40: 0 | AG40: 0 | AH40: 0 | AI40: 0 | AJ40: 0 | AK40: 0 | AL40: 0 | AM40: 0 | AN40: 0 | AO40: 0 | AP40: 0 | AQ40: 0 | AR40: 0 | AS40: 0 | AT40: 0 | AU40: 0 | AV40: 0 | AW40: 0 | AX40: 0 | AY40: 0 | AZ40: 0
A41: Pine Chip-N-Saw | B41: 0 | C41: 0 | D41: 0 | E41: 0 | F41: 0 | G41: 0 | H41: 0 | I41: 0 | J41: 0 | K41: 0 | L41: 0 | M41: 0 | N41: 0 | O41: 0 | P41: 0 | Q41: 0 | R41: 0 | S41: 0 | T41: 0 | U41: 0 | V41: 0 | W41: 0 | X41: 0 | Y41: 0 | Z41: 0 | AA41: 0 | AB41: 0 | AC41: 0 | AD41: 0 | AE41: 0 | AF41: 0 | AG41: 0 | AH41: 0 | AI41: 0 | AJ41: 0 | AK41: 0 | AL41: 0 | AM41: 0 | AN41: 0 | AO41: 0 | AP41: 0 | AQ41: 0 | AR41: 0 | AS41: 0 | AT41: 0 | AU41: 0 | AV41: 0 | AW41: 0 | AX41: 0 | AY41: 0 | AZ41: 0
A42: Pine Pulpwood | B42: 0 | C42: 0 | D42: 0 | E42: 0 | F42: 0 | G42: 0 | H42: 0 | I42: 0 | J42: 0 | K42: 0 | L42: 0 | M42: 0 | N42: 0 | O42: 0 | P42: 0 | Q42: 0 | R42: 0 | S42: 0 | T42: 0 | U42: 0 | V42: 0 | W42: 0 | X42: 0 | Y42: 0 | Z42: 0 | AA42: 0 | AB42: 0 | AC42: 0 | AD42: 0 | AE42: 0 | AF42: 0 | AG42: 0 | AH42: 0 | AI42: 0 | AJ42: 0 | AK42: 0 | AL42: 0 | AM42: 0 | AN42: 0 | AO42: 0 | AP42: 0 | AQ42: 0 | AR42: 0 | AS42: 0 | AT42: 0 | AU42: 0 | AV42: 0 | AW42: 0 | AX42: 0 | AY42: 0 | AZ42: 0
A44: Total Revenue | B44: 0 | C44: 777965.22 | D44: 183259.13 | E44: 881229.74 | F44: 303369.61 | G44: 431851.52 | H44: 187667.95 | I44: 1151060.5 | J44: 1513224 | K44: 684956.39 | L44: 1102075.5 | M44: 1106970.5 | N44: 2603399.7 | O44: 371585.05 | P44: 1790512.6 | Q44: 2099007.9 | R44: 748997.02 | S44: 315949.93 | T44: 503286.28 | U44: 924970.57 | V44: 576046.58 | W44: 402329.34 | X44: 1252673.8 | Y44: 2769440.7 | Z44: 5095858.5 | AA44: 324450.63 | AB44: 442688.5 | AC44: 310928.8 | AD44: 599817.1 | AE44: 685996.16 | AF44: 641412.54 | AG44: 1511921.4 | AH44: 648222.08 | AI44: 383377.36 | AJ44: 1547252 | AK44: 592139.1 | AL44: 475498.04 | AM44: 291326.36 | AN44: 2231419.6 | AO44: 2581923.3 | AP44: 581467.47 | AQ44: 1294770.1 | AR44: 1311047.7 | AS44: 2609576.2 | AT44: 326826.46 | AU44: 1751583.2 | AV44: 2232201.8 | AW44: 194370.58 | AX44: 210258.66 | AY44: 2908072.4 | AZ44: 3007619.9
A45: Total Removals | B45: 0 | C45: 643620.23 | D45: 48914.117 | E45: 746884.7 | F45: 169024.55 | G45: 297506.43 | H45: 53322.828 | I45: 1016715.4 | J45: 1378878.8 | K45: 550611.19 | L45: 967730.29 | M45: 972625.2 | N45: 2469054.4 | O45: 237239.74 | P45: 1656167.2 | Q45: 1964662.6 | R45: 614651.63 | S45: 181604.51 | T45: 368940.83 | U45: 790625.1 | V45: 441701.08 | W45: 267983.81 | X45: 1118328.2 | Y45: 2635095.1 | Z45: 4961512.9 | AA45: 190104.99 | AB45: 308342.85 | AC45: 176583.12 | AD45: 465471.39 | AE45: 551650.42 | AF45: 507066.78 | AG45: 1377575.6 | AH45: 513876.26 | AI45: 249031.51 | AJ45: 1412906.1 | AK45: 457793.2 | AL45: 341152.11 | AM45: 156980.4 | AN45: 2097073.6 | AO45: 2447577.3 | AP45: 447121.43 | AQ45: 1160424 | AR45: 1176701.6 | AS45: 2475230.1 | AT45: 192480.32 | AU45: 1617237 | AV45: 2097855.6 | AW45: 60024.361 | AX45: 75912.415 | AY45: 2773726.1 | AZ45: 2873273.6
A46: Clearcut Revenue | B46: 0 | C46: 524767.55 | D46: 0 | E46: 665400.28 | F46: 0 | G46: 258078.56 | H46: 0 | I46: 977383.49 | J46: 946214.46 | K46: 69220.067 | L46: 855415.01 | M46: 947769.02 | N46: 2385226.8 | O46: 78390.287 | P46: 1145467.8 | Q46: 1630925 | R46: 70756.85 | S46: 23764.111 | T46: 335427.68 | U46: 428506.01 | V46: 380991.54 | W46: 179696.76 | X46: 1118328.2 | Y46: 2321622.8 | Z46: 4432310 | AA46: 0 | AB46: 0 | AC46: 0 | AD46: 122985 | AE46: 527269.13 | AF46: 0 | AG46: 265082.96 | AH46: 510860.59 | AI46: 0 | AJ46: 1090838.3 | AK46: 0 | AL46: 277836.05 | AM46: 0 | AN46: 1444418 | AO46: 2282585.4 | AP46: 54705.2 | AQ46: 1139908.5 | AR46: 1054019.3 | AS46: 2406305.7 | AT46: 109306.92 | AU46: 1269020.3 | AV46: 2097855.6 | AW46: 43521.113 | AX46: 25374.334 | AY46: 2773692.8 | AZ46: 2547416.3
A47: First Thin Revenue | B47: 0 | C47: 118852.68 | D47: 48914.117 | E47: 22378.544 | F47: 86328.853 | G47: 34109.066 | H47: 0 | I47: 0 | J47: 269785.97 | K47: 479236.9 | L47: 112315.28 | M47: 0 | N47: 83827.6 | O47: 158849.45 | P47: 243120.68 | Q47: 0 | R47: 38273.764 | S47: 83465.361 | T47: 33.3337 | U47: 195473.09 | V47: 0 | W47: 21178.894 | X47: 0 | Y47: 247877.02 | Z47: 483327.01 | AA47: 3543.5778 | AB47: 204559.18 | AC47: 176583.12 | AD47: 318902.27 | AE47: 16368.503 | AF47: 126074.75 | AG47: 462317.92 | AH47: 3015.6671 | AI47: 2235.7487 | AJ47: 68281.063 | AK47: 75485.064 | AL47: 39191.861 | AM47: 20417.837 | AN47: 98107.967 | AO47: 162445.79 | AP47: 320184.54 | AQ47: 4089.0114 | AR47: 0 | AS47: 0 | AT47: 17277.424 | AU47: 98423.885 | AV47: 0 | AW47: 16503.248 | AX47: 50538.081 | AY47: 33.3337 | AZ47: 199634.68
A48: Second Thin Revenue | B48: 0 | C48: 0 | D48: 0 | E48: 59105.873 | F48: 82695.696 | G48: 5318.7988 | H48: 53322.828 | I48: 39331.868 | J48: 162878.36 | K48: 2154.2208 | L48: 0 | M48: 24856.178 | N48: 0 | O48: 0 | P48: 267578.76 | Q48: 333737.55 | R48: 505621.02 | S48: 74375.042 | T48: 33479.819 | U48: 166646 | V48: 60709.538 | W48: 67108.155 | X48: 0 | Y48: 65595.281 | Z48: 45875.912 | AA48: 186561.42 | AB48: 103783.67 | AC48: 0 | AD48: 23584.124 | AE48: 8012.7886 | AF48: 380992.03 | AG48: 650174.74 | AH48: 0 | AI48: 246795.76 | AJ48: 253786.68 | AK48: 382308.14 | AL48: 24124.198 | AM48: 136562.57 | AN48: 554547.63 | AO48: 2546.1288 | AP48: 72231.697 | AQ48: 16426.489 | AR48: 122682.27 | AS48: 68924.434 | AT48: 65895.97 | AU48: 249792.8 | AV48: 0 | AW48: 0 | AX48: 0 | AY48: 0 | AZ48: 126222.67
A49: Selection Thin Revenue | B49: 0 | C49: 0 | D49: 0 | E49: 0 | F49: 0 | G49: 0 | H49: 0 | I49: 0 | J49: 0 | K49: 0 | L49: 0 | M49: 0 | N49: 0 | O49: 0 | P49: 0 | Q49: 0 | R49: 0 | S49: 0 | T49: 0 | U49: 0 | V49: 0 | W49: 0 | X49: 0 | Y49: 0 | Z49: 0 | AA49: 0 | AB49: 0 | AC49: 0 | AD49: 0 | AE49: 0 | AF49: 0 | AG49: 0 | AH49: 0 | AI49: 0 | AJ49: 0 | AK49: 0 | AL49: 0 | AM49: 0 | AN49: 0 | AO49: 0 | AP49: 0 | AQ49: 0 | AR49: 0 | AS49: 0 | AT49: 0 | AU49: 0 | AV49: 0 | AW49: 0 | AX49: 0 | AY49: 0 | AZ49: 0
A50: Hunt Lease | B50: 0 | C50: 134344.99 | D50: 134345.01 | E50: 134345.04 | F50: 134345.07 | G50: 134345.09 | H50: 134345.12 | I50: 134345.15 | J50: 134345.17 | K50: 134345.2 | L50: 134345.23 | M50: 134345.25 | N50: 134345.28 | O50: 134345.31 | P50: 134345.33 | Q50: 134345.36 | R50: 134345.39 | S50: 134345.42 | T50: 134345.44 | U50: 134345.47 | V50: 134345.5 | W50: 134345.52 | X50: 134345.55 | Y50: 134345.58 | Z50: 134345.6 | AA50: 134345.63 | AB50: 134345.66 | AC50: 134345.68 | AD50: 134345.71 | AE50: 134345.74 | AF50: 134345.76 | AG50: 134345.79 | AH50: 134345.82 | AI50: 134345.85 | AJ50: 134345.87 | AK50: 134345.9 | AL50: 134345.93 | AM50: 134345.95 | AN50: 134345.98 | AO50: 134346.01 | AP50: 134346.03 | AQ50: 134346.06 | AR50: 134346.09 | AS50: 134346.11 | AT50: 134346.14 | AU50: 134346.17 | AV50: 134346.19 | AW50: 134346.22 | AX50: 134346.25 | AY50: 134346.28 | AZ50: 134346.3
A51: Miscellanous Revenue | B51: 0 | C51: 0 | D51: 0 | E51: 0 | F51: 0 | G51: 0 | H51: 0 | I51: 0 | J51: 0 | K51: 0 | L51: 0 | M51: 0 | N51: 0 | O51: 0 | P51: 0 | Q51: 0 | R51: 0 | S51: 0 | T51: 0 | U51: 0 | V51: 0 | W51: 0 | X51: 0 | Y51: 0 | Z51: 0 | AA51: 0 | AB51: 0 | AC51: 0 | AD51: 0 | AE51: 0 | AF51: 0 | AG51: 0 | AH51: 0 | AI51: 0 | AJ51: 0 | AK51: 0 | AL51: 0 | AM51: 0 | AN51: 0 | AO51: 0 | AP51: 0 | AQ51: 0 | AR51: 0 | AS51: 0 | AT51: 0 | AU51: 0 | AV51: 0 | AW51: 0 | AX51: 0 | AY51: 0 | AZ51: 0
A53: Total Costs | B53: 0 | C53: 235968.19 | D53: 351120.4 | E53: 287820.13 | F53: 272213.66 | G53: 310923.68 | H53: 218603.71 | I53: 273095.08 | J53: 311598.13 | K53: 433278.31 | L53: 406187.56 | M53: 294376.79 | N53: 401888.95 | O53: 371307.83 | P53: 411089.13 | Q53: 397723.32 | R53: 420171.73 | S53: 377954.08 | T53: 238746.46 | U53: 243095.95 | V53: 367937.34 | W53: 268176.19 | X53: 270526.17 | Y53: 307099.2 | Z53: 572371.99 | AA53: 559487.59 | AB53: 453211.14 | AC53: 223015.86 | AD53: 204190.47 | AE53: 261259.39 | AF53: 241971.18 | AG53: 353490.13 | AH53: 326117.27 | AI53: 263546.39 | AJ53: 316327.7 | AK53: 318903.64 | AL53: 390014.67 | AM53: 231840.01 | AN53: 329615.18 | AO53: 406336.96 | AP53: 377941.25 | AQ53: 391865.33 | AR53: 293834.36 | AS53: 416974.21 | AT53: 392749.36 | AU53: 417397.83 | AV53: 387880.13 | AW53: 350163.41 | AX53: 289556.37 | AY53: 278887.97 | AZ53: 458675.87
A54: Overhead - Fixed | B54: Used for Cashflow Chart below | C54: =-C53 -> -235968.19 | D54: =-D53 -> -351120.4 | E54: =-E53 -> -287820.13 | F54: =-F53 -> -272213.66 | G54: =-G53 -> -310923.68 | H54: =-H53 -> -218603.71 | I54: =-I53 -> -273095.08 | J54: =-J53 -> -311598.13 | ... AZ54: =-AZ53 -> -458675.87
A55: Lease Fees | C55: OLEASEFEE_FV
A56: Management | B56: 0 | C56: 99239.14 | D56: 99239.16 | E56: 99239.179 | F56: 99239.199 | G56: 99239.219 | H56: 99239.239 | I56: 99239.259 | J56: 99239.279 | K56: 99239.299 | L56: 99239.318 | M56: 99239.338 | N56: 99239.358 | O56: 99239.378 | P56: 99239.398 | Q56: 99239.418 | R56: 99239.438 | S56: 99239.457 | T56: 99239.477 | U56: 99239.497 | V56: 99239.517 | W56: 99239.537 | X56: 99239.557 | Y56: 99239.576 | Z56: 99239.596 | AA56: 99239.616 | AB56: 99239.636 | AC56: 99239.656 | AD56: 99239.676 | AE56: 99239.696 | AF56: 99239.715 | AG56: 99239.735 | AH56: 99239.755 | AI56: 99239.775 | AJ56: 99239.795 | AK56: 99239.815 | AL56: 99239.834 | AM56: 99239.854 | AN56: 99239.874 | AO56: 99239.894 | AP56: 99239.914 | AQ56: 99239.934 | AR56: 99239.954 | AS56: 99239.973 | AT56: 99239.993 | AU56: 99240.013 | AV56: 99240.033 | AW56: 99240.053 | AX56: 99240.073 | AY56: 99240.092 | AZ56: 99240.112
A57: Taxes | B57: 0 | C57: 31136.28 | D57: 31136.286 | E57: 31136.293 | F57: 31136.299 | G57: 31136.305 | H57: 31136.311 | I57: 31136.318 | J57: 31136.324 | K57: 31136.33 | L57: 31136.336 | M57: 31136.342 | N57: 31136.349 | O57: 31136.355 | P57: 31136.361 | Q57: 31136.367 | R57: 31136.374 | S57: 31136.38 | T57: 31136.386 | U57: 31136.392 | V57: 31136.398 | W57: 31136.405 | X57: 31136.411 | Y57: 31136.417 | Z57: 31136.423 | AA57: 31136.43 | AB57: 31136.436 | AC57: 31136.442 | AD57: 31136.448 | AE57: 31136.454 | AF57: 31136.461 | AG57: 31136.467 | AH57: 31136.473 | AI57: 31136.479 | AJ57: 31136.486 | AK57: 31136.492 | AL57: 31136.498 | AM57: 31136.504 | AN57: 31136.511 | AO57: 31136.517 | AP57: 31136.523 | AQ57: 31136.529 | AR57: 31136.535 | AS57: 31136.542 | AT57: 31136.548 | AU57: 31136.554 | AV57: 31136.56 | AW57: 31136.567 | AX57: 31136.573 | AY57: 31136.579 | AZ57: 31136.585
A58: Roads | B58: 0 | C58: 43417.124 | D58: 43417.132 | E58: 43417.141 | F58: 43417.15 | G58: 43417.158 | H58: 43417.167 | I58: 43417.176 | J58: 43417.185 | K58: 43417.193 | L58: 43417.202 | M58: 43417.211 | N58: 43417.219 | O58: 43417.228 | P58: 43417.237 | Q58: 43417.245 | R58: 43417.254 | S58: 43417.263 | T58: 43417.271 | U58: 43417.28 | V58: 43417.289 | W58: 43417.297 | X58: 43417.306 | Y58: 43417.315 | Z58: 43417.323 | AA58: 43417.332 | AB58: 43417.341 | AC58: 43417.349 | AD58: 43417.358 | AE58: 43417.367 | AF58: 43417.376 | AG58: 43417.384 | AH58: 43417.393 | AI58: 43417.402 | AJ58: 43417.41 | AK58: 43417.419 | AL58: 43417.428 | AM58: 43417.436 | AN58: 43417.445 | AO58: 43417.454 | AP58: 43417.462 | AQ58: 43417.471 | AR58: 43417.48 | AS58: 43417.488 | AT58: 43417.497 | AU58: 43417.506 | AV58: 43417.514 | AW58: 43417.523 | AX58: 43417.532 | AY58: 43417.541 | AZ58: 43417.549
A59: Misc. | B59: 0 | C59: 4341.7124 | D59: 4341.7132 | E59: 4341.7141 | F59: 4341.715 | G59: 4341.7158 | H59: 4341.7167 | I59: 4341.7176 | J59: 4341.7184 | K59: 4341.7193 | L59: 4341.7202 | M59: 4341.7211 | N59: 4341.7219 | O59: 4341.7228 | P59: 4341.7237 | Q59: 4341.7245 | R59: 4341.7254 | S59: 4341.7263 | T59: 4341.7271 | U59: 4341.728 | V59: 4341.7289 | W59: 4341.7297 | X59: 4341.7306 | Y59: 4341.7315 | Z59: 4341.7323 | AA59: 4341.7332 | AB59: 4341.7341 | AC59: 4341.7349 | AD59: 4341.7358 | AE59: 4341.7367 | AF59: 4341.7376 | AG59: 4341.7384 | AH59: 4341.7393 | AI59: 4341.7402 | AJ59: 4341.741 | AK59: 4341.7419 | AL59: 4341.7428 | AM59: 4341.7436 | AN59: 4341.7445 | AO59: 4341.7454 | AP59: 4341.7462 | AQ59: 4341.7471 | AR59: 4341.748 | AS59: 4341.7488 | AT59: 4341.7497 | AU59: 4341.7506 | AV59: 4341.7514 | AW59: 4341.7523 | AX59: 4341.7532 | AY59: 4341.754 | AZ59: 4341.7549
A60: Silviculture
A61: SitePrep | B61: 0 | C61: 26434.28 | D61: 45856.668 | E61: 0 | F61: 54514.994 | G61: 0 | H61: 25602.531 | I61: 0 | J61: 67383.683 | K61: 82908.149 | L61: 3610.0822 | M61: 58906.705 | N61: 42338.552 | O61: 117051.5 | P61: 4352.4372 | Q61: 65658.972 | R61: 69872.999 | S61: 3124.9856 | T61: 1248.2795 | U61: 19508.199 | V61: 25289.001 | W61: 20636.437 | X61: 5441.4739 | Y61: 30505.531 | Z61: 119830.86 | AA61: 163998.48 | AB61: 0 | AC61: 0 | AD61: 0 | AE61: 7258.1671 | AF61: 25349.518 | AG61: 0 | AH61: 19671.176 | AI61: 39406.06 | AJ61: 0 | AK61: 55906.941 | AL61: 0 | AM61: 24211.079 | AN61: 0 | AO61: 67384.101 | AP61: 82908.663 | AQ61: 3610.1046 | AR61: 58907.07 | AS61: 42338.814 | AT61: 117052.23 | AU61: 4352.4642 | AV61: 65659.379 | AW61: 69873.432 | AX61: 3125.005 | AY61: 1248.2872 | AZ61: 180572.49
A62: Planting | B62: 0 | C62: 0 | D62: 25981.126 | E62: 45070.563 | F62: 0 | G62: 53580.462 | H62: 0 | I62: 25163.635 | J62: 0 | K62: 66228.547 | L62: 81486.883 | M62: 3548.1958 | N62: 57896.887 | O62: 41612.756 | P62: 115044.93 | Q62: 4277.8248 | R62: 64533.402 | S62: 68675.189 | T62: 3071.4151 | U62: 1226.8807 | V62: 19173.777 | W62: 24855.48 | X62: 20282.673 | Y62: 5348.1926 | Z62: 29982.585 | AA62: 117776.64 | AB62: 161187.11 | AC62: 0 | AD62: 0 | AE62: 0 | AF62: 7133.7428 | AG62: 24914.96 | AH62: 0 | AI62: 19333.96 | AJ62: 38730.535 | AK62: 0 | AL62: 54948.548 | AM62: 0 | AN62: 23796.037 | AO62: 0 | AP62: 66228.958 | AQ62: 81487.388 | AR62: 3548.2178 | AS62: 57897.246 | AT62: 41613.014 | AU62: 115045.64 | AV62: 4277.8514 | AW62: 64533.803 | AX62: 68675.615 | AY62: 3071.4341 | AZ62: 1226.8883
A63: Herb Weed Control | B63: 0 | C63: 0 | D63: 9553.0252 | E63: 16572.037 | F63: 0 | G63: 19701.045 | H63: 0 | I63: 9252.4365 | J63: 0 | K63: 24351.621 | L63: 29961.966 | M63: 1304.6383 | N63: 21288.14 | O63: 15300.617 | P63: 42300.93 | Q63: 1572.9155 | R63: 23728.315 | S63: 25251.208 | T63: 1129.3297 | U63: 451.1122 | V63: 7050.0116 | W63: 9139.118 | X63: 7457.7406 | Y63: 1966.4779 | Z63: 11024.301 | AA63: 43305.306 | AB63: 59266.9 | AC63: 0 | AD63: 0 | AE63: 0 | AF63: 2623.0054 | AG63: 9160.9789 | AH63: 0 | AI63: 7108.9001 | AJ63: 14240.822 | AK63: 0 | AL63: 20204.015 | AM63: 0 | AN63: 8749.556 | AO63: 0 | AP63: 24351.696 | AQ63: 29962.059 | AR63: 1304.6424 | AS63: 21288.206 | AT63: 15300.665 | AU63: 42301.061 | AV63: 1572.9203 | AW63: 23728.389 | AX63: 25251.286 | AY63: 1129.3332 | AZ63: 451.1136
A64: Fertilizer | B64: 0 | C64: 0 | D64: 78036.816 | E64: 13545.604 | F64: 22402.509 | G64: 38491.519 | H64: 1176.0007 | I64: 17952.013 | J64: 12622.51 | K64: 53046.048 | L64: 71871.072 | M64: 11212.812 | N64: 16068.019 | O64: 0 | P64: 9480.0133 | Q64: 77047.892 | R64: 53371.585 | S64: 85228.645 | T64: 32003.258 | U64: 7965.0151 | V64: 112947.49 | W64: 15279.572 | X64: 13568.33 | Y64: 0 | Z64: 72462.674 | AA64: 38477.796 | AB64: 33280.586 | AC64: 27492.074 | AD64: 0 | AE64: 47225.337 | AF64: 1426.5043 | AG64: 87860.472 | AH64: 100803.32 | AI64: 0 | AJ64: 30742.605 | AK64: 59036.307 | AL64: 114400.91 | AM64: 12692.847 | AN64: 43930.667 | AO64: 75298.794 | AP64: 811.5032 | AQ64: 51766.236 | AR64: 4546.5191 | AS64: 30966.133 | AT64: 22782.1 | AU64: 16954.576 | AV64: 63207.291 | AW64: 0 | AX64: 0 | AY64: 0 | AZ64: 0
A65: Production
A66: First Thin Commission | B66: 0 | C66: 3565.5803 | D66: 1467.4235 | E66: 671.3563 | F66: 2589.8656 | G66: 1023.272 | H66: 0 | I66: 0 | J66: 8093.5791 | K66: 14377.107 | L66: 3369.4584 | M66: 0 | N66: 2514.828 | O66: 4765.4836 | P66: 7293.6204 | Q66: 0 | R66: 1148.2129 | S66: 2503.9608 | T66: 1 | U66: 5864.1928 | V66: 0 | W66: 635.3668 | X66: 0 | Y66: 7436.3106 | Z66: 14499.81 | AA66: 106.3073 | AB66: 6136.7754 | AC66: 5297.4935 | AD66: 9567.0682 | AE66: 491.0551 | AF66: 3782.2424 | AG66: 13869.538 | AH66: 90.47 | AI66: 67.0725 | AJ66: 2048.4319 | AK66: 2264.5519 | AL66: 1175.7558 | AM66: 612.5351 | AN66: 2943.239 | AO66: 4873.3737 | AP66: 9605.5361 | AQ66: 122.6703 | AR66: 0 | AS66: 0 | AT66: 518.3227 | AU66: 2952.7166 | AV66: 0 | AW66: 495.0974 | AX66: 1516.1424 | AY66: 1 | AZ66: 5989.0405
A67: Second Thin Commission | B67: 0 | C67: 0 | D67: 0 | E67: 1773.1762 | F67: 2480.8709 | G67: 159.564 | H67: 1599.6848 | I67: 1179.956 | J67: 4886.3508 | K67: 64.6266 | L67: 0 | M67: 745.6853 | N67: 0 | O67: 0 | P67: 8027.3628 | Q67: 10012.127 | R67: 15168.631 | S67: 2231.2513 | T67: 1004.3946 | U67: 4999.3801 | V67: 1821.2861 | W67: 2013.2447 | X67: 0 | Y67: 1967.8584 | Z67: 1376.2774 | AA67: 5596.8425 | AB67: 3113.51 | AC67: 0 | AD67: 707.5237 | AE67: 240.3837 | AF67: 11429.761 | AG67: 19505.242 | AH67: 0 | AI67: 7403.8728 | AJ67: 7613.6005 | AK67: 11469.244 | AL67: 723.7259 | AM67: 4096.877 | AN67: 16636.429 | AO67: 76.3839 | AP67: 2166.9509 | AQ67: 492.7947 | AR67: 3680.4683 | AS67: 2067.733 | AT67: 1976.8791 | AU67: 7493.7841 | AV67: 0 | AW67: 0 | AX67: 0 | AY67: 0 | AZ67: 3786.6801
A68: Clearcut Commision | B68: 0 | C68: 15743.027 | D68: 0 | E68: 19962.008 | F68: 0 | G68: 7742.3568 | H68: 0 | I68: 29321.505 | J68: 28386.434 | K68: 2076.602 | L68: 25662.45 | M68: 28433.071 | N68: 71556.804 | O68: 2351.7086 | P68: 34364.034 | Q68: 48927.751 | R68: 2122.7055 | S68: 712.9233 | T68: 10062.83 | U68: 12855.18 | V68: 11429.746 | W68: 5390.9029 | X68: 33549.847 | Y68: 69648.684 | Z68: 132969.3 | AA68: 0 | AB68: 0 | AC68: 0 | AD68: 3689.5499 | AE68: 15818.074 | AF68: 0 | AG68: 7952.4889 | AH68: 15325.818 | AI68: 0 | AJ68: 32725.15 | AK68: 0 | AL68: 8335.0815 | AM68: 0 | AN68: 43332.54 | AO68: 68477.561 | AP68: 1641.156 | AQ68: 34197.255 | AR68: 31620.58 | AS68: 72189.17 | AT68: 3279.2077 | AU68: 38070.61 | AV68: 62935.669 | AW68: 1305.6334 | AX68: 761.23 | AY68: 83210.783 | AZ68: 76422.488
A69: Selection Thin Commision | B69: 0 | C69: 0 | D69: 0 | E69: 0 | F69: 0 | G69: 0 | H69: 0 | I69: 0 | J69: 0 | K69: 0 | L69: 0 | M69: 0 | N69: 0 | O69: 0 | P69: 0 | Q69: 0 | R69: 0 | S69: 0 | T69: 0 | U69: 0 | V69: 0 | W69: 0 | X69: 0 | Y69: 0 | Z69: 0 | AA69: 0 | AB69: 0 | AC69: 0 | AD69: 0 | AE69: 0 | AF69: 0 | AG69: 0 | AH69: 0 | AI69: 0 | AJ69: 0 | AK69: 0 | AL69: 0 | AM69: 0 | AN69: 0 | AO69: 0 | AP69: 0 | AQ69: 0 | AR69: 0 | AS69: 0 | AT69: 0 | AU69: 0 | AV69: 0 | AW69: 0 | AX69: 0 | AY69: 0 | AZ69: 0
A70: Hunt Lease Commission | B70: 0 | C70: 12091.049 | D70: 12091.051 | E70: 12091.053 | F70: 12091.056 | G70: 12091.058 | H70: 12091.061 | I70: 12091.063 | J70: 12091.066 | K70: 12091.068 | L70: 12091.07 | M70: 12091.073 | N70: 12091.075 | O70: 12091.078 | P70: 12091.08 | Q70: 12091.083 | R70: 12091.085 | S70: 12091.087 | T70: 12091.09 | U70: 12091.092 | V70: 12091.095 | W70: 12091.097 | X70: 12091.1 | Y70: 12091.102 | Z70: 12091.104 | AA70: 12091.107 | AB70: 12091.109 | AC70: 12091.112 | AD70: 12091.114 | AE70: 12091.116 | AF70: 12091.119 | AG70: 12091.121 | AH70: 12091.124 | AI70: 12091.126 | AJ70: 12091.129 | AK70: 12091.131 | AL70: 12091.133 | AM70: 12091.136 | AN70: 12091.138 | AO70: 12091.141 | AP70: 12091.143 | AQ70: 12091.145 | AR70: 12091.148 | AS70: 12091.15 | AT70: 12091.153 | AU70: 12091.155 | AV70: 12091.157 | AW70: 12091.16 | AX70: 12091.162 | AY70: 12091.165 | AZ70: 12091.167
A72: Cash Flow | B72: 0 | C72: 541997.02 | D72: -167861.27 | E72: 593409.61 | F72: 31155.957 | G72: 120927.84 | H72: -30935.764 | I72: 877965.42 | J72: 1201625.8 | K72: 251678.08 | L72: 695887.96 | M72: 812593.66 | N72: 2201510.7 | O72: 277.2158 | P72: 1379423.5 | Q72: 1701284.6 | R72: 328825.3 | S72: -62004.147 | T72: 264539.82 | U72: 681874.62 | V72: 208109.24 | W72: 134153.15 | X72: 982147.61 | Y72: 2462341.5 | Z72: 4523486.6 | AA72: -235036.96 | AB72: -10522.633 | AC72: 87912.939 | AD72: 395626.63 | AE72: 424736.77 | AF72: 399441.36 | AG72: 1158431.3 | AH72: 322104.81 | AI72: 119830.97 | AJ72: 1230924.3 | AK72: 273235.46 | AL72: 85483.361 | AM72: 59486.345 | AN72: 1901804.4 | AO72: 2175586.3 | AP72: 203526.21 | AQ72: 902904.74 | AR72: 1017213.3 | AS72: 2192602 | AT72: -65922.9 | AU72: 1334185.4 | AV72: 1844321.7 | AW72: -155792.83 | AX72: -79297.708 | AY72: 2629184.4 | AZ72: 2548944.1
A73: Discounted Cash Flow | B73: 0 | C73: 516187.64 | D73: -152255.12 | E73: 512609.54 | F73: 25632.083 | G73: 94750.131 | H73: -23084.743 | I73: 623953.63 | J73: 813307.65 | K73: 162233.93 | L73: 427214.83 | M73: 475106.7 | N73: 1225883.6 | O73: 147.0135 | P73: 696702.57 | Q73: 818347.01 | R73: 150638.66 | S73: -27052.205 | T73: 109921.76 | U73: 269840.94 | V73: 78434.187 | W73: 48153.248 | X73: 335747.03 | Y73: 801667.72 | Z73: 1402588.1 | AA73: -69407.068 | AB73: -2959.3931 | AC73: 23547.332 | AD73: 100921.83 | AE73: 103188.24 | AF73: 92421.725 | AG73: 255271.31 | AH73: 67598.901 | AI73: 23950.92 | AJ73: 234312.33 | AK73: 49534.933 | AL73: 14759.336 | AM73: 9781.6752 | AN73: 297832.77 | AO73: 324484.29 | AP73: 28910.019 | AQ73: 122146.4 | AR73: 131057.39 | AS73: 269041.92 | AT73: -7703.8382 | AU73: 148490.18 | AV73: 195491.97 | AW73: -15727.163 | AX73: -7623.8487 | AY73: 240738.41 | AZ73: 222277.42
A75: Total Standing Inventory PV | B75: 7596555.8 | C75: 7421732.1 | D75: 7934579.9 | E75: 7702678 | F75: 7900050.7 | G75: 8393176.6 | H75: 9315484.4 | I75: 9028409 | J75: 8346399.4 | K75: 8260544.3 | L75: 7866029.4 | M75: 7568223.1 | N75: 6487713.6 | O75: 6847639.1 | P75: 6205304.7 | Q75: 5485405.2 | R75: 5474707.7 | S75: 5538762.7 | T75: 5520878.7 | U75: 5311114.3 | V75: 5368950.9 | W75: 5638393.1 | X75: 5311366.7 | Y75: 4567212.7 | Z75: 3054110.5 | AA75: 3165996.9 | AB75: 3135771.4 | AC75: 3167084.8 | AD75: 3312506.1 | AE75: 3231210.7 | AF75: 3162825.8 | AG75: 2911236.5 | AH75: 2873248.1 | AI75: 2877921.5 | AJ75: 2647465.9 | AK75: 2629956.6 | AL75: 2659581.7 | AM75: 2746962.9 | AN75: 2470849.1 | AO75: 2140811.1 | AP75: 2117542.3 | AQ75: 1985709.7 | AR75: 1873918.7 | AS75: 1570577.4 | AT75: 1555735.3 | AU75: 1376135.9 | AV75: 1140872.8 | AW75: 1168299.5 | AX75: 1163403.5 | AY75: 891316.46 | AZ75: 612842.01
A76: Total PreMerch Value | B76: 2747624.7 | C76: 2319821.7 | D76: 2206514.6 | E76: 2493872.6 | F76: 2647584.5 | G76: 2470092.3 | H76: 1631790.9 | I76: 1673880.3 | J76: 1851506.2 | K76: 1742006.7 | L76: 1444455.1 | M76: 1101469.6 | N76: 1384402.4 | O76: 1250693.4 | P76: 1272354.5 | Q76: 1402846.8 | R76: 1198923.4 | S76: 1409082.5 | T76: 1415566.9 | U76: 1563831 | V76: 1366496.8 | W76: 1083500.4 | X76: 1213047.9 | Y76: 1114666.6 | Z76: 1079193.9 | AA76: 677244.94 | AB76: 864095.79 | AC76: 694499.6 | AD76: 507692.91 | AE76: 556493.55 | AF76: 600845.45 | AG76: 624097.12 | AH76: 616872.67 | AI76: 613219.44 | AJ76: 703525.36 | AK76: 671457.88 | AL76: 473182.15 | AM76: 117053.46 | AN76: 160748.37 | AO76: 178614.26 | AP76: 199422.31 | AQ76: 252817.08 | AR76: 225636.27 | AS76: 286236.83 | AT76: 266439.55 | AU76: 280806.03 | AV76: 309605.26 | AW76: 262656.7 | AX76: 308810.12 | AY76: 340700.72 | AZ76: 371559.92
A77: Bare Land PV | B77: 18654503 | C77: 17766197 | D77: 16920191 | E77: 16114471 | F77: 15347118 | G77: 14616306 | H77: 13920294 | I77: 13257426 | J77: 12626122 | K77: 12024881 | L77: 11452269 | M77: 10906926 | N77: 10387551 | O77: 9892907.3 | P77: 9421818.1 | Q77: 8973162.3 | R77: 8545870.3 | S77: 8138926 | T77: 7751359.6 | U77: 7382248.4 | V77: 7030714.5 | W77: 6695919.6 | X77: 6377067.5 | Y77: 6073398.8 | Z77: 5784190.9 | AA77: 5508754.2 | AB77: 5246433.5 | AC77: 4996604.2 | AD77: 4758671.7 | AE77: 4532069.4 | AF77: 4316257.4 | AG77: 4110722 | AH77: 3914974.2 | AI77: 3728547.5 | AJ77: 3550998.3 | AK77: 3381903.9 | AL77: 3220861.5 | AM77: 3067487.9 | AN77: 2921417.5 | AO77: 2782303.1 | AP77: 2649812.8 | AQ77: 2523631.9 | AR77: 2403459.4 | AS77: 2289009.4 | AT77: 2180009.4 | AU77: 2076199.8 | AV77: 1977333.5 | AW77: 1883175.1 | AX77: 1793500.5 | AY77: 1708096 | AZ77: 1626758.5
A79: Sum of DCF
A80: Initital inventory Value | B80: =B75 -> 7596555.8
A81: Initial Premerch Value | B81: =B76 -> 2747624.7
A82: Initital BLV | B82: =B77 -> 18654503
A83: Total initial Value | B83: =SUM(B80:B82) -> 28998684
A85: Sum of DCF
A86: 50-Year DCF | B86: =SUM(C73:AZ73) -> 12239014
A87: Total NPV per acre | B87: =B86/$B$9 -> 986.62816
A89: Enter # of years for Reversion Calculation ---> | B89: 50
A91: =CONCATENATE(B89,"-Year DCF") -> 50-Year DCF | B91: =SUMIF(C98:AZ98,B89,C73:AZ73) -> 12239014
A92: =CONCATENATE("Discounted Standing Inventory Value, at ",B89," years") -> Discounted Standing Inventory Value, at 50 years | B92: =LOOKUP(B89,C99:AZ99,C75:AZ75) -> 612842.01
A93: =CONCATENATE("Discounted Premerch Value, at ",B89," years") -> Discounted Premerch Value, at 50 years | B93: =LOOKUP(B89,C99:AZ99,C76:AZ76) -> 371559.92
A94: =CONCATENATE("Discounted Bareland Value, at ",B89," years") -> Discounted Bareland Value, at 50 years | B94: =LOOKUP(B89,C99:AZ99,C77:AZ77) -> 1626758.5
A95: =CONCATENATE(B89,"-Year NPV") -> 50-Year NPV | B95: =SUM(B91:B94) -> 14850174
A96: =CONCATENATE(B89,"-Year NPV per acre") -> 50-Year NPV per acre | B96: =B95/B9 -> 1197.1226
B98: 0 | C98: =IF(C99<=$B$89,$B$89,0) -> 50 | D98: =IF(D99<=$B$89,$B$89,0) -> 50 | E98: =IF(E99<=$B$89,$B$89,0) -> 50 | F98: =IF(F99<=$B$89,$B$89,0) -> 50 | G98: =IF(G99<=$B$89,$B$89,0) -> 50 | H98: =IF(H99<=$B$89,$B$89,0) -> 50 | I98: =IF(I99<=$B$89,$B$89,0) -> 50 | J98: =IF(J99<=$B$89,$B$89,0) -> 50 | ... AZ98: =IF(AZ99<=$B$89,$B$89,0) -> 50
B99: 0 | C99: 1 | D99: 2 | E99: 3 | F99: 4 | G99: 5 | H99: 6 | I99: 7 | J99: 8 | K99: 9 | L99: 10 | M99: 11 | N99: 12 | O99: 13 | P99: 14 | Q99: 15 | R99: 16 | S99: 17 | T99: 18 | U99: 19 | V99: 20 | W99: 21 | X99: 22 | Y99: 23 | Z99: 24 | AA99: 25 | AB99: 26 | AC99: 27 | AD99: 28 | AE99: 29 | AF99: 30 | AG99: 31 | AH99: 32 | AI99: 33 | AJ99: 34 | AK99: 35 | AL99: 36 | AM99: 37 | AN99: 38 | AO99: 39 | AP99: 40 | AQ99: 41 | AR99: 42 | AS99: 43 | AT99: 44 | AU99: 45 | AV99: 46 | AW99: 47 | AX99: 48 | AY99: 49 | AZ99: 50

Sheet Output Graphs
A1: DISCOUNTED CASH FLOW ANALYSIS
A2: Output Graphs
A3: =CONCATENATE('Model Assumptions'!B2, " - ",'Model Assumptions'!B3 ) -> IWC - Boot Hill
A4: ='Model Assumptions'!B5 -> IWC - Boothill - HSM

Sheet Finance Per Unit
A1: DISCOUNTED CASH FLOW ANALYSIS
A2: Finance Per Unit
A3: =CONCATENATE('Model Assumptions'!B2, " - ",'Model Assumptions'!B3 ) -> IWC - Boot Hill
A4: ='Model Assumptions'!B5 -> IWC - Boothill - HSM
A6: Calendar Year >> | B6: ='Finance Report'!B6 -> Model Year 0 | C6: 2026 | D6: =C6+1 -> 2027 | E6: =D6+1 -> 2028 | F6: =E6+1 -> 2029 | G6: =F6+1 -> 2030 | H6: =G6+1 -> 2031 | I6: =H6+1 -> 2032 | J6: =I6+1 -> 2033 | K6: =J6+1 -> 2034 | ... AZ6: =AY6+1 -> 2075
A7: Model Discount Period >> | B7: 0 | C7: 1 | D7: =C7+1 -> 2 | E7: =D7+1 -> 3 | F7: =E7+1 -> 4 | G7: =F7+1 -> 5 | H7: =G7+1 -> 6 | I7: =H7+1 -> 7 | J7: =I7+1 -> 8 | K7: =J7+1 -> 9 | ... AZ7: =AY7+1 -> 50
A9: Total Acres | B9: 12404.89 | C9: 12404.89 | D9: 12404.89 | E9: 12404.89 | F9: 12404.89 | G9: 12404.89 | H9: 12404.89 | I9: 12404.89 | J9: 12404.89 | K9: 12404.89 | L9: 12404.89 | M9: 12404.89 | N9: 12404.89 | O9: 12404.89 | P9: 12404.89 | Q9: 12404.89 | R9: 12404.89 | S9: 12404.89 | T9: 12404.89 | U9: 12404.89 | V9: 12404.89 | W9: 12404.89 | X9: 12404.89 | Y9: 12404.89 | Z9: 12404.89 | AA9: 12404.89 | AB9: 12404.89 | AC9: 12404.89 | AD9: 12404.89 | AE9: 12404.89 | AF9: 12404.89 | AG9: 12404.89 | AH9: 12404.89 | AI9: 12404.89 | AJ9: 12404.89 | AK9: 12404.89 | AL9: 12404.89 | AM9: 12404.89 | AN9: 12404.89 | AO9: 12404.89 | AP9: 12404.89 | AQ9: 12404.89 | AR9: 12404.89 | AS9: 12404.89 | AT9: 12404.89 | AU9: 12404.89 | AV9: 12404.89 | AW9: 12404.89 | AX9: 12404.89 | AY9: 12404.89 | AZ9: 12404.89
A10: Productive Plantation Acres | B10: 8762.98 | C10: 8762.98 | D10: 8762.98 | E10: 8762.98 | F10: 8762.98 | G10: 8762.98 | H10: 8762.98 | I10: 8762.98 | J10: 8762.98 | K10: 8762.98 | L10: 8762.98 | M10: 8762.98 | N10: 8762.98 | O10: 8762.98 | P10: 8762.98 | Q10: 8762.98 | R10: 8762.98 | S10: 8762.98 | T10: 8762.98 | U10: 8762.98 | V10: 8762.98 | W10: 8762.98 | X10: 8762.98 | Y10: 8762.98 | Z10: 8762.98 | AA10: 8762.98 | AB10: 8762.98 | AC10: 8762.98 | AD10: 8762.98 | AE10: 8762.98 | AF10: 8762.98 | AG10: 8762.98 | AH10: 8762.98 | AI10: 8762.98 | AJ10: 8762.98 | AK10: 8762.98 | AL10: 8762.98 | AM10: 8762.98 | AN10: 8762.98 | AO10: 8762.98 | AP10: 8762.98 | AQ10: 8762.98 | AR10: 8762.98 | AS10: 8762.98 | AT10: 8762.98 | AU10: 8762.98 | AV10: 8762.98 | AW10: 8762.98 | AX10: 8762.98 | AY10: 8762.98 | AZ10: 8762.98
A11: Natural Convertible Acres | B11: 611.17 | C11: 611.17 | D11: 611.17 | E11: 611.17 | F11: 611.17 | G11: 611.17 | H11: 611.17 | I11: 611.17 | J11: 611.17 | K11: 611.17 | L11: 611.17 | M11: 611.17 | N11: 611.17 | O11: 611.17 | P11: 611.17 | Q11: 611.17 | R11: 611.17 | S11: 611.17 | T11: 611.17 | U11: 611.17 | V11: 611.17 | W11: 611.17 | X11: 611.17 | Y11: 611.17 | Z11: 611.17 | AA11: 611.17 | AB11: 611.17 | AC11: 611.17 | AD11: 611.17 | AE11: 611.17 | AF11: 611.17 | AG11: 611.17 | AH11: 611.17 | AI11: 611.17 | AJ11: 611.17 | AK11: 611.17 | AL11: 611.17 | AM11: 611.17 | AN11: 611.17 | AO11: 611.17 | AP11: 611.17 | AQ11: 611.17 | AR11: 611.17 | AS11: 611.17 | AT11: 611.17 | AU11: 611.17 | AV11: 611.17 | AW11: 611.17 | AX11: 611.17 | AY11: 611.17 | AZ11: 611.17
A12: Non-Converitble Acres | B12: 3030.74 | C12: 3030.74 | D12: 3030.74 | E12: 3030.74 | F12: 3030.74 | G12: 3030.74 | H12: 3030.74 | I12: 3030.74 | J12: 3030.74 | K12: 3030.74 | L12: 3030.74 | M12: 3030.74 | N12: 3030.74 | O12: 3030.74 | P12: 3030.74 | Q12: 3030.74 | R12: 3030.74 | S12: 3030.74 | T12: 3030.74 | U12: 3030.74 | V12: 3030.74 | W12: 3030.74 | X12: 3030.74 | Y12: 3030.74 | Z12: 3030.74 | AA12: 3030.74 | AB12: 3030.74 | AC12: 3030.74 | AD12: 3030.74 | AE12: 3030.74 | AF12: 3030.74 | AG12: 3030.74 | AH12: 3030.74 | AI12: 3030.74 | AJ12: 3030.74 | AK12: 3030.74 | AL12: 3030.74 | AM12: 3030.74 | AN12: 3030.74 | AO12: 3030.74 | AP12: 3030.74 | AQ12: 3030.74 | AR12: 3030.74 | AS12: 3030.74 | AT12: 3030.74 | AU12: 3030.74 | AV12: 3030.74 | AW12: 3030.74 | AX12: 3030.74 | AY12: 3030.74 | AZ12: 3030.74
A14: Total Revenue (Per Harvest Acre)
A15: Total Removals | B15: =IF('Finance Report'!B$19=0,0,'Finance Report'!B45/'Finance Report'!B$19) -> 0 | C15: =IF('Finance Report'!C$19=0,0,'Finance Report'!C45/'Finance Report'!C$19) -> 699.61762 | D15: =IF('Finance Report'!D$19=0,0,'Finance Report'!D45/'Finance Report'!D$19) -> 252.99533 | E15: =IF('Finance Report'!E$19=0,0,'Finance Report'!E45/'Finance Report'!E$19) -> 1068.2289 | F15: =IF('Finance Report'!F$19=0,0,'Finance Report'!F45/'Finance Report'!F$19) -> 293.0384 | G15: =IF('Finance Report'!G$19=0,0,'Finance Report'!G45/'Finance Report'!G$19) -> 705.47634 | H15: =IF('Finance Report'!H$19=0,0,'Finance Report'!H45/'Finance Report'!H$19) -> 445.54502 | I15: =IF('Finance Report'!I$19=0,0,'Finance Report'!I45/'Finance Report'!I$19) -> 1575.762 | ... AZ15: =IF('Finance Report'!AZ$19=0,0,'Finance Report'!AZ45/'Finance Report'!AZ$19) -> 1292.7745
A16: Clearcut Revenue | B16: =IF('Finance Report'!B$46=0,0,'Finance Report'!B46/'Harvest Report'!B$55) -> 0 | C16: =IF('Finance Report'!C$46=0,0,'Finance Report'!C46/'Harvest Report'!C$55) -> 1393.3608 | D16: =IF('Finance Report'!D$46=0,0,'Finance Report'!D46/'Harvest Report'!D$55) -> 0 | E16: =IF('Finance Report'!E$46=0,0,'Finance Report'!E46/'Harvest Report'!E$55) -> 1465.8964 | F16: =IF('Finance Report'!F$46=0,0,'Finance Report'!F46/'Harvest Report'!F$55) -> 0 | G16: =IF('Finance Report'!G$46=0,0,'Finance Report'!G46/'Harvest Report'!G$55) -> 1210.6134 | H16: =IF('Finance Report'!H$46=0,0,'Finance Report'!H46/'Harvest Report'!H$55) -> 0 | I16: =IF('Finance Report'!I$46=0,0,'Finance Report'!I46/'Harvest Report'!I$55) -> 1741.9948 | ... AZ16: =IF('Finance Report'!AZ$46=0,0,'Finance Report'!AZ46/'Harvest Report'!AZ$55) -> 1698.2775
A17: First Thin Revenue | B17: =IF('Finance Report'!B$47=0,0,'Finance Report'!B47/'Harvest Report'!B$77) -> 0 | C17: =IF('Finance Report'!C$47=0,0,'Finance Report'!C47/'Harvest Report'!C$77) -> 218.74458 | D17: =IF('Finance Report'!D$47=0,0,'Finance Report'!D47/'Harvest Report'!D$77) -> 252.99533 | E17: =IF('Finance Report'!E$47=0,0,'Finance Report'!E47/'Harvest Report'!E$77) -> 233.32858 | F17: =IF('Finance Report'!F$47=0,0,'Finance Report'!F47/'Harvest Report'!F$77) -> 200.41521 | G17: =IF('Finance Report'!G$47=0,0,'Finance Report'!G47/'Harvest Report'!G$77) -> 169.95897 | H17: =IF('Finance Report'!H$47=0,0,'Finance Report'!H47/'Harvest Report'!H$77) -> 0 | I17: =IF('Finance Report'!I$47=0,0,'Finance Report'!I47/'Harvest Report'!I$77) -> 0 | ... AZ17: =IF('Finance Report'!AZ$47=0,0,'Finance Report'!AZ47/'Harvest Report'!AZ$77) -> 437.43083
A18: Second Thin Revenue | B18: =IF('Finance Report'!B$48=0,0,'Finance Report'!B48/'Harvest Report'!B$86) -> 0 | C18: =IF('Finance Report'!C$48=0,0,'Finance Report'!C48/'Harvest Report'!C$86) -> 0 | D18: =IF('Finance Report'!D$48=0,0,'Finance Report'!D48/'Harvest Report'!D$86) -> 0 | E18: =IF('Finance Report'!E$48=0,0,'Finance Report'!E48/'Harvest Report'!E$86) -> 395.75409 | F18: =IF('Finance Report'!F$48=0,0,'Finance Report'!F48/'Harvest Report'!F$86) -> 566.21496 | G18: =IF('Finance Report'!G$48=0,0,'Finance Report'!G48/'Harvest Report'!G$86) -> 678.41821 | H18: =IF('Finance Report'!H$48=0,0,'Finance Report'!H48/'Harvest Report'!H$86) -> 445.54502 | I18: =IF('Finance Report'!I$48=0,0,'Finance Report'!I48/'Harvest Report'!I$86) -> 467.40188 | ... AZ18: =IF('Finance Report'!AZ$48=0,0,'Finance Report'!AZ48/'Harvest Report'!AZ$86) -> 474.19402
A19: Selection Thin Revenue | B19: =IF('Finance Report'!B$49=0,0,'Finance Report'!B49/'Harvest Report'!B$107) -> 0 | C19: =IF('Finance Report'!C$49=0,0,'Finance Report'!C49/'Harvest Report'!C$107) -> 0 | D19: =IF('Finance Report'!D$49=0,0,'Finance Report'!D49/'Harvest Report'!D$107) -> 0 | E19: =IF('Finance Report'!E$49=0,0,'Finance Report'!E49/'Harvest Report'!E$107) -> 0 | F19: =IF('Finance Report'!F$49=0,0,'Finance Report'!F49/'Harvest Report'!F$107) -> 0 | G19: =IF('Finance Report'!G$49=0,0,'Finance Report'!G49/'Harvest Report'!G$107) -> 0 | H19: =IF('Finance Report'!H$49=0,0,'Finance Report'!H49/'Harvest Report'!H$107) -> 0 | I19: =IF('Finance Report'!I$49=0,0,'Finance Report'!I49/'Harvest Report'!I$107) -> 0 | ... AZ19: =IF('Finance Report'!AZ$49=0,0,'Finance Report'!AZ49/'Harvest Report'!AZ$107) -> 0
A20: Hunt Lease (Per Acre) | B20: ='Finance Report'!B50/'Finance Report'!B$9 -> 0 | C20: ='Finance Report'!C50/'Finance Report'!C$9 -> 10.830002 | D20: ='Finance Report'!D50/'Finance Report'!D$9 -> 10.830004 | E20: ='Finance Report'!E50/'Finance Report'!E$9 -> 10.830006 | F20: ='Finance Report'!F50/'Finance Report'!F$9 -> 10.830009 | G20: ='Finance Report'!G50/'Finance Report'!G$9 -> 10.830011 | H20: ='Finance Report'!H50/'Finance Report'!H$9 -> 10.830013 | I20: ='Finance Report'!I50/'Finance Report'!I$9 -> 10.830015 | ... AZ20: ='Finance Report'!AZ50/'Finance Report'!AZ$9 -> 10.830108
A21: Miscellanous Revenue (Per Acre) | B21: ='Finance Report'!B51/'Finance Report'!B$9 -> 0 | C21: ='Finance Report'!C51/'Finance Report'!C$9 -> 0 | D21: ='Finance Report'!D51/'Finance Report'!D$9 -> 0 | E21: ='Finance Report'!E51/'Finance Report'!E$9 -> 0 | F21: ='Finance Report'!F51/'Finance Report'!F$9 -> 0 | G21: ='Finance Report'!G51/'Finance Report'!G$9 -> 0 | H21: ='Finance Report'!H51/'Finance Report'!H$9 -> 0 | I21: ='Finance Report'!I51/'Finance Report'!I$9 -> 0 | ... AZ21: ='Finance Report'!AZ51/'Finance Report'!AZ$9 -> 0
A23: Total Costs
A24: Overhead - Fixed
A25: Lease Fees | B25: ='Finance Report'!B55/'Finance Report'!B$9 -> 0 | C25: ='Finance Report'!C55/'Finance Report'!C$9 -> #VALUE! | D25: ='Finance Report'!D55/'Finance Report'!D$9 -> 0 | E25: ='Finance Report'!E55/'Finance Report'!E$9 -> 0 | F25: ='Finance Report'!F55/'Finance Report'!F$9 -> 0 | G25: ='Finance Report'!G55/'Finance Report'!G$9 -> 0 | H25: ='Finance Report'!H55/'Finance Report'!H$9 -> 0 | I25: ='Finance Report'!I55/'Finance Report'!I$9 -> 0 | ... AZ25: ='Finance Report'!AZ55/'Finance Report'!AZ$9 -> 0
A26: Management | B26: ='Finance Report'!B56/'Finance Report'!B$9 -> 0 | C26: ='Finance Report'!C56/'Finance Report'!C$9 -> 8.0000016 | D26: ='Finance Report'!D56/'Finance Report'!D$9 -> 8.0000032 | E26: ='Finance Report'!E56/'Finance Report'!E$9 -> 8.0000048 | F26: ='Finance Report'!F56/'Finance Report'!F$9 -> 8.0000064 | G26: ='Finance Report'!G56/'Finance Report'!G$9 -> 8.000008 | H26: ='Finance Report'!H56/'Finance Report'!H$9 -> 8.0000096 | I26: ='Finance Report'!I56/'Finance Report'!I$9 -> 8.0000112 | ... AZ26: ='Finance Report'!AZ56/'Finance Report'!AZ$9 -> 8.00008
A27: Taxes | B27: ='Finance Report'!B57/'Finance Report'!B$9 -> 0 | C27: ='Finance Report'!C57/'Finance Report'!C$9 -> 2.5100005 | D27: ='Finance Report'!D57/'Finance Report'!D$9 -> 2.510001 | E27: ='Finance Report'!E57/'Finance Report'!E$9 -> 2.5100015 | F27: ='Finance Report'!F57/'Finance Report'!F$9 -> 2.510002 | G27: ='Finance Report'!G57/'Finance Report'!G$9 -> 2.5100025 | H27: ='Finance Report'!H57/'Finance Report'!H$9 -> 2.510003 | I27: ='Finance Report'!I57/'Finance Report'!I$9 -> 2.5100035 | ... AZ27: ='Finance Report'!AZ57/'Finance Report'!AZ$9 -> 2.5100251
A28: Roads | B28: ='Finance Report'!B58/'Finance Report'!B$9 -> 0 | C28: ='Finance Report'!C58/'Finance Report'!C$9 -> 3.5000007 | D28: ='Finance Report'!D58/'Finance Report'!D$9 -> 3.5000014 | E28: ='Finance Report'!E58/'Finance Report'!E$9 -> 3.5000021 | F28: ='Finance Report'!F58/'Finance Report'!F$9 -> 3.5000028 | G28: ='Finance Report'!G58/'Finance Report'!G$9 -> 3.5000035 | H28: ='Finance Report'!H58/'Finance Report'!H$9 -> 3.5000042 | I28: ='Finance Report'!I58/'Finance Report'!I$9 -> 3.5000049 | ... AZ28: ='Finance Report'!AZ58/'Finance Report'!AZ$9 -> 3.500035
A29: Misc. | B29: ='Finance Report'!B59/'Finance Report'!B$9 -> 0 | C29: ='Finance Report'!C59/'Finance Report'!C$9 -> 0.35000007 | D29: ='Finance Report'!D59/'Finance Report'!D$9 -> 0.35000014 | E29: ='Finance Report'!E59/'Finance Report'!E$9 -> 0.35000021 | F29: ='Finance Report'!F59/'Finance Report'!F$9 -> 0.35000028 | G29: ='Finance Report'!G59/'Finance Report'!G$9 -> 0.35000035 | H29: ='Finance Report'!H59/'Finance Report'!H$9 -> 0.35000042 | I29: ='Finance Report'!I59/'Finance Report'!I$9 -> 0.35000049 | ... AZ29: ='Finance Report'!AZ59/'Finance Report'!AZ$9 -> 0.3500035
A30: Silviculture
A31: SitePrep | B31: =IF('Activity Report'!B25=0,0,'Finance Report'!B61/'Activity Report'!B25) -> 0 | C31: =IF('Activity Report'!C25=0,0,'Finance Report'!C61/'Activity Report'!C25) -> 122.50002 | D31: =IF('Activity Report'!D25=0,0,'Finance Report'!D61/'Activity Report'!D25) -> 122.50005 | E31: =IF('Activity Report'!E25=0,0,'Finance Report'!E61/'Activity Report'!E25) -> 0 | F31: =IF('Activity Report'!F25=0,0,'Finance Report'!F61/'Activity Report'!F25) -> 122.5001 | G31: =IF('Activity Report'!G25=0,0,'Finance Report'!G61/'Activity Report'!G25) -> 0 | H31: =IF('Activity Report'!H25=0,0,'Finance Report'!H61/'Activity Report'!H25) -> 122.50015 | I31: =IF('Activity Report'!I25=0,0,'Finance Report'!I61/'Activity Report'!I25) -> 0 | ... AZ31: =IF('Activity Report'!AZ25=0,0,'Finance Report'!AZ61/'Activity Report'!AZ25) -> 122.50122
A32: Planting | B32: =IF('Activity Report'!B26=0,0,'Finance Report'!B62/'Activity Report'!B26) -> 0 | C32: =IF('Activity Report'!C26=0,0,'Finance Report'!C62/'Activity Report'!C26) -> 0 | D32: =IF('Activity Report'!D26=0,0,'Finance Report'!D62/'Activity Report'!D26) -> 120.40005 | E32: =IF('Activity Report'!E26=0,0,'Finance Report'!E62/'Activity Report'!E26) -> 120.40007 | F32: =IF('Activity Report'!F26=0,0,'Finance Report'!F62/'Activity Report'!F26) -> 0 | G32: =IF('Activity Report'!G26=0,0,'Finance Report'!G62/'Activity Report'!G26) -> 120.40012 | H32: =IF('Activity Report'!H26=0,0,'Finance Report'!H62/'Activity Report'!H26) -> 0 | I32: =IF('Activity Report'!I26=0,0,'Finance Report'!I62/'Activity Report'!I26) -> 120.40017 | ... AZ32: =IF('Activity Report'!AZ26=0,0,'Finance Report'!AZ62/'Activity Report'!AZ26) -> 120.40121
A33: Herb Weed Control | B33: =IF('Activity Report'!B27=0,0,'Finance Report'!B63/'Activity Report'!B27) -> 0 | C33: =IF('Activity Report'!C27=0,0,'Finance Report'!C63/'Activity Report'!C27) -> 0 | D33: =IF('Activity Report'!D27=0,0,'Finance Report'!D63/'Activity Report'!D27) -> 44.270009 | E33: =IF('Activity Report'!E27=0,0,'Finance Report'!E63/'Activity Report'!E27) -> 44.270013 | F33: =IF('Activity Report'!F27=0,0,'Finance Report'!F63/'Activity Report'!F27) -> 0 | G33: =IF('Activity Report'!G27=0,0,'Finance Report'!G63/'Activity Report'!G27) -> 44.270022 | H33: =IF('Activity Report'!H27=0,0,'Finance Report'!H63/'Activity Report'!H27) -> 0 | I33: =IF('Activity Report'!I27=0,0,'Finance Report'!I63/'Activity Report'!I27) -> 44.270031 | ... AZ33: =IF('Activity Report'!AZ27=0,0,'Finance Report'!AZ63/'Activity Report'!AZ27) -> 44.270226
A34: Fertilizer | B34: =IF('Activity Report'!B32=0,0,'Finance Report'!B64/'Activity Report'!B32) -> 0 | C34: =IF('Activity Report'!C32=0,0,'Finance Report'!C64/'Activity Report'!C32) -> 0 | D34: =IF('Activity Report'!D32=0,0,'Finance Report'!D64/'Activity Report'!D32) -> 160.00003 | E34: =IF('Activity Report'!E32=0,0,'Finance Report'!E64/'Activity Report'!E32) -> 160.00005 | F34: =IF('Activity Report'!F32=0,0,'Finance Report'!F64/'Activity Report'!F32) -> 150.00006 | G34: =IF('Activity Report'!G32=0,0,'Finance Report'!G64/'Activity Report'!G32) -> 154.15106 | H34: =IF('Activity Report'!H32=0,0,'Finance Report'!H64/'Activity Report'!H32) -> 150.00009 | I34: =IF('Activity Report'!I32=0,0,'Finance Report'!I64/'Activity Report'!I32) -> 150.00011 | ... AZ34: =IF('Activity Report'!AZ32=0,0,'Finance Report'!AZ64/'Activity Report'!AZ32) -> 0
A35: Production Commissions
A36: First Thin Commission | B36: =IF('Activity Report'!B18=0,0,'Finance Report'!B66/'Activity Report'!B18) -> 0 | C36: =IF('Activity Report'!C18=0,0,'Finance Report'!C66/'Activity Report'!C18) -> 6.5623372 | D36: =IF('Activity Report'!D18=0,0,'Finance Report'!D66/'Activity Report'!D18) -> 7.5898598 | E36: =IF('Activity Report'!E18=0,0,'Finance Report'!E66/'Activity Report'!E18) -> 6.9998572 | F36: =IF('Activity Report'!F18=0,0,'Finance Report'!F66/'Activity Report'!F18) -> 6.0124564 | G36: =IF('Activity Report'!G18=0,0,'Finance Report'!G66/'Activity Report'!G18) -> 5.0987692 | H36: =IF('Activity Report'!H18=0,0,'Finance Report'!H66/'Activity Report'!H18) -> 0 | I36: =IF('Activity Report'!I18=0,0,'Finance Report'!I66/'Activity Report'!I18) -> 0 | ... AZ36: =IF('Activity Report'!AZ18=0,0,'Finance Report'!AZ66/'Activity Report'!AZ18) -> 13.122925
A37: Second Thin Commission | B37: =IF('Activity Report'!B19=0,0,'Finance Report'!B67/'Activity Report'!B19) -> 0 | C37: =IF('Activity Report'!C19=0,0,'Finance Report'!C67/'Activity Report'!C19) -> 0 | D37: =IF('Activity Report'!D19=0,0,'Finance Report'!D67/'Activity Report'!D19) -> 0 | E37: =IF('Activity Report'!E19=0,0,'Finance Report'!E67/'Activity Report'!E19) -> 11.872623 | F37: =IF('Activity Report'!F19=0,0,'Finance Report'!F67/'Activity Report'!F19) -> 16.986449 | G37: =IF('Activity Report'!G19=0,0,'Finance Report'!G67/'Activity Report'!G19) -> 20.352551 | H37: =IF('Activity Report'!H19=0,0,'Finance Report'!H67/'Activity Report'!H19) -> 13.36635 | I37: =IF('Activity Report'!I19=0,0,'Finance Report'!I67/'Activity Report'!I19) -> 14.022056 | ... AZ37: =IF('Activity Report'!AZ19=0,0,'Finance Report'!AZ67/'Activity Report'!AZ19) -> 14.22582
A38: Clearcut Commision | B38: =IF('Activity Report'!B15=0,0,'Finance Report'!B68/'Activity Report'!B15) -> 0 | C38: =IF('Activity Report'!C15=0,0,'Finance Report'!C68/'Activity Report'!C15) -> 41.800825 | D38: =IF('Activity Report'!D15=0,0,'Finance Report'!D68/'Activity Report'!D15) -> 0 | E38: =IF('Activity Report'!E15=0,0,'Finance Report'!E68/'Activity Report'!E15) -> 43.976892 | F38: =IF('Activity Report'!F15=0,0,'Finance Report'!F68/'Activity Report'!F15) -> 0 | G38: =IF('Activity Report'!G15=0,0,'Finance Report'!G68/'Activity Report'!G15) -> 36.318401 | H38: =IF('Activity Report'!H15=0,0,'Finance Report'!H68/'Activity Report'!H15) -> 0 | I38: =IF('Activity Report'!I15=0,0,'Finance Report'!I68/'Activity Report'!I15) -> 52.259845 | ... AZ38: =IF('Activity Report'!AZ15=0,0,'Finance Report'!AZ68/'Activity Report'!AZ15) -> 50.948326
A39: Hunt Lease Commission | B39: =IF('Activity Report'!B9=0,0,'Finance Report'!B70/'Activity Report'!B9) -> 0 | C39: =IF('Activity Report'!C9=0,0,'Finance Report'!C70/'Activity Report'!C9) -> 0.97470019 | D39: =IF('Activity Report'!D9=0,0,'Finance Report'!D70/'Activity Report'!D9) -> 0.97470039 | E39: =IF('Activity Report'!E9=0,0,'Finance Report'!E70/'Activity Report'!E9) -> 0.97470058 | F39: =IF('Activity Report'!F9=0,0,'Finance Report'!F70/'Activity Report'!F9) -> 0.97470078 | G39: =IF('Activity Report'!G9=0,0,'Finance Report'!G70/'Activity Report'!G9) -> 0.97470098 | H39: =IF('Activity Report'!H9=0,0,'Finance Report'!H70/'Activity Report'!H9) -> 0.97470117 | I39: =IF('Activity Report'!I9=0,0,'Finance Report'!I70/'Activity Report'!I9) -> 0.97470136 | ... AZ39: =IF('Activity Report'!AZ9=0,0,'Finance Report'!AZ70/'Activity Report'!AZ9) -> 0.97470975

Sheet Harvest Report
A1: DISCOUNTED CASH FLOW ANALYSIS
A2: Harvest Report
A3: =CONCATENATE('Model Assumptions'!B2, " - ",'Model Assumptions'!B3 ) -> IWC - Boot Hill
A4: ='Model Assumptions'!B5 -> IWC - Boothill - HSM
A6: Calendar Year >> | C6: 2026 | D6: =C6+1 -> 2027 | E6: =D6+1 -> 2028 | F6: =E6+1 -> 2029 | G6: =F6+1 -> 2030 | H6: =G6+1 -> 2031 | I6: =H6+1 -> 2032 | J6: =I6+1 -> 2033 | K6: =J6+1 -> 2034 | ... AZ6: =AY6+1 -> 2075
A7: Model Discount Period >> | B7: 0 | C7: 1 | D7: =C7+1 -> 2 | E7: =D7+1 -> 3 | F7: =E7+1 -> 4 | G7: =F7+1 -> 5 | H7: =G7+1 -> 6 | I7: =H7+1 -> 7 | J7: =I7+1 -> 8 | K7: =J7+1 -> 9 | ... AZ7: =AY7+1 -> 50
A9: Total Acres | B9: 12404.89 | C9: 12404.89 | D9: 12404.89 | E9: 12404.89 | F9: 12404.89 | G9: 12404.89 | H9: 12404.89 | I9: 12404.89 | J9: 12404.89 | K9: 12404.89 | L9: 12404.89 | M9: 12404.89 | N9: 12404.89 | O9: 12404.89 | P9: 12404.89 | Q9: 12404.89 | R9: 12404.89 | S9: 12404.89 | T9: 12404.89 | U9: 12404.89 | V9: 12404.89 | W9: 12404.89 | X9: 12404.89 | Y9: 12404.89 | Z9: 12404.89 | AA9: 12404.89 | AB9: 12404.89 | AC9: 12404.89 | AD9: 12404.89 | AE9: 12404.89 | AF9: 12404.89 | AG9: 12404.89 | AH9: 12404.89 | AI9: 12404.89 | AJ9: 12404.89 | AK9: 12404.89 | AL9: 12404.89 | AM9: 12404.89 | AN9: 12404.89 | AO9: 12404.89 | AP9: 12404.89 | AQ9: 12404.89 | AR9: 12404.89 | AS9: 12404.89 | AT9: 12404.89 | AU9: 12404.89 | AV9: 12404.89 | AW9: 12404.89 | AX9: 12404.89 | AY9: 12404.89 | AZ9: 12404.89
A10: Productive Plantation Acres | B10: 8762.98 | C10: 8762.98 | D10: 8762.98 | E10: 8762.98 | F10: 8762.98 | G10: 8762.98 | H10: 8762.98 | I10: 8762.98 | J10: 8762.98 | K10: 8762.98 | L10: 8762.98 | M10: 8762.98 | N10: 8762.98 | O10: 8762.98 | P10: 8762.98 | Q10: 8762.98 | R10: 8762.98 | S10: 8762.98 | T10: 8762.98 | U10: 8762.98 | V10: 8762.98 | W10: 8762.98 | X10: 8762.98 | Y10: 8762.98 | Z10: 8762.98 | AA10: 8762.98 | AB10: 8762.98 | AC10: 8762.98 | AD10: 8762.98 | AE10: 8762.98 | AF10: 8762.98 | AG10: 8762.98 | AH10: 8762.98 | AI10: 8762.98 | AJ10: 8762.98 | AK10: 8762.98 | AL10: 8762.98 | AM10: 8762.98 | AN10: 8762.98 | AO10: 8762.98 | AP10: 8762.98 | AQ10: 8762.98 | AR10: 8762.98 | AS10: 8762.98 | AT10: 8762.98 | AU10: 8762.98 | AV10: 8762.98 | AW10: 8762.98 | AX10: 8762.98 | AY10: 8762.98 | AZ10: 8762.98
A11: Natural Convertible Acres | B11: 611.17 | C11: 611.17 | D11: 611.17 | E11: 611.17 | F11: 611.17 | G11: 611.17 | H11: 611.17 | I11: 611.17 | J11: 611.17 | K11: 611.17 | L11: 611.17 | M11: 611.17 | N11: 611.17 | O11: 611.17 | P11: 611.17 | Q11: 611.17 | R11: 611.17 | S11: 611.17 | T11: 611.17 | U11: 611.17 | V11: 611.17 | W11: 611.17 | X11: 611.17 | Y11: 611.17 | Z11: 611.17 | AA11: 611.17 | AB11: 611.17 | AC11: 611.17 | AD11: 611.17 | AE11: 611.17 | AF11: 611.17 | AG11: 611.17 | AH11: 611.17 | AI11: 611.17 | AJ11: 611.17 | AK11: 611.17 | AL11: 611.17 | AM11: 611.17 | AN11: 611.17 | AO11: 611.17 | AP11: 611.17 | AQ11: 611.17 | AR11: 611.17 | AS11: 611.17 | AT11: 611.17 | AU11: 611.17 | AV11: 611.17 | AW11: 611.17 | AX11: 611.17 | AY11: 611.17 | AZ11: 611.17
A12: Non-Converitble Acres | B12: 3030.74 | C12: 3030.74 | D12: 3030.74 | E12: 3030.74 | F12: 3030.74 | G12: 3030.74 | H12: 3030.74 | I12: 3030.74 | J12: 3030.74 | K12: 3030.74 | L12: 3030.74 | M12: 3030.74 | N12: 3030.74 | O12: 3030.74 | P12: 3030.74 | Q12: 3030.74 | R12: 3030.74 | S12: 3030.74 | T12: 3030.74 | U12: 3030.74 | V12: 3030.74 | W12: 3030.74 | X12: 3030.74 | Y12: 3030.74 | Z12: 3030.74 | AA12: 3030.74 | AB12: 3030.74 | AC12: 3030.74 | AD12: 3030.74 | AE12: 3030.74 | AF12: 3030.74 | AG12: 3030.74 | AH12: 3030.74 | AI12: 3030.74 | AJ12: 3030.74 | AK12: 3030.74 | AL12: 3030.74 | AM12: 3030.74 | AN12: 3030.74 | AO12: 3030.74 | AP12: 3030.74 | AQ12: 3030.74 | AR12: 3030.74 | AS12: 3030.74 | AT12: 3030.74 | AU12: 3030.74 | AV12: 3030.74 | AW12: 3030.74 | AX12: 3030.74 | AY12: 3030.74 | AZ12: 3030.74
A14: Harvest Acres | B14: 0 | C14: 919.96 | D14: 193.34 | E14: 699.1804 | F14: 576.8 | G14: 421.71 | H14: 119.68 | I14: 645.2214 | J14: 1479.316 | K14: 817.0594 | L14: 703.2174 | M14: 459.6524 | N14: 1242.6004 | O14: 662.5206 | P14: 1338.2898 | Q14: 929.28 | R14: 809.49 | S14: 453.22 | T14: 213.74 | U14: 981.9564 | V14: 273.6928 | W14: 365.9684 | X14: 254.00407 | Y14: 1626.1983 | Z14: 2098.8264 | AA14: 251.34 | AB14: 664.15 | AC14: 345.62 | AD14: 1058.01 | AE14: 251.9736 | AF14: 1081.33 | AG14: 1402.99 | AH14: 347.19 | AI14: 215.14 | AJ14: 984.0868 | AK14: 858.55 | AL14: 412.0532 | AM14: 337.29 | AN14: 1312.085 | AO14: 1667.4954 | AP14: 1326.6564 | AQ14: 681.69 | AR14: 558.9724 | AS14: 1125.025 | AT14: 207.81 | AU14: 1193.5536 | AV14: 577.3024 | AW14: 186.6002 | AX14: 330.6838 | AY14: 1501.39 | AZ14: 2222.5636
A15: Total Harvest Volume (tons) | B15: 0 | C15: 47414.973 | D15: 4751.7809 | E15: 61308.341 | F15: 19745.034 | G15: 23397.271 | H15: 2857.348 | I15: 66441.282 | J15: 89801.794 | K15: 56532.3 | L15: 57588.441 | M15: 45747.972 | N15: 132949.63 | O15: 26330.913 | P15: 96057.543 | Q15: 81707.906 | R15: 45318.094 | S15: 16359.018 | T15: 17890.641 | U15: 53193.448 | V15: 23838.226 | W15: 13810.017 | X15: 38950.185 | Y15: 133120.2 | Z15: 238627.42 | AA15: 14458.257 | AB15: 21431.415 | AC15: 13415.615 | AD15: 42202.378 | AE15: 26087.256 | AF15: 40687.067 | AG15: 79747.543 | AH15: 27593.294 | AI15: 12223.322 | AJ15: 74817.252 | AK15: 32247.983 | AL15: 21118.63 | AM15: 9643.3586 | AN15: 102286.55 | AO15: 106829.67 | AP15: 44890.272 | AQ15: 45470.353 | AR15: 46208.697 | AS15: 111441.86 | AT15: 9743.998 | AU15: 81938.098 | AV15: 69260.061 | AW15: 5312.4927 | AX15: 7471.1763 | AY15: 133175 | AZ15: 166268.65
A16: Pine Large Saw Timber | B16: 0 | C16: 1498.1175 | D16: 0 | E16: 2964.9441 | F16: 162.81051 | G16: 332.31952 | H16: 0 | I16: 2170.11 | J16: 391.68203 | K16: 0 | L16: 0 | M16: 176.91779 | N16: 8943.018 | O16: 17.180887 | P16: 273.91626 | Q16: 214.47303 | R16: 692.74119 | S16: 264.97248 | T16: 40.363068 | U16: 2820.199 | V16: 625.60038 | W16: 14.94796 | X16: 0 | Y16: 23.949768 | Z16: 33442.975 | AA16: 100.29704 | AB16: 28.597095 | AC16: 0 | AD16: 1740.3532 | AE16: 5046.9542 | AF16: 85.851185 | AG16: 1304.0859 | AH16: 2402.3533 | AI16: 0 | AJ16: 16547.826 | AK16: 77.506328 | AL16: 961.25851 | AM16: 6.169023 | AN16: 12587.13 | AO16: 6100.3956 | AP16: 0 | AQ16: 3.992679 | AR16: 16.884585 | AS16: 9459.3367 | AT16: 0 | AU16: 1164.05 | AV16: 139.81642 | AW16: 10.319764 | AX16: 4.1222422 | AY16: 4668.9147 | AZ16: 4320.0348
A17: Tons/Acre | B17: =IF(B16=0,0,B16/B$14) -> 0 | C17: =IF(C16=0,0,C16/C$14) -> 1.6284594 | D17: =IF(D16=0,0,D16/D$14) -> 0 | E17: =IF(E16=0,0,E16/E$14) -> 4.2405996 | F17: =IF(F16=0,0,F16/F$14) -> 0.28226509 | G17: =IF(G16=0,0,G16/G$14) -> 0.78802855 | H17: =IF(H16=0,0,H16/H$14) -> 0 | I17: =IF(I16=0,0,I16/I$14) -> 3.3633571 | ... AZ17: =IF(AZ16=0,0,AZ16/AZ$14) -> 1.9437171
A18: Pine Sawtimber | B18: 0 | C18: 678.1187 | D18: 22.062283 | E18: 1187.6678 | F18: 0 | G18: 200.59973 | H18: 11.273856 | I18: 2096.4404 | J18: 1807.5501 | K18: 127.93901 | L18: 2176.8839 | M18: 6408.5779 | N18: 8890.6326 | O18: 426.09889 | P18: 7595.1671 | Q18: 18812.231 | R18: 1262.7054 | S18: 126.48941 | T18: 1919.8263 | U18: 1293.6365 | V18: 1766.8829 | W18: 2566.9074 | X18: 17001.716 | Y18: 17988.442 | Z18: 29972.563 | AA18: 0 | AB18: 0 | AC18: 0 | AD18: 0.544752 | AE18: 3168.2347 | AF18: 0 | AG18: 608.26832 | AH18: 1642.4434 | AI18: 125.28598 | AJ18: 450.63396 | AK18: 0.614592 | AL18: 31.152279 | AM18: 0 | AN18: 8787.1829 | AO18: 30561.883 | AP18: 25.055394 | AQ18: 13771.544 | AR18: 12713.628 | AS18: 12149.188 | AT18: 1263.041 | AU18: 5440.4405 | AV18: 33216.445 | AW18: 64.43744 | AX18: 104.99762 | AY18: 10153.318 | AZ18: 6077.301
A19: Tons/Acre | B19: =IF(B18=0,0,B18/B$14) -> 0 | C19: =IF(C18=0,0,C18/C$14) -> 0.73711759 | D19: =IF(D18=0,0,D18/D$14) -> 0.11411132 | E19: =IF(E18=0,0,E18/E$14) -> 1.6986571 | F19: =IF(F18=0,0,F18/F$14) -> 0 | G19: =IF(G18=0,0,G18/G$14) -> 0.47568171 | H19: =IF(H18=0,0,H18/H$14) -> 0.0942 | I19: =IF(I18=0,0,I18/I$14) -> 3.2491799 | ... AZ19: =IF(AZ18=0,0,AZ18/AZ$14) -> 2.7343654
A20: Pine Chip-n-Saw | B20: 0 | C20: 28179.922 | D20: 1552.6814 | E20: 33160.264 | F20: 7214.5042 | G20: 10315.016 | H20: 2250.1516 | I20: 45763.124 | J20: 52466.978 | K20: 19787.546 | L20: 34757.179 | M20: 28817.147 | N20: 72258.897 | O20: 4788.327 | P20: 54895.259 | Q20: 44670.597 | R20: 26582.179 | S20: 7990.6019 | T20: 11753.985 | U20: 31419.996 | V20: 15460.601 | W20: 6796.8094 | X20: 14744.306 | Y20: 77027.982 | Z20: 101794.33 | AA20: 11505.422 | AB20: 13545.431 | AC20: 5644.838 | AD20: 14807.857 | AE20: 9337.3698 | AF20: 22955.03 | AG20: 55968.524 | AH20: 14674.815 | AI20: 9906.9573 | AJ20: 30626.518 | AK20: 21967.85 | AL20: 11587.81 | AM20: 6426.1655 | AN20: 50880.775 | AO20: 31121.891 | AP20: 16409.415 | AQ20: 22461.497 | AR20: 26565.597 | AS20: 66029.675 | AT20: 5644.692 | AU20: 58413.742 | AV20: 25631.27 | AW20: 1923.8276 | AX20: 2434.8363 | AY20: 89222.802 | AZ20: 117477.55
A21: Tons/Acre | B21: =IF(B20=0,0,B20/B$14) -> 0 | C21: =IF(C20=0,0,C20/C$14) -> 30.631682 | D21: =IF(D20=0,0,D20/D$14) -> 8.030834 | E21: =IF(E20=0,0,E20/E$14) -> 47.427336 | F21: =IF(F20=0,0,F20/F$14) -> 12.507809 | G21: =IF(G20=0,0,G20/G$14) -> 24.459975 | H21: =IF(H20=0,0,H20/H$14) -> 18.8014 | I21: =IF(I20=0,0,I20/I$14) -> 70.926234 | ... AZ21: =IF(AZ20=0,0,AZ20/AZ$14) -> 52.856776
A22: Pine Pulpwood | B22: 0 | C22: 14847.122 | D22: 3177.0371 | E22: 19263.949 | F22: 12367.719 | G22: 11948.107 | H22: 595.92262 | I22: 14212.172 | J22: 34420.76 | K22: 36486.91 | L22: 20373.646 | M22: 9667.9841 | N22: 38740.781 | O22: 21050.563 | P22: 32469.605 | Q22: 17877.15 | R22: 16734.502 | S22: 7976.9542 | T22: 4004.2446 | U22: 17659.617 | V22: 5338.9829 | W22: 4417.8094 | X22: 7128.2433 | Y22: 37967.456 | Z22: 73417.55 | AA22: 2852.5374 | AB22: 7857.3871 | AC22: 7770.7774 | AD22: 25653.623 | AE22: 8534.6978 | AF22: 17646.186 | AG22: 21866.665 | AH22: 8873.6815 | AI22: 2191.0787 | AJ22: 27186.947 | AK22: 10202.012 | AL22: 8518.9879 | AM22: 3211.0241 | AN22: 29752.491 | AO22: 38955.96 | AP22: 28455.802 | AQ22: 9233.3191 | AR22: 6715.6351 | AS22: 23396.989 | AT22: 2836.265 | AU22: 16919.865 | AV22: 9831.6612 | AW22: 3281.3676 | AX22: 4914.2218 | AY22: 27437.949 | AZ22: 38393.768
A23: Tons/Acre | B23: =IF(B22=0,0,B22/B$14) -> 0 | C23: =IF(C22=0,0,C22/C$14) -> 16.138878 | D23: =IF(D22=0,0,D22/D$14) -> 16.432384 | E23: =IF(E22=0,0,E22/E$14) -> 27.552186 | F23: =IF(F22=0,0,F22/F$14) -> 21.441954 | G23: =IF(G22=0,0,G22/G$14) -> 28.332519 | H23: =IF(H22=0,0,H22/H$14) -> 4.9793 | I23: =IF(I22=0,0,I22/I$14) -> 22.026814 | ... AZ23: =IF(AZ22=0,0,AZ22/AZ$14) -> 17.274542
A24: Hardwood Sawtimber | B24: 0 | C24: 335.78893 | D24: 0 | E24: 569.44043 | F24: 0 | G24: 72.061585 | H24: 0 | I24: 252.34545 | J24: 52.68087 | K24: 9.5890075 | L24: 21.766297 | M24: 203.87142 | N24: 538.59126 | O24: 20.243075 | P24: 335.95217 | Q24: 32.964104 | R24: 2.480963 | S24: 0 | T24: 58.357762 | U24: 0 | V24: 47.936062 | W24: 0.57452828 | X24: 3.2208712 | Y24: 4.7674258 | Z24: 0 | AA24: 0 | AB24: 0 | AC24: 0 | AD24: 0 | AE24: 0 | AF24: 0 | AG24: 0 | AH24: 0 | AI24: 0 | AJ24: 0.9684287 | AK24: 0 | AL24: 3.5958789 | AM24: 0 | AN24: 19.058427 | AO24: 0 | AP24: 0 | AQ24: 0 | AR24: 14.801522 | AS24: 26.536905 | AT24: 0 | AU24: 0 | AV24: 163.21766 | AW24: 12.046995 | AX24: 4.8121867 | AY24: 646.75535 | AZ24: 0
A25: Tons/Acre | B25: =IF(B24=0,0,B24/B$14) -> 0 | C25: =IF(C24=0,0,C24/C$14) -> 0.36500383 | D25: =IF(D24=0,0,D24/D$14) -> 0 | E25: =IF(E24=0,0,E24/E$14) -> 0.81443993 | F25: =IF(F24=0,0,F24/F$14) -> 0 | G25: =IF(G24=0,0,G24/G$14) -> 0.17087948 | H25: =IF(H24=0,0,H24/H$14) -> 0 | I25: =IF(I24=0,0,I24/I$14) -> 0.39109902 | ... AZ25: =IF(AZ24=0,0,AZ24/AZ$14) -> 0
A26: Hardwood Pulpwood | B26: 0 | C26: 1875.9037 | D26: 0 | E26: 4162.076 | F26: 0 | G26: 529.16745 | H26: 0 | I26: 1947.0905 | J26: 662.14328 | K26: 120.31581 | L26: 258.96642 | M26: 473.47431 | N26: 3577.7072 | O26: 28.500461 | P26: 487.6436 | Q26: 100.49091 | R26: 43.484844 | S26: 0 | T26: 113.8638 | U26: 0 | V26: 598.2232 | W26: 12.967975 | X26: 72.69995 | Y26: 107.60803 | Z26: 0 | AA26: 0 | AB26: 0 | AC26: 0 | AD26: 0 | AE26: 0 | AF26: 0 | AG26: 0 | AH26: 0 | AI26: 0 | AJ26: 4.3585918 | AK26: 0 | AL26: 15.825895 | AM26: 0 | AN26: 259.91388 | AO26: 89.538024 | AP26: 0 | AQ26: 0 | AR26: 182.15142 | AS26: 380.13809 | AT26: 0 | AU26: 0 | AV26: 277.65106 | AW26: 20.493254 | AX26: 8.186055 | AY26: 1045.2601 | AZ26: 0
A27: Tons/Acre | B27: =IF(B26=0,0,B26/B$14) -> 0 | C27: =IF(C26=0,0,C26/C$14) -> 2.0391144 | D27: =IF(D26=0,0,D26/D$14) -> 0 | E27: =IF(E26=0,0,E26/E$14) -> 5.9527927 | F27: =IF(F26=0,0,F26/F$14) -> 0 | G27: =IF(G26=0,0,G26/G$14) -> 1.2548136 | H27: =IF(H26=0,0,H26/H$14) -> 0 | I27: =IF(I26=0,0,I26/I$14) -> 3.0177091 | ... AZ27: =IF(AZ26=0,0,AZ26/AZ$14) -> 0
A29: Clearcut Harvests
A30: Plantation Clearcut
A31: Clearcut Acres | B31: 0 | C31: 374.34 | D31: 0 | E31: 445.02 | F31: 0 | G31: 209 | H31: 0 | I31: 550.07 | J31: 676.8 | K31: 29.47 | L31: 480.87 | M31: 345.62 | N31: 955.52 | O31: 35.53 | P31: 535.99 | Q31: 570.39 | R31: 25.51 | S31: 10.19 | T31: 159.25 | U31: 206.44 | V31: 168.46 | W31: 44.42 | X31: 249.0236 | Y31: 978.2064 | Z31: 1338.7564 | AA31: 0 | AB31: 0 | AC31: 0 | AD31: 59.25 | AE31: 206.9336 | AF31: 0 | AG31: 160.58 | AH31: 321.68 | AI31: 0 | AJ31: 456.38 | AK31: 0 | AL31: 197.64 | AM31: 0 | AN31: 550.07 | AO31: 676.8 | AP31: 29.47 | AQ31: 480.87 | AR31: 345.62 | AS31: 955.52 | AT31: 35.53 | AU31: 535.99 | AV31: 570.39 | AW31: 25.51 | AX31: 10.19 | AY31: 1474.0464 | AZ31: 1500
A32: Pine Large Saw Timber | B32: 0 | C32: 1494.3755 | D32: 0 | E32: 2955.033 | F32: 0 | G32: 284.41672 | H32: 0 | I32: 2170.11 | J32: 391.68203 | K32: 0 | L32: 0 | M32: 0 | N32: 8589.7755 | O32: 0 | P32: 4.071025 | Q32: 0 | R32: 0 | S32: 0 | T32: 40.363068 | U32: 2810.4066 | V32: 625.60038 | W32: 0 | X32: 0 | Y32: 0 | Z32: 33431.298 | AA32: 0 | AB32: 0 | AC32: 0 | AD32: 1735.1599 | AE32: 5042.629 | AF32: 0 | AG32: 1256.1003 | AH32: 2402.3533 | AI32: 0 | AJ32: 16547.826 | AK32: 0 | AL32: 961.25851 | AM32: 0 | AN32: 12587.13 | AO32: 6100.3956 | AP32: 0 | AQ32: 0 | AR32: 0 | AS32: 9459.3367 | AT32: 0 | AU32: 1141.8714 | AV32: 0 | AW32: 0 | AX32: 0 | AY32: 4114.8688 | AZ32: 4315.5272
A33: Pine Saw Timber | B33: 0 | C33: 663.53996 | D33: 0 | E33: 837.76633 | F33: 0 | G33: 191.88207 | H33: 0 | I33: 1517.4807 | J33: 1629.9971 | K33: 126.5206 | L33: 2110.9039 | M33: 6408.3695 | N33: 8884.5226 | O33: 426.09889 | P33: 7186.1485 | Q33: 18212.207 | R33: 899.35563 | S33: 126.48941 | T33: 1919.8263 | U33: 1293.6365 | V33: 1732.5383 | W33: 2553.1861 | X33: 16950.946 | Y33: 17913.294 | Z33: 29972.563 | AA33: 0 | AB33: 0 | AC33: 0 | AD33: 0 | AE33: 3168.2347 | AF33: 0 | AG33: 463.4481 | AH33: 1642.4434 | AI33: 0 | AJ33: 426.61939 | AK33: 0 | AL33: 26.057472 | AM33: 0 | AN33: 8202.0522 | AO33: 30530.506 | AP33: 25.055394 | AQ33: 13771.544 | AR33: 12472.758 | AS33: 11928.06 | AT33: 1263.041 | AU33: 5440.4405 | AV33: 33216.445 | AW33: 64.43744 | AX33: 104.99762 | AY33: 10153.318 | AZ33: 6072.6358
A34: Pine Chip-N-Saw | B34: 0 | C34: 23501.219 | D34: 0 | E34: 29672.324 | F34: 0 | G34: 9512.3474 | H34: 0 | I34: 44144.97 | J34: 37922.824 | K34: 2489.5136 | L34: 30578.591 | M34: 27366.917 | N34: 70602.368 | O34: 2379.1778 | P34: 33695.148 | Q34: 32899.808 | R34: 1226.6657 | S34: 726.36945 | T34: 10410.352 | U34: 11570.18 | V34: 11725.19 | W34: 2638.8278 | X34: 14582.343 | Y34: 62325.821 | Z34: 80103.406 | AA34: 0 | AB34: 0 | AC34: 0 | AD34: 2767.2949 | AE34: 8355.2488 | AF34: 0 | AG34: 10537.282 | AH34: 14650.159 | AI34: 0 | AJ34: 18351.636 | AK34: 0 | AL34: 9699.9656 | AM34: 0 | AN34: 25829.061 | AO34: 29344.177 | AP34: 2183.2407 | AQ34: 21494.697 | AR34: 20208.606 | AS34: 62663.29 | AT34: 2227.4474 | AU34: 40925.319 | AV34: 25550.434 | AW34: 1608.8732 | AX34: 836.62656 | AY34: 88920.959 | AZ34: 99790.039
A35: Pine Pulpwood | B35: 0 | C35: 9423.1613 | D35: 0 | E35: 15605.993 | F35: 0 | G35: 6994.7122 | H35: 0 | I35: 13280.917 | J35: 15065.543 | K35: 1064.3415 | L35: 11040.171 | M35: 8660.3248 | N35: 29222.874 | O35: 794.98125 | P35: 11883.663 | Q35: 11337.778 | R35: 515.13311 | S35: 238.41994 | T35: 3621.9893 | U35: 5620.7235 | V35: 4538.0248 | W35: 1186.0096 | X35: 7027.5865 | Y35: 24448.559 | Z35: 58255.623 | AA35: 0 | AB35: 0 | AC35: 0 | AD35: 2524.9565 | AE35: 7573.2416 | AF35: 0 | AG35: 3454.1396 | AH35: 8452.119 | AI35: 0 | AJ35: 20277.314 | AK35: 0 | AL35: 3762.6304 | AM35: 0 | AN35: 18811.483 | AO35: 16168.665 | AP35: 471.64672 | AQ35: 7835.7517 | AR35: 5056.1592 | AS35: 22023.328 | AT35: 509.979 | AU35: 8802.2842 | AV35: 9714.0951 | AW35: 373.61062 | AX35: 158.3511 | AY35: 26985.179 | AZ35: 26373.389
A36: Total Pine Tons | B36: =SUM(B32:B35) -> 0 | C36: =SUM(C32:C35) -> 35082.296 | D36: =SUM(D32:D35) -> 0 | E36: =SUM(E32:E35) -> 49071.116 | F36: =SUM(F32:F35) -> 0 | G36: =SUM(G32:G35) -> 16983.358 | H36: =SUM(H32:H35) -> 0 | I36: =SUM(I32:I35) -> 61113.478 | ... AZ36: =SUM(AZ32:AZ35) -> 136551.59
A37: HW Saw Timber | B37: 0 | C37: 335.70958 | D37: 0 | E37: 548.81109 | F37: 0 | G37: 23.281821 | H37: 0 | I37: 219.64489 | J37: 28.636873 | K37: 9.026661 | L37: 21.138752 | M37: 24.951552 | N37: 120.51866 | O37: 0 | P37: 16.898765 | Q37: 16.897284 | R37: 2.480963 | S37: 0 | T37: 58.357762 | U37: 0 | V37: 45.7572 | W37: 0 | X37: 0 | Y37: 0 | Z37: 0 | AA37: 0 | AB37: 0 | AC37: 0 | AD37: 0 | AE37: 0 | AF37: 0 | AG37: 0 | AH37: 0 | AI37: 0 | AJ37: 0 | AK37: 0 | AL37: 0 | AM37: 0 | AN37: 0 | AO37: 0 | AP37: 0 | AQ37: 0 | AR37: 0 | AS37: 0 | AT37: 0 | AU37: 0 | AV37: 0 | AW37: 0 | AX37: 0 | AY37: 0 | AZ37: 0
A38: HW Pulpwood | B38: 0 | C38: 1868.5174 | D38: 0 | E38: 3921.7758 | F38: 0 | G38: 400.47946 | H38: 0 | I38: 1623.8936 | J38: 353.35193 | K38: 117.74444 | L38: 111.00713 | M38: 194.59699 | N38: 2948.0166 | O38: 0 | P38: 58.412085 | Q38: 72.682515 | R38: 43.484844 | S38: 0 | T38: 113.8638 | U38: 0 | V38: 549.04298 | W38: 0 | X38: 0 | Y38: 0 | Z38: 0 | AA38: 0 | AB38: 0 | AC38: 0 | AD38: 0 | AE38: 0 | AF38: 0 | AG38: 0 | AH38: 0 | AI38: 0 | AJ38: 0 | AK38: 0 | AL38: 0 | AM38: 0 | AN38: 0 | AO38: 0 | AP38: 0 | AQ38: 0 | AR38: 0 | AS38: 0 | AT38: 0 | AU38: 0 | AV38: 0 | AW38: 0 | AX38: 0 | AY38: 0 | AZ38: 0
A39: Total Hardwood Tons | B39: =SUM(B37:B38) -> 0 | C39: =SUM(C37:C38) -> 2204.227 | D39: =SUM(D37:D38) -> 0 | E39: =SUM(E37:E38) -> 4470.5869 | F39: =SUM(F37:F38) -> 0 | G39: =SUM(G37:G38) -> 423.76128 | H39: =SUM(H37:H38) -> 0 | I39: =SUM(I37:I38) -> 1843.5385 | ... AZ39: =SUM(AZ37:AZ38) -> 0
A40: Mean CC Age | B40: 0 | C40: 31.397339 | D40: 0 | E40: 25.484023 | F40: 0 | G40: 24.472536 | H40: 0 | I40: 25.389041 | J40: 24 | K40: 29 | L40: 26.92212 | M40: 26.60173 | N40: 28.607721 | O40: 25.674923 | P40: 27.780388 | Q40: 27.488701 | R40: 28.366915 | S40: 28.57213 | T40: 26.937834 | U40: 29 | V40: 28.763267 | W40: 27 | X40: 27.956992 | Y40: 25.610347 | Z40: 27.114697 | AA40: 0 | AB40: 0 | AC40: 0 | AD40: 29 | AE40: 27.702966 | AF40: 0 | AG40: 29 | AH40: 29 | AI40: 0 | AJ40: 28.950217 | AK40: 0 | AL40: 29 | AM40: 0 | AN40: 29 | AO40: 29 | AP40: 29 | AQ40: 29 | AR40: 29 | AS40: 29 | AT40: 29 | AU40: 29 | AV40: 29 | AW40: 29 | AX40: 29 | AY40: 25.503501 | AZ40: 24.387185
C41: =C33/C36 -> 0.018913812 | D41: =D33/D36 -> #DIV/0! | E41: =E33/E36 -> 0.017072494 | F41: =F33/F36 -> #DIV/0! | G41: =G33/G36 -> 0.01129824 | H41: =H33/H36 -> #DIV/0! | I41: =I33/I36 -> 0.02483054 | J41: =J33/J36 -> 0.029630899 | ... AZ41: =AZ33/AZ36 -> 0.044471366
A42: Natural Clearcut
A43: Clearcut Acres | B43: 0 | C43: 2.28 | D43: 0 | E43: 8.9004 | F43: 0 | G43: 4.18 | H43: 0 | I43: 11.0014 | J43: 13.536 | K43: 0.5894 | L43: 9.6174 | M43: 6.9124 | N43: 19.1104 | O43: 0.7106 | P43: 10.7198 | Q43: 3.08 | R43: 0 | S43: 0 | T43: 0 | U43: 0 | V43: 3.3692 | W43: 0.8884 | X43: 4.980472 | Y43: 7.371928 | Z43: 0 | AA43: 0 | AB43: 0 | AC43: 0 | AD43: 0 | AE43: 0 | AF43: 0 | AG43: 0 | AH43: 0 | AI43: 0 | AJ43: 1.0268 | AK43: 0 | AL43: 3.8732 | AM43: 0 | AN43: 11.0014 | AO43: 7.079 | AP43: 0 | AQ43: 0 | AR43: 6.9124 | AS43: 17.625 | AT43: 0 | AU43: 0 | AV43: 6.9124 | AW43: 0.5102 | AX43: 0.2038 | AY43: 25.9536 | AZ43: 0
A44: Pine Large Saw Timber | B44: 0 | C44: 3.741936 | D44: 0 | E44: 0 | F44: 0 | G44: 47.9028 | H44: 0 | I44: 0 | J44: 0 | K44: 0 | L44: 0 | M44: 153.24998 | N44: 353.24248 | O44: 17.180887 | P44: 269.84524 | Q44: 214.47303 | R44: 0 | S44: 0 | T44: 0 | U44: 0 | V44: 0 | W44: 0 | X44: 0 | Y44: 0 | Z44: 0 | AA44: 0 | AB44: 0 | AC44: 0 | AD44: 0 | AE44: 0 | AF44: 0 | AG44: 0 | AH44: 0 | AI44: 0 | AJ44: 0 | AK44: 0 | AL44: 0 | AM44: 0 | AN44: 0 | AO44: 0 | AP44: 0 | AQ44: 0 | AR44: 0 | AS44: 0 | AT44: 0 | AU44: 0 | AV44: 139.81642 | AW44: 10.319764 | AX44: 4.1222422 | AY44: 554.04591 | AZ44: 0
A45: Pine Saw Timber | B45: 0 | C45: 0.04104 | D45: 0 | E45: 325.7671 | F45: 0 | G45: 0.316844 | H45: 0 | I45: 471.93806 | J45: 100.55759 | K45: 0.9297785 | L45: 65.979994 | M45: 0 | N45: 6.109973 | O45: 0 | P45: 0 | Q45: 0 | R45: 0 | S45: 0 | T45: 0 | U45: 0 | V45: 34.344614 | W45: 9.0560831 | X45: 50.769437 | Y45: 75.147222 | Z45: 0 | AA45: 0 | AB45: 0 | AC45: 0 | AD45: 0 | AE45: 0 | AF45: 0 | AG45: 0 | AH45: 0 | AI45: 0 | AJ45: 1.5051345 | AK45: 0 | AL45: 5.0948073 | AM45: 0 | AN45: 318.50259 | AO45: 31.37696 | AP45: 0 | AQ45: 0 | AR45: 240.86949 | AS45: 221.12779 | AT45: 0 | AU45: 0 | AV45: 0 | AW45: 0 | AX45: 0 | AY45: 0 | AZ45: 0
A46: Pine Chip-N-Saw | B46: 0 | C46: 99.189576 | D46: 0 | E46: 172.30017 | F46: 0 | G46: 214.70821 | H46: 0 | I46: 213.58008 | J46: 253.40746 | K46: 15.250489 | L46: 232.02862 | M46: 80.03868 | N46: 274.24309 | O46: 8.0107359 | P46: 119.37676 | Q46: 129.8143 | R46: 0 | S46: 0 | T46: 0 | U46: 0 | V46: 109.56504 | W46: 28.890413 | X46: 161.96296 | Y46: 239.73215 | Z46: 0 | AA46: 0 | AB46: 0 | AC46: 0 | AD46: 0 | AE46: 0 | AF46: 0 | AG46: 0 | AH46: 0 | AI46: 0 | AJ46: 25.89803 | AK46: 0 | AL46: 94.284533 | AM46: 0 | AN46: 213.03183 | AO46: 144.62893 | AP46: 0 | AQ46: 0 | AR46: 133.23858 | AS46: 302.92811 | AT46: 0 | AU46: 0 | AV46: 80.836371 | AW46: 5.9664829 | AX46: 2.3833187 | AY46: 301.8435 | AZ46: 0
A47: Pine Pulpwood | B47: 0 | C47: 58.704528 | D47: 0 | E47: 170.84763 | F47: 0 | G47: 119.10241 | H47: 0 | I47: 211.08936 | J47: 182.58304 | K47: 32.966674 | L47: 192.60672 | M47: 118.39144 | N47: 479.58651 | O47: 12.354421 | P47: 187.76802 | Q47: 233.44614 | R47: 0 | S47: 0 | T47: 0 | U47: 0 | V47: 68.092543 | W47: 17.954831 | X47: 100.65683 | Y47: 148.98888 | Z47: 0 | AA47: 0 | AB47: 0 | AC47: 0 | AD47: 0 | AE47: 0 | AF47: 0 | AG47: 0 | AH47: 0 | AI47: 0 | AJ47: 57.476996 | AK47: 0 | AL47: 217.04018 | AM47: 0 | AN47: 209.06418 | AO47: 129.81045 | AP47: 0 | AQ47: 0 | AR47: 132.60195 | AS47: 262.85207 | AT47: 0 | AU47: 0 | AV47: 117.5661 | AW47: 8.6774816 | AX47: 3.4662304 | AY47: 443.17424 | AZ47: 0
A48: Total Pine Tons | B48: =SUM(B44:B47) -> 0 | C48: =SUM(C44:C47) -> 161.67708 | D48: =SUM(D44:D47) -> 0 | E48: =SUM(E44:E47) -> 668.9149 | F48: =SUM(F44:F47) -> 0 | G48: =SUM(G44:G47) -> 382.03026 | H48: =SUM(H44:H47) -> 0 | I48: =SUM(I44:I47) -> 896.6075 | ... AZ48: =SUM(AZ44:AZ47) -> 0
A49: HW Saw Timber | B49: 0 | C49: 0.079344 | D49: 0 | E49: 20.629347 | F49: 0 | G49: 48.779764 | H49: 0 | I49: 32.700561 | J49: 24.043997 | K49: 0.56234654 | L49: 0.62754534 | M49: 178.91987 | N49: 418.0726 | O49: 20.243075 | P49: 319.05341 | Q49: 16.06682 | R49: 0 | S49: 0 | T49: 0 | U49: 0 | V49: 2.1788616 | W49: 0.57452828 | X49: 3.2208712 | Y49: 4.7674258 | Z49: 0 | AA49: 0 | AB49: 0 | AC49: 0 | AD49: 0 | AE49: 0 | AF49: 0 | AG49: 0 | AH49: 0 | AI49: 0 | AJ49: 0.9684287 | AK49: 0 | AL49: 3.5958789 | AM49: 0 | AN49: 19.058427 | AO49: 0 | AP49: 0 | AQ49: 0 | AR49: 14.801522 | AS49: 26.536905 | AT49: 0 | AU49: 0 | AV49: 163.21766 | AW49: 12.046995 | AX49: 4.8121867 | AY49: 646.75535 | AZ49: 0
A50: HW Pulpwood | B50: 0 | C50: 7.386288 | D50: 0 | E50: 240.30012 | F50: 0 | G50: 128.68799 | H50: 0 | I50: 323.19693 | J50: 308.79135 | K50: 2.5713754 | L50: 147.95929 | M50: 278.87732 | N50: 629.69056 | O50: 28.500461 | P50: 429.23151 | Q50: 27.808396 | R50: 0 | S50: 0 | T50: 0 | U50: 0 | V50: 49.180212 | W50: 12.967975 | X50: 72.69995 | Y50: 107.60803 | Z50: 0 | AA50: 0 | AB50: 0 | AC50: 0 | AD50: 0 | AE50: 0 | AF50: 0 | AG50: 0 | AH50: 0 | AI50: 0 | AJ50: 4.3585918 | AK50: 0 | AL50: 15.825895 | AM50: 0 | AN50: 259.91388 | AO50: 89.538024 | AP50: 0 | AQ50: 0 | AR50: 182.15142 | AS50: 380.13809 | AT50: 0 | AU50: 0 | AV50: 277.65106 | AW50: 20.493254 | AX50: 8.186055 | AY50: 1045.2601 | AZ50: 0
A51: Total Hardwood Tons | B51: =SUM(B49:B50) -> 0 | C51: =SUM(C49:C50) -> 7.465632 | D51: =SUM(D49:D50) -> 0 | E51: =SUM(E49:E50) -> 260.92947 | F51: =SUM(F49:F50) -> 0 | G51: =SUM(G49:G50) -> 177.46775 | H51: =SUM(H49:H50) -> 0 | I51: =SUM(I49:I50) -> 355.89749 | ... AZ51: =SUM(AZ49:AZ50) -> 0
A52: Mean CC Age | B52: 0 | C52: 26 | D52: 0 | E52: 36 | F52: 0 | G52: 35 | H52: 0 | I52: 40 | J52: 40 | K52: 27 | L52: 34.68164 | M52: 37 | N52: 36.3786 | O52: 39 | P52: 40 | Q52: 40 | R52: 0 | S52: 0 | T52: 0 | U52: 0 | V52: 35 | W52: 36 | X52: 37 | Y52: 38 | Z52: 0 | AA52: 0 | AB52: 0 | AC52: 0 | AD52: 0 | AE52: 0 | AF52: 0 | AG52: 0 | AH52: 0 | AI52: 0 | AJ52: 24.574016 | AK52: 0 | AL52: 24 | AM52: 0 | AN52: 33.66317 | AO52: 29 | AP52: 0 | AQ52: 0 | AR52: 35 | AS52: 35.232 | AT52: 0 | AU52: 0 | AV52: 35 | AW52: 35 | AX52: 35 | AY52: 36.154399 | AZ52: 0
A54: Total
A55: Clearcut Acres | B55: =SUM(B31,B43) -> 0 | C55: =SUM(C31,C43) -> 376.62 | D55: =SUM(D31,D43) -> 0 | E55: =SUM(E31,E43) -> 453.9204 | F55: =SUM(F31,F43) -> 0 | G55: =SUM(G31,G43) -> 213.18 | H55: =SUM(H31,H43) -> 0 | I55: =SUM(I31,I43) -> 561.0714 | ... AZ55: =SUM(AZ31,AZ43) -> 1500
A56: Pine Large Saw Timber | B56: =SUM(B32,B44) -> 0 | C56: =SUM(C32,C44) -> 1498.1175 | D56: =SUM(D32,D44) -> 0 | E56: =SUM(E32,E44) -> 2955.033 | F56: =SUM(F32,F44) -> 0 | G56: =SUM(G32,G44) -> 332.31952 | H56: =SUM(H32,H44) -> 0 | I56: =SUM(I32,I44) -> 2170.11 | ... AZ56: =SUM(AZ32,AZ44) -> 4315.5272
A57: Pine Saw Timber | B57: =SUM(B33,B45) -> 0 | C57: =SUM(C33,C45) -> 663.581 | D57: =SUM(D33,D45) -> 0 | E57: =SUM(E33,E45) -> 1163.5334 | F57: =SUM(F33,F45) -> 0 | G57: =SUM(G33,G45) -> 192.19891 | H57: =SUM(H33,H45) -> 0 | I57: =SUM(I33,I45) -> 1989.4187 | ... AZ57: =SUM(AZ33,AZ45) -> 6072.6358
A58: Pine Chip-N-Saw | B58: =SUM(B34,B46) -> 0 | C58: =SUM(C34,C46) -> 23600.409 | D58: =SUM(D34,D46) -> 0 | E58: =SUM(E34,E46) -> 29844.624 | F58: =SUM(F34,F46) -> 0 | G58: =SUM(G34,G46) -> 9727.0556 | H58: =SUM(H34,H46) -> 0 | I58: =SUM(I34,I46) -> 44358.55 | ... AZ58: =SUM(AZ34,AZ46) -> 99790.039
A59: Pine Pulpwood | B59: =SUM(B35,B47) -> 0 | C59: =SUM(C35,C47) -> 9481.8658 | D59: =SUM(D35,D47) -> 0 | E59: =SUM(E35,E47) -> 15776.841 | F59: =SUM(F35,F47) -> 0 | G59: =SUM(G35,G47) -> 7113.8146 | H59: =SUM(H35,H47) -> 0 | I59: =SUM(I35,I47) -> 13492.006 | ... AZ59: =SUM(AZ35,AZ47) -> 26373.389
A60: Total Pine Tons | B60: =SUM(B56:B59) -> 0 | C60: =SUM(C56:C59) -> 35243.973 | D60: =SUM(D56:D59) -> 0 | E60: =SUM(E56:E59) -> 49740.031 | F60: =SUM(F56:F59) -> 0 | G60: =SUM(G56:G59) -> 17365.389 | H60: =SUM(H56:H59) -> 0 | I60: =SUM(I56:I59) -> 62010.085 | ... AZ60: =SUM(AZ56:AZ59) -> 136551.59
A61: HW Saw Timber | B61: =SUM(B37,B49) -> 0 | C61: =SUM(C37,C49) -> 335.78893 | D61: =SUM(D37,D49) -> 0 | E61: =SUM(E37,E49) -> 569.44043 | F61: =SUM(F37,F49) -> 0 | G61: =SUM(G37,G49) -> 72.061585 | H61: =SUM(H37,H49) -> 0 | I61: =SUM(I37,I49) -> 252.34545 | ... AZ61: =SUM(AZ37,AZ49) -> 0
A62: HW Pulpwood | B62: =SUM(B38,B50) -> 0 | C62: =SUM(C38,C50) -> 1875.9037 | D62: =SUM(D38,D50) -> 0 | E62: =SUM(E38,E50) -> 4162.076 | F62: =SUM(F38,F50) -> 0 | G62: =SUM(G38,G50) -> 529.16745 | H62: =SUM(H38,H50) -> 0 | I62: =SUM(I38,I50) -> 1947.0905 | ... AZ62: =SUM(AZ38,AZ50) -> 0
A63: Total Hardwood Tons | B63: =SUM(B61:B62) -> 0 | C63: =SUM(C61:C62) -> 2211.6926 | D63: =SUM(D61:D62) -> 0 | E63: =SUM(E61:E62) -> 4731.5164 | F63: =SUM(F61:F62) -> 0 | G63: =SUM(G61:G62) -> 601.22904 | H63: =SUM(H61:H62) -> 0 | I63: =SUM(I61:I62) -> 2199.436 | ... AZ63: =SUM(AZ61:AZ62) -> 0
A64: Total Tons, All Products | B64: =B63+B60 -> 0 | C64: =C63+C60 -> 37455.666 | D64: =D63+D60 -> 0 | E64: =E63+E60 -> 54471.547 | F64: =F63+F60 -> 0 | G64: =G63+G60 -> 17966.618 | H64: =H63+H60 -> 0 | I64: =I63+I60 -> 64209.521 | ... AZ64: =AZ63+AZ60 -> 136551.59
A65: % Pine Solidwood | B65: =IF(B60>0,(SUM(B56:B58)/B60),0) -> 0 | C65: =IF(C60>0,(SUM(C56:C58)/C60),0) -> 0.7309649 | D65: =IF(D60>0,(SUM(D56:D58)/D60),0) -> 0 | E65: =IF(E60>0,(SUM(E56:E58)/E60),0) -> 0.68281402 | F65: =IF(F60>0,(SUM(F56:F58)/F60),0) -> 0 | G65: =IF(G60>0,(SUM(G56:G58)/G60),0) -> 0.59034521 | H65: =IF(H60>0,(SUM(H56:H58)/H60),0) -> 0 | I65: =IF(I60>0,(SUM(I56:I58)/I60),0) -> 0.78242239 | ... AZ65: =IF(AZ60>0,(SUM(AZ56:AZ58)/AZ60),0) -> 0.80686136
A66: % Pine Large Saw Timber | B66: =IF(B$60>0,(SUM(B56)/B$60),0) -> 0 | C66: =IF(C$60>0,(SUM(C56)/C$60),0) -> 0.042507054 | D66: =IF(D$60>0,(SUM(D56)/D$60),0) -> 0 | E66: =IF(E$60>0,(SUM(E56)/E$60),0) -> 0.059409552 | F66: =IF(F$60>0,(SUM(F56)/F$60),0) -> 0 | G66: =IF(G$60>0,(SUM(G56)/G$60),0) -> 0.019136889 | H66: =IF(H$60>0,(SUM(H56)/H$60),0) -> 0 | I66: =IF(I$60>0,(SUM(I56)/I$60),0) -> 0.034996082 | ... AZ66: =IF(AZ$60>0,(SUM(AZ56)/AZ$60),0) -> 0.031603639
A67: % Pine Saw Timber | B67: =IF(B$60>0,(SUM(B57)/B$60),0) -> 0 | C67: =IF(C$60>0,(SUM(C57)/C$60),0) -> 0.018828212 | D67: =IF(D$60>0,(SUM(D57)/D$60),0) -> 0 | E67: =IF(E$60>0,(SUM(E57)/E$60),0) -> 0.023392294 | F67: =IF(F$60>0,(SUM(F57)/F$60),0) -> 0 | G67: =IF(G$60>0,(SUM(G57)/G$60),0) -> 0.01106793 | H67: =IF(H$60>0,(SUM(H57)/H$60),0) -> 0 | I67: =IF(I$60>0,(SUM(I57)/I$60),0) -> 0.03208218 | ... AZ67: =IF(AZ$60>0,(SUM(AZ57)/AZ$60),0) -> 0.044471366
A68: % Pine Chip-N-Saw | B68: =IF(B$60>0,(SUM(B58)/B$60),0) -> 0 | C68: =IF(C$60>0,(SUM(C58)/C$60),0) -> 0.66962964 | D68: =IF(D$60>0,(SUM(D58)/D$60),0) -> 0 | E68: =IF(E$60>0,(SUM(E58)/E$60),0) -> 0.60001217 | F68: =IF(F$60>0,(SUM(F58)/F$60),0) -> 0 | G68: =IF(G$60>0,(SUM(G58)/G$60),0) -> 0.56014039 | H68: =IF(H$60>0,(SUM(H58)/H$60),0) -> 0 | I68: =IF(I$60>0,(SUM(I58)/I$60),0) -> 0.71534413 | ... AZ68: =IF(AZ$60>0,(SUM(AZ58)/AZ$60),0) -> 0.73078635
A69: % Pine Pulpwood | B69: =IF(B$60>0,(SUM(B59)/B$60),0) -> 0 | C69: =IF(C$60>0,(SUM(C59)/C$60),0) -> 0.2690351 | D69: =IF(D$60>0,(SUM(D59)/D$60),0) -> 0 | E69: =IF(E$60>0,(SUM(E59)/E$60),0) -> 0.31718598 | F69: =IF(F$60>0,(SUM(F59)/F$60),0) -> 0 | G69: =IF(G$60>0,(SUM(G59)/G$60),0) -> 0.40965479 | H69: =IF(H$60>0,(SUM(H59)/H$60),0) -> 0 | I69: =IF(I$60>0,(SUM(I59)/I$60),0) -> 0.21757761 | ... AZ69: =IF(AZ$60>0,(SUM(AZ59)/AZ$60),0) -> 0.19313864
B70: =SUM(B66:B69) -> 0 | C70: =SUM(C66:C69) -> 1 | D70: =SUM(D66:D69) -> 0 | E70: =SUM(E66:E69) -> 1 | F70: =SUM(F66:F69) -> 0 | G70: =SUM(G66:G69) -> 1 | H70: =SUM(H66:H69) -> 0 | I70: =SUM(I66:I69) -> 1 | ... AZ70: =SUM(AZ66:AZ69) -> 1
A71: % HW Saw Timber | B71: =IF(B$63>0,(SUM(B61)/B$63),0) -> 0 | C71: =IF(C$63>0,(SUM(C61)/C$63),0) -> 0.15182441 | D71: =IF(D$63>0,(SUM(D61)/D$63),0) -> 0 | E71: =IF(E$63>0,(SUM(E61)/E$63),0) -> 0.12035051 | F71: =IF(F$63>0,(SUM(F61)/F$63),0) -> 0 | G71: =IF(G$63>0,(SUM(G61)/G$63),0) -> 0.11985713 | H71: =IF(H$63>0,(SUM(H61)/H$63),0) -> 0 | I71: =IF(I$63>0,(SUM(I61)/I$63),0) -> 0.11473189 | ... AZ71: =IF(AZ$63>0,(SUM(AZ61)/AZ$63),0) -> 0
A72: % HW Pulpwood | B72: =IF(B$63>0,(SUM(B62)/B$63),0) -> 0 | C72: =IF(C$63>0,(SUM(C62)/C$63),0) -> 0.84817559 | D72: =IF(D$63>0,(SUM(D62)/D$63),0) -> 0 | E72: =IF(E$63>0,(SUM(E62)/E$63),0) -> 0.87964949 | F72: =IF(F$63>0,(SUM(F62)/F$63),0) -> 0 | G72: =IF(G$63>0,(SUM(G62)/G$63),0) -> 0.88014287 | H72: =IF(H$63>0,(SUM(H62)/H$63),0) -> 0 | I72: =IF(I$63>0,(SUM(I62)/I$63),0) -> 0.88526811 | ... AZ72: =IF(AZ$63>0,(SUM(AZ62)/AZ$63),0) -> 0
B73: =SUM(B71:B72) -> 0 | C73: =SUM(C71:C72) -> 1 | D73: =SUM(D71:D72) -> 0 | E73: =SUM(E71:E72) -> 1 | F73: =SUM(F71:F72) -> 0 | G73: =SUM(G71:G72) -> 1 | H73: =SUM(H71:H72) -> 0 | I73: =SUM(I71:I72) -> 1 | ... AZ73: =SUM(AZ71:AZ72) -> 0
A75: Thinning Harvests
A76: First Thin
A77: 1st Thin Acres | B77: 0 | C77: 543.34 | D77: 193.34 | E77: 95.91 | F77: 430.75 | G77: 200.69 | H77: 0 | I77: 0 | J77: 435.34 | K77: 781.46 | L77: 212.73 | M77: 0 | N77: 267.97 | O77: 626.28 | P77: 444.94 | Q77: 0 | R77: 215.79 | S77: 372.95 | T77: 1.39 | U77: 445.02 | V77: 0 | W77: 209 | X77: 0 | Y77: 550.07 | Z77: 676.8 | AA77: 29.47 | AB77: 480.87 | AC77: 345.62 | AD77: 955.52 | AE77: 35.53 | AF77: 535.99 | AG77: 570.39 | AH77: 25.51 | AI77: 10.19 | AJ77: 159.25 | AK77: 206.44 | AL77: 168.46 | AM77: 44.42 | AN77: 249.0236 | AO77: 978.2064 | AP77: 1168.2464 | AQ77: 170.51 | AR77: 0 | AS77: 0 | AT77: 59.25 | AU77: 206.9336 | AV77: 0 | AW77: 160.58 | AX77: 320.29 | AY77: 1.39 | AZ77: 456.38
A78: Pine Large Saw Timber | B78: 0 | C78: 0 | D78: 0 | E78: 0 | F78: 2.461212 | G78: 0 | H78: 0 | I78: 0 | J78: 0 | K78: 0 | L78: 0 | M78: 0 | N78: 0 | O78: 0 | P78: 0 | Q78: 0 | R78: 0 | S78: 0 | T78: 0 | U78: 0 | V78: 0 | W78: 0 | X78: 0 | Y78: 0 | Z78: 0 | AA78: 0 | AB78: 0 | AC78: 0 | AD78: 0 | AE78: 0 | AF78: 0 | AG78: 0 | AH78: 0 | AI78: 0 | AJ78: 0 | AK78: 0 | AL78: 0 | AM78: 0 | AN78: 0 | AO78: 0 | AP78: 0 | AQ78: 0 | AR78: 0 | AS78: 0 | AT78: 0 | AU78: 0 | AV78: 0 | AW78: 0 | AX78: 0 | AY78: 0 | AZ78: 0
A79: Pine Saw Timber | B79: 0 | C79: 14.537703 | D79: 22.062283 | E79: 19.640917 | F79: 0 | G79: 7.3932 | H79: 0 | I79: 0 | J79: 0 | K79: 0 | L79: 0 | M79: 0 | N79: 0 | O79: 0 | P79: 0 | Q79: 0 | R79: 0 | S79: 0 | T79: 0 | U79: 0 | V79: 0 | W79: 0 | X79: 0 | Y79: 0 | Z79: 0 | AA79: 0 | AB79: 0 | AC79: 0 | AD79: 0 | AE79: 0 | AF79: 0 | AG79: 0 | AH79: 0 | AI79: 0 | AJ79: 0 | AK79: 0 | AL79: 0 | AM79: 0 | AN79: 0 | AO79: 0 | AP79: 0 | AQ79: 0 | AR79: 0 | AS79: 0 | AT79: 0 | AU79: 0 | AV79: 0 | AW79: 0 | AX79: 0 | AY79: 0 | AZ79: 0
A80: Pine Chip-N-Saw | B80: 0 | C80: 4579.5133 | D80: 1552.6814 | E80: 529.89649 | F80: 2057.1727 | G80: 363.84031 | H80: 0 | I80: 0 | J80: 7915.9029 | K80: 17200.412 | L80: 3946.5599 | M80: 0 | N80: 1382.2862 | O80: 2401.1385 | P80: 11696.285 | Q80: 0 | R80: 935.70432 | S80: 3517.1739 | T80: 0 | U80: 10507.889 | V80: 0 | W80: 541.63643 | X80: 0 | Y80: 10882.776 | Z80: 18852.184 | AA80: 1.373302 | AB80: 7156.4577 | AC80: 5644.838 | AD80: 10696.078 | AE80: 487.30812 | AF80: 2398.3382 | AG80: 16737.544 | AH80: 24.656528 | AI80: 31.857541 | AJ80: 2125.64 | AK80: 2714.6567 | AL80: 837.73436 | AM80: 602.504 | AN80: 2682.092 | AO80: 1533.6055 | AP80: 11368.632 | AQ80: 0 | AR80: 0 | AS80: 0 | AT80: 803.65515 | AU80: 4758.2287 | AV80: 0 | AW80: 308.98801 | AX80: 1595.8265 | AY80: 0 | AZ80: 10617.111
A81: Pine Pulpwood | B81: 0 | C81: 5365.256 | D81: 3177.0371 | E81: 2013.593 | F81: 10627.167 | G81: 4759.5856 | H81: 0 | I81: 0 | J81: 16262.987 | K81: 35342.669 | L81: 9140.868 | M81: 0 | N81: 9038.3202 | O81: 20243.227 | P81: 14689.298 | Q81: 0 | R81: 4135.8166 | S81: 5850.2918 | T81: 9.595031 | U81: 9726.6187 | V81: 0 | W81: 2402.3859 | X81: 0 | Y81: 12550.853 | Z81: 14545.626 | AA81: 606.47786 | AB81: 6516.5588 | AC81: 7770.7774 | AD81: 22812.89 | AE81: 865.03332 | AF81: 13217.409 | AG81: 12459.355 | AH81: 421.5625 | AI81: 257.87178 | AJ81: 3946.0815 | AK81: 5115.8001 | AL81: 4221.1038 | AM81: 1100.5988 | AN81: 6145.7388 | AO81: 22618.262 | AP81: 27013.856 | AQ81: 1177.0135 | AR81: 0 | AS81: 0 | AT81: 1468.0432 | AU81: 4538.6871 | AV81: 0 | AW81: 2899.0795 | AX81: 4752.4045 | AY81: 9.595031 | AZ81: 10005.621
A82: Total Pine Tons | B82: =SUM(B78:B81) -> 0 | C82: =SUM(C78:C81) -> 9959.3071 | D82: =SUM(D78:D81) -> 4751.7809 | E82: =SUM(E78:E81) -> 2563.1304 | F82: =SUM(F78:F81) -> 12686.801 | G82: =SUM(G78:G81) -> 5130.8191 | H82: =SUM(H78:H81) -> 0 | I82: =SUM(I78:I81) -> 0 | ... AZ82: =SUM(AZ78:AZ81) -> 20622.732
A83: Mean 1st Thin Age | B83: 0 | C83: 16.146096 | D83: 15.57448 | E83: 14 | F83: 14 | G83: 14 | H83: 0 | I83: 0 | J83: 14 | K83: 14 | L83: 14 | M83: 0 | N83: 14 | O83: 14 | P83: 14 | Q83: 0 | R83: 14 | S83: 14 | T83: 15 | U83: 14 | V83: 0 | W83: 14 | X83: 0 | Y83: 14 | Z83: 14 | AA83: 14 | AB83: 14 | AC83: 14 | AD83: 14 | AE83: 14 | AF83: 14 | AG83: 14 | AH83: 14 | AI83: 14 | AJ83: 14 | AK83: 14 | AL83: 14 | AM83: 14 | AN83: 14 | AO83: 14 | AP83: 14 | AQ83: 15 | AR83: 0 | AS83: 0 | AT83: 14 | AU83: 14 | AV83: 0 | AW83: 14 | AX83: 14 | AY83: 15 | AZ83: 14
A85: Second Thin
A86: 2nd Thin Acres | B86: 0 | C86: 0 | D86: 0 | E86: 149.35 | F86: 146.05 | G86: 7.84 | H86: 119.68 | I86: 84.15 | J86: 353.64 | K86: 5.54 | L86: 0 | M86: 107.12 | N86: 0 | O86: 0 | P86: 346.64 | Q86: 355.81 | R86: 568.19 | S86: 70.08 | T86: 53.1 | U86: 330.4964 | V86: 101.8636 | W86: 111.66 | X86: 0 | Y86: 90.55 | Z86: 83.27 | AA86: 221.87 | AB86: 183.28 | AC86: 0 | AD86: 43.24 | AE86: 9.51 | AF86: 545.34 | AG86: 672.02 | AH86: 0 | AI86: 204.95 | AJ86: 367.43 | AK86: 652.11 | AL86: 42.08 | AM86: 292.87 | AN86: 501.99 | AO86: 5.41 | AP86: 128.94 | AQ86: 30.31 | AR86: 206.44 | AS86: 151.88 | AT86: 113.03 | AU86: 450.63 | AV86: 0 | AW86: 0 | AX86: 0 | AY86: 0 | AZ86: 266.1836
A87: Pine Large Saw Timber | B87: 0 | C87: 0 | D87: 0 | E87: 9.91116 | F87: 160.34929 | G87: 0 | H87: 0 | I87: 0 | J87: 0 | K87: 0 | L87: 0 | M87: 23.667807 | N87: 0 | O87: 0 | P87: 0 | Q87: 0 | R87: 692.74119 | S87: 264.97248 | T87: 0 | U87: 9.792384 | V87: 0 | W87: 14.94796 | X87: 0 | Y87: 23.949768 | Z87: 11.677051 | AA87: 100.29704 | AB87: 28.597095 | AC87: 0 | AD87: 5.193252 | AE87: 4.325148 | AF87: 85.851185 | AG87: 47.985616 | AH87: 0 | AI87: 0 | AJ87: 0 | AK87: 77.506328 | AL87: 0 | AM87: 6.169023 | AN87: 0 | AO87: 0 | AP87: 0 | AQ87: 3.992679 | AR87: 16.884585 | AS87: 0 | AT87: 0 | AU87: 22.178584 | AV87: 0 | AW87: 0 | AX87: 0 | AY87: 0 | AZ87: 4.507696
A88: Pine Saw Timber | B88: 0 | C88: 0 | D88: 0 | E88: 4.493424 | F88: 0 | G88: 1.007624 | H88: 11.273856 | I88: 107.02169 | J88: 76.995358 | K88: 0.488628 | L88: 0 | M88: 0.208408 | N88: 0 | O88: 0 | P88: 409.01862 | Q88: 600.02363 | R88: 363.34979 | S88: 0 | T88: 0 | U88: 0 | V88: 0 | W88: 4.665245 | X88: 0 | Y88: 0 | Z88: 0 | AA88: 0 | AB88: 0 | AC88: 0 | AD88: 0.544752 | AE88: 0 | AF88: 0 | AG88: 144.82022 | AH88: 0 | AI88: 125.28598 | AJ88: 22.509432 | AK88: 0.614592 | AL88: 0 | AM88: 0 | AN88: 266.62817 | AO88: 0 | AP88: 0 | AQ88: 0 | AR88: 0 | AS88: 0 | AT88: 0 | AU88: 0 | AV88: 0 | AW88: 0 | AX88: 0 | AY88: 0 | AZ88: 4.665245
A89: Pine Chip-N-Saw | B89: 0 | C89: 0 | D89: 0 | E89: 2785.7437 | F89: 5157.3315 | G89: 224.12027 | H89: 2250.1516 | I89: 1404.5737 | J89: 6374.8437 | K89: 82.369274 | L89: 0 | M89: 1370.1911 | N89: 0 | O89: 0 | P89: 9384.4496 | Q89: 11640.975 | R89: 24419.809 | S89: 3747.0585 | T89: 1343.6328 | U89: 9341.9275 | V89: 3625.8462 | W89: 3587.4547 | X89: 0 | Y89: 3579.6525 | Z89: 2838.7443 | AA89: 11504.049 | AB89: 6388.9731 | AC89: 0 | AD89: 1344.4835 | AE89: 494.81291 | AF89: 20556.692 | AG89: 28693.698 | AH89: 0 | AI89: 9875.0998 | AJ89: 10123.344 | AK89: 19253.194 | AL89: 955.82531 | AM89: 5823.6615 | AN89: 22156.589 | AO89: 99.4798 | AP89: 2857.5425 | AQ89: 966.80018 | AR89: 6223.7518 | AS89: 3063.4569 | AT89: 2613.5894 | AU89: 12730.194 | AV89: 0 | AW89: 0 | AX89: 0 | AY89: 0 | AZ89: 7070.3958
A90: Pine Pulpwood | B90: 0 | C90: 0 | D90: 0 | E90: 1473.515 | F90: 1740.5522 | G90: 74.706503 | H90: 595.92262 | I90: 720.16529 | J90: 2909.6463 | K90: 46.933218 | L90: 0 | M90: 889.26783 | N90: 0 | O90: 0 | P90: 5708.8764 | Q90: 6305.9264 | R90: 12083.553 | S90: 1888.2425 | T90: 372.66028 | U90: 2312.2745 | V90: 732.86558 | W90: 811.45916 | X90: 0 | Y90: 819.05483 | Z90: 616.30091 | AA90: 2246.0595 | AB90: 1340.8283 | AC90: 0 | AD90: 315.77689 | AE90: 96.422841 | AF90: 4428.7775 | AG90: 5953.1709 | AH90: 0 | AI90: 1933.2069 | AJ90: 2906.0738 | AK90: 5086.212 | AL90: 318.21345 | AM90: 2110.4253 | AN90: 4586.2049 | AO90: 39.223271 | AP90: 970.29929 | AQ90: 220.55397 | AR90: 1526.8739 | AS90: 1110.8082 | AT90: 858.24279 | AU90: 3578.8941 | AV90: 0 | AW90: 0 | AX90: 0 | AY90: 0 | AZ90: 2014.7574
A91: Total Pine Tons | B91: =SUM(B87:B90) -> 0 | C91: =SUM(C87:C90) -> 0 | D91: =SUM(D87:D90) -> 0 | E91: =SUM(E87:E90) -> 4273.6633 | F91: =SUM(F87:F90) -> 7058.233 | G91: =SUM(G87:G90) -> 299.8344 | H91: =SUM(H87:H90) -> 2857.348 | I91: =SUM(I87:I90) -> 2231.7607 | ... AZ91: =SUM(AZ87:AZ90) -> 9094.3261
A92: Mean 2nd Thin Age | B92: 0 | C92: 0 | D92: 0 | E92: 20 | F92: 21 | G92: 20.672194 | H92: 21 | I92: 20.337493 | J92: 21 | K92: 20 | L92: 0 | M92: 21 | N92: 0 | O92: 0 | P92: 20 | Q92: 20.24929 | R92: 20.905243 | S92: 21 | T92: 20 | U92: 19.386812 | V92: 20.58166 | W92: 20.011105 | X92: 0 | Y92: 20 | Z92: 21 | AA92: 20 | AB92: 21 | AC92: 0 | AD92: 21 | AE92: 20 | AF92: 20.991235 | AG92: 21 | AH92: 0 | AI92: 21 | AJ92: 20.867267 | AK92: 20.966309 | AL92: 20.322243 | AM92: 20.766449 | AN92: 21 | AO92: 20.597043 | AP92: 20 | AQ92: 21 | AR92: 21 | AS92: 20.707532 | AT92: 20 | AU92: 19.787158 | AV92: 0 | AW92: 0 | AX92: 0 | AY92: 0 | AZ92: 19.222591
A94: 1st & 2nd Thin
A95: Thin Acres | B95: =SUM(B77,B86) -> 0 | C95: =SUM(C77,C86) -> 543.34 | D95: =SUM(D77,D86) -> 193.34 | E95: =SUM(E77,E86) -> 245.26 | F95: =SUM(F77,F86) -> 576.8 | G95: =SUM(G77,G86) -> 208.53 | H95: =SUM(H77,H86) -> 119.68 | I95: =SUM(I77,I86) -> 84.15 | ... AZ95: =SUM(AZ77,AZ86) -> 722.5636
A96: Pine Large Saw Timber | B96: =SUM(B78,B87) -> 0 | C96: =SUM(C78,C87) -> 0 | D96: =SUM(D78,D87) -> 0 | E96: =SUM(E78,E87) -> 9.91116 | F96: =SUM(F78,F87) -> 162.81051 | G96: =SUM(G78,G87) -> 0 | H96: =SUM(H78,H87) -> 0 | I96: =SUM(I78,I87) -> 0 | ... AZ96: =SUM(AZ78,AZ87) -> 4.507696
A97: Pine Saw Timber | B97: =SUM(B79,B88) -> 0 | C97: =SUM(C79,C88) -> 14.537703 | D97: =SUM(D79,D88) -> 22.062283 | E97: =SUM(E79,E88) -> 24.134341 | F97: =SUM(F79,F88) -> 0 | G97: =SUM(G79,G88) -> 8.400824 | H97: =SUM(H79,H88) -> 11.273856 | I97: =SUM(I79,I88) -> 107.02169 | ... AZ97: =SUM(AZ79,AZ88) -> 4.665245
A98: Pine Chip-N-Saw | B98: =SUM(B80,B89) -> 0 | C98: =SUM(C80,C89) -> 4579.5133 | D98: =SUM(D80,D89) -> 1552.6814 | E98: =SUM(E80,E89) -> 3315.6402 | F98: =SUM(F80,F89) -> 7214.5042 | G98: =SUM(G80,G89) -> 587.96058 | H98: =SUM(H80,H89) -> 2250.1516 | I98: =SUM(I80,I89) -> 1404.5737 | ... AZ98: =SUM(AZ80,AZ89) -> 17687.507
A99: Pine Pulpwood | B99: =SUM(B81:B81)+SUM(B90:B90) -> 0 | C99: =SUM(C81:C81)+SUM(C90:C90) -> 5365.256 | D99: =SUM(D81:D81)+SUM(D90:D90) -> 3177.0371 | E99: =SUM(E81:E81)+SUM(E90:E90) -> 3487.108 | F99: =SUM(F81:F81)+SUM(F90:F90) -> 12367.719 | G99: =SUM(G81:G81)+SUM(G90:G90) -> 4834.2921 | H99: =SUM(H81:H81)+SUM(H90:H90) -> 595.92262 | I99: =SUM(I81:I81)+SUM(I90:I90) -> 720.16529 | ... AZ99: =SUM(AZ81:AZ81)+SUM(AZ90:AZ90) -> 12020.379
A100: Total Pine Tons | B100: =SUM(B82,B91) -> 0 | C100: =SUM(C82,C91) -> 9959.3071 | D100: =SUM(D82,D91) -> 4751.7809 | E100: =SUM(E82,E91) -> 6836.7937 | F100: =SUM(F82,F91) -> 19745.034 | G100: =SUM(G82,G91) -> 5430.6535 | H100: =SUM(H82,H91) -> 2857.348 | I100: =SUM(I82,I91) -> 2231.7607 | ... AZ100: =SUM(AZ82,AZ91) -> 29717.058
A101: % Pine Large Saw Timber | B101: =IF(B$100>0,(SUM(B96)/B$100),0) -> 0 | C101: =IF(C$100>0,(SUM(C96)/C$100),0) -> 0 | D101: =IF(D$100>0,(SUM(D96)/D$100),0) -> 0 | E101: =IF(E$100>0,(SUM(E96)/E$100),0) -> 0.0014496796 | F101: =IF(F$100>0,(SUM(F96)/F$100),0) -> 0.0082456432 | G101: =IF(G$100>0,(SUM(G96)/G$100),0) -> 0 | H101: =IF(H$100>0,(SUM(H96)/H$100),0) -> 0 | I101: =IF(I$100>0,(SUM(I96)/I$100),0) -> 0 | ... AZ101: =IF(AZ$100>0,(SUM(AZ96)/AZ$100),0) -> 0.00015168715
A102: % Pine Saw Timber | B102: =IF(B$100>0,(SUM(B97)/B$100),0) -> 0 | C102: =IF(C$100>0,(SUM(C97)/C$100),0) -> 0.0014597103 | D102: =IF(D$100>0,(SUM(D97)/D$100),0) -> 0.0046429504 | E102: =IF(E$100>0,(SUM(E97)/E$100),0) -> 0.0035300672 | F102: =IF(F$100>0,(SUM(F97)/F$100),0) -> 0 | G102: =IF(G$100>0,(SUM(G97)/G$100),0) -> 0.0015469269 | H102: =IF(H$100>0,(SUM(H97)/H$100),0) -> 0.0039455663 | I102: =IF(I$100>0,(SUM(I97)/I$100),0) -> 0.04795393 | ... AZ102: =IF(AZ$100>0,(SUM(AZ97)/AZ$100),0) -> 0.00015698879
A103: % Pine Chip-N-Saw | B103: =IF(B$100>0,(SUM(B98)/B$100),0) -> 0 | C103: =IF(C$100>0,(SUM(C98)/C$100),0) -> 0.45982249 | D103: =IF(D$100>0,(SUM(D98)/D$100),0) -> 0.3267578 | E103: =IF(E$100>0,(SUM(E98)/E$100),0) -> 0.48497005 | F103: =IF(F$100>0,(SUM(F98)/F$100),0) -> 0.36538323 | G103: =IF(G$100>0,(SUM(G98)/G$100),0) -> 0.108267 | H103: =IF(H$100>0,(SUM(H98)/H$100),0) -> 0.78749649 | I103: =IF(I$100>0,(SUM(I98)/I$100),0) -> 0.62935677 | ... AZ103: =IF(AZ$100>0,(SUM(AZ98)/AZ$100),0) -> 0.5951971
A104: % Pine Pulpwood | B104: =IF(B$100>0,(SUM(B99)/B$100),0) -> 0 | C104: =IF(C$100>0,(SUM(C99)/C$100),0) -> 0.5387178 | D104: =IF(D$100>0,(SUM(D99)/D$100),0) -> 0.66859925 | E104: =IF(E$100>0,(SUM(E99)/E$100),0) -> 0.5100502 | F104: =IF(F$100>0,(SUM(F99)/F$100),0) -> 0.62637113 | G104: =IF(G$100>0,(SUM(G99)/G$100),0) -> 0.89018607 | H104: =IF(H$100>0,(SUM(H99)/H$100),0) -> 0.20855794 | I104: =IF(I$100>0,(SUM(I99)/I$100),0) -> 0.3226893 | ... AZ104: =IF(AZ$100>0,(SUM(AZ99)/AZ$100),0) -> 0.40449423
A106: Selection Thin
A107: Thin Acres | B107: 0 | C107: 0 | D107: 0 | E107: 0 | F107: 0 | G107: 0 | H107: 0 | I107: 0 | J107: 0 | K107: 0 | L107: 0 | M107: 0 | N107: 0 | O107: 0 | P107: 0 | Q107: 0 | R107: 0 | S107: 0 | T107: 0 | U107: 0 | V107: 0 | W107: 0 | X107: 0 | Y107: 0 | Z107: 0 | AA107: 0 | AB107: 0 | AC107: 0 | AD107: 0 | AE107: 0 | AF107: 0 | AG107: 0 | AH107: 0 | AI107: 0 | AJ107: 0 | AK107: 0 | AL107: 0 | AM107: 0 | AN107: 0 | AO107: 0 | AP107: 0 | AQ107: 0 | AR107: 0 | AS107: 0 | AT107: 0 | AU107: 0 | AV107: 0 | AW107: 0 | AX107: 0 | AY107: 0 | AZ107: 0
A108: Pine Large Saw Timber | B108: 0 | C108: 0 | D108: 0 | E108: 0 | F108: 0 | G108: 0 | H108: 0 | I108: 0 | J108: 0 | K108: 0 | L108: 0 | M108: 0 | N108: 0 | O108: 0 | P108: 0 | Q108: 0 | R108: 0 | S108: 0 | T108: 0 | U108: 0 | V108: 0 | W108: 0 | X108: 0 | Y108: 0 | Z108: 0 | AA108: 0 | AB108: 0 | AC108: 0 | AD108: 0 | AE108: 0 | AF108: 0 | AG108: 0 | AH108: 0 | AI108: 0 | AJ108: 0 | AK108: 0 | AL108: 0 | AM108: 0 | AN108: 0 | AO108: 0 | AP108: 0 | AQ108: 0 | AR108: 0 | AS108: 0 | AT108: 0 | AU108: 0 | AV108: 0 | AW108: 0 | AX108: 0 | AY108: 0 | AZ108: 0
A109: Pine Saw Timber | B109: 0 | C109: 0 | D109: 0 | E109: 0 | F109: 0 | G109: 0 | H109: 0 | I109: 0 | J109: 0 | K109: 0 | L109: 0 | M109: 0 | N109: 0 | O109: 0 | P109: 0 | Q109: 0 | R109: 0 | S109: 0 | T109: 0 | U109: 0 | V109: 0 | W109: 0 | X109: 0 | Y109: 0 | Z109: 0 | AA109: 0 | AB109: 0 | AC109: 0 | AD109: 0 | AE109: 0 | AF109: 0 | AG109: 0 | AH109: 0 | AI109: 0 | AJ109: 0 | AK109: 0 | AL109: 0 | AM109: 0 | AN109: 0 | AO109: 0 | AP109: 0 | AQ109: 0 | AR109: 0 | AS109: 0 | AT109: 0 | AU109: 0 | AV109: 0 | AW109: 0 | AX109: 0 | AY109: 0 | AZ109: 0
...

Sheet Inventory Report
A1: DISCOUNTED CASH FLOW ANALYSIS
A2: Inventory Report
A3: =CONCATENATE('Model Assumptions'!B2, " - ",'Model Assumptions'!B3 ) -> IWC - Boot Hill
A4: ='Model Assumptions'!B5 -> IWC - Boothill - HSM
A6: Calendar Year >> | B6: Model Year 0 | C6: 2026 | D6: =C6+1 -> 2027 | E6: =D6+1 -> 2028 | F6: =E6+1 -> 2029 | G6: =F6+1 -> 2030 | H6: =G6+1 -> 2031 | I6: =H6+1 -> 2032 | J6: =I6+1 -> 2033 | K6: =J6+1 -> 2034 | ... AZ6: =AY6+1 -> 2075
A7: Model Discount Period >> | B7: 0 | C7: 1 | D7: =C7+1 -> 2 | E7: =D7+1 -> 3 | F7: =E7+1 -> 4 | G7: =F7+1 -> 5 | H7: =G7+1 -> 6 | I7: =H7+1 -> 7 | J7: =I7+1 -> 8 | K7: =J7+1 -> 9 | ... AZ7: =AY7+1 -> 50
A9: Total Acres | B9: 12404.89 | C9: 12404.89 | D9: 12404.89 | E9: 12404.89 | F9: 12404.89 | G9: 12404.89 | H9: 12404.89 | I9: 12404.89 | J9: 12404.89 | K9: 12404.89 | L9: 12404.89 | M9: 12404.89 | N9: 12404.89 | O9: 12404.89 | P9: 12404.89 | Q9: 12404.89 | R9: 12404.89 | S9: 12404.89 | T9: 12404.89 | U9: 12404.89 | V9: 12404.89 | W9: 12404.89 | X9: 12404.89 | Y9: 12404.89 | Z9: 12404.89 | AA9: 12404.89 | AB9: 12404.89 | AC9: 12404.89 | AD9: 12404.89 | AE9: 12404.89 | AF9: 12404.89 | AG9: 12404.89 | AH9: 12404.89 | AI9: 12404.89 | AJ9: 12404.89 | AK9: 12404.89 | AL9: 12404.89 | AM9: 12404.89 | AN9: 12404.89 | AO9: 12404.89 | AP9: 12404.89 | AQ9: 12404.89 | AR9: 12404.89 | AS9: 12404.89 | AT9: 12404.89 | AU9: 12404.89 | AV9: 12404.89 | AW9: 12404.89 | AX9: 12404.89 | AY9: 12404.89 | AZ9: 12404.89
A10: Productive Plantation Acres | B10: 8762.98 | C10: 8762.98 | D10: 8762.98 | E10: 8762.98 | F10: 8762.98 | G10: 8762.98 | H10: 8762.98 | I10: 8762.98 | J10: 8762.98 | K10: 8762.98 | L10: 8762.98 | M10: 8762.98 | N10: 8762.98 | O10: 8762.98 | P10: 8762.98 | Q10: 8762.98 | R10: 8762.98 | S10: 8762.98 | T10: 8762.98 | U10: 8762.98 | V10: 8762.98 | W10: 8762.98 | X10: 8762.98 | Y10: 8762.98 | Z10: 8762.98 | AA10: 8762.98 | AB10: 8762.98 | AC10: 8762.98 | AD10: 8762.98 | AE10: 8762.98 | AF10: 8762.98 | AG10: 8762.98 | AH10: 8762.98 | AI10: 8762.98 | AJ10: 8762.98 | AK10: 8762.98 | AL10: 8762.98 | AM10: 8762.98 | AN10: 8762.98 | AO10: 8762.98 | AP10: 8762.98 | AQ10: 8762.98 | AR10: 8762.98 | AS10: 8762.98 | AT10: 8762.98 | AU10: 8762.98 | AV10: 8762.98 | AW10: 8762.98 | AX10: 8762.98 | AY10: 8762.98 | AZ10: 8762.98
A11: Natural Convertible Acres | B11: 611.17 | C11: 611.17 | D11: 611.17 | E11: 611.17 | F11: 611.17 | G11: 611.17 | H11: 611.17 | I11: 611.17 | J11: 611.17 | K11: 611.17 | L11: 611.17 | M11: 611.17 | N11: 611.17 | O11: 611.17 | P11: 611.17 | Q11: 611.17 | R11: 611.17 | S11: 611.17 | T11: 611.17 | U11: 611.17 | V11: 611.17 | W11: 611.17 | X11: 611.17 | Y11: 611.17 | Z11: 611.17 | AA11: 611.17 | AB11: 611.17 | AC11: 611.17 | AD11: 611.17 | AE11: 611.17 | AF11: 611.17 | AG11: 611.17 | AH11: 611.17 | AI11: 611.17 | AJ11: 611.17 | AK11: 611.17 | AL11: 611.17 | AM11: 611.17 | AN11: 611.17 | AO11: 611.17 | AP11: 611.17 | AQ11: 611.17 | AR11: 611.17 | AS11: 611.17 | AT11: 611.17 | AU11: 611.17 | AV11: 611.17 | AW11: 611.17 | AX11: 611.17 | AY11: 611.17 | AZ11: 611.17
A12: Non-Converitble Acres | B12: 3030.74 | C12: 3030.74 | D12: 3030.74 | E12: 3030.74 | F12: 3030.74 | G12: 3030.74 | H12: 3030.74 | I12: 3030.74 | J12: 3030.74 | K12: 3030.74 | L12: 3030.74 | M12: 3030.74 | N12: 3030.74 | O12: 3030.74 | P12: 3030.74 | Q12: 3030.74 | R12: 3030.74 | S12: 3030.74 | T12: 3030.74 | U12: 3030.74 | V12: 3030.74 | W12: 3030.74 | X12: 3030.74 | Y12: 3030.74 | Z12: 3030.74 | AA12: 3030.74 | AB12: 3030.74 | AC12: 3030.74 | AD12: 3030.74 | AE12: 3030.74 | AF12: 3030.74 | AG12: 3030.74 | AH12: 3030.74 | AI12: 3030.74 | AJ12: 3030.74 | AK12: 3030.74 | AL12: 3030.74 | AM12: 3030.74 | AN12: 3030.74 | AO12: 3030.74 | AP12: 3030.74 | AQ12: 3030.74 | AR12: 3030.74 | AS12: 3030.74 | AT12: 3030.74 | AU12: 3030.74 | AV12: 3030.74 | AW12: 3030.74 | AX12: 3030.74 | AY12: 3030.74 | AZ12: 3030.74
A14: Harvest Acres | B14: 0 | C14: 919.96 | D14: 193.34 | E14: 699.1804 | F14: 576.8 | G14: 421.71 | H14: 119.68 | I14: 645.2214 | J14: 1479.316 | K14: 817.0594 | L14: 703.2174 | M14: 459.6524 | N14: 1242.6004 | O14: 662.5206 | P14: 1338.2898 | Q14: 929.28 | R14: 809.49 | S14: 453.22 | T14: 213.74 | U14: 981.9564 | V14: 273.6928 | W14: 365.9684 | X14: 254.00407 | Y14: 1626.1983 | Z14: 2098.8264 | AA14: 251.34 | AB14: 664.15 | AC14: 345.62 | AD14: 1058.01 | AE14: 251.9736 | AF14: 1081.33 | AG14: 1402.99 | AH14: 347.19 | AI14: 215.14 | AJ14: 984.0868 | AK14: 858.55 | AL14: 412.0532 | AM14: 337.29 | AN14: 1312.085 | AO14: 1667.4954 | AP14: 1326.6564 | AQ14: 681.69 | AR14: 558.9724 | AS14: 1125.025 | AT14: 207.81 | AU14: 1193.5536 | AV14: 577.3024 | AW14: 186.6002 | AX14: 330.6838 | AY14: 1501.39 | AZ14: 2222.5636
A16: LAND USE ACRES
A17: Timber Deed / Easement Acres | B17: 0 | C17: 0 | D17: 0 | E17: 0 | F17: 0 | G17: 0 | H17: 0 | I17: 0 | J17: 0 | K17: 0 | L17: 0 | M17: 0 | N17: 0 | O17: 0 | P17: 0 | Q17: 0 | R17: 0 | S17: 0 | T17: 0 | U17: 0 | V17: 0 | W17: 0 | X17: 0 | Y17: 0 | Z17: 0 | AA17: 0 | AB17: 0 | AC17: 0 | AD17: 0 | AE17: 0 | AF17: 0 | AG17: 0 | AH17: 0 | AI17: 0 | AJ17: 0 | AK17: 0 | AL17: 0 | AM17: 0 | AN17: 0 | AO17: 0 | AP17: 0 | AQ17: 0 | AR17: 0 | AS17: 0 | AT17: 0 | AU17: 0 | AV17: 0 | AW17: 0 | AX17: 0 | AY17: 0 | AZ17: 0
A18: Long Term Timberland | B18: 12404.89 | C18: 12404.89 | D18: 12404.89 | E18: 12404.89 | F18: 12404.89 | G18: 12404.89 | H18: 12404.89 | I18: 12404.89 | J18: 12404.89 | K18: 12404.89 | L18: 12404.89 | M18: 12404.89 | N18: 12404.89 | O18: 12404.89 | P18: 12404.89 | Q18: 12404.89 | R18: 12404.89 | S18: 12404.89 | T18: 12404.89 | U18: 12404.89 | V18: 12404.89 | W18: 12404.89 | X18: 12404.89 | Y18: 12404.89 | Z18: 12404.89 | AA18: 12404.89 | AB18: 12404.89 | AC18: 12404.89 | AD18: 12404.89 | AE18: 12404.89 | AF18: 12404.89 | AG18: 12404.89 | AH18: 12404.89 | AI18: 12404.89 | AJ18: 12404.89 | AK18: 12404.89 | AL18: 12404.89 | AM18: 12404.89 | AN18: 12404.89 | AO18: 12404.89 | AP18: 12404.89 | AQ18: 12404.89 | AR18: 12404.89 | AS18: 12404.89 | AT18: 12404.89 | AU18: 12404.89 | AV18: 12404.89 | AW18: 12404.89 | AX18: 12404.89 | AY18: 12404.89 | AZ18: 12404.89
A19: Total Acres | B19: 12404.89 | C19: 12404.89 | D19: 12404.89 | E19: 12404.89 | F19: 12404.89 | G19: 12404.89 | H19: 12404.89 | I19: 12404.89 | J19: 12404.89 | K19: 12404.89 | L19: 12404.89 | M19: 12404.89 | N19: 12404.89 | O19: 12404.89 | P19: 12404.89 | Q19: 12404.89 | R19: 12404.89 | S19: 12404.89 | T19: 12404.89 | U19: 12404.89 | V19: 12404.89 | W19: 12404.89 | X19: 12404.89 | Y19: 12404.89 | Z19: 12404.89 | AA19: 12404.89 | AB19: 12404.89 | AC19: 12404.89 | AD19: 12404.89 | AE19: 12404.89 | AF19: 12404.89 | AG19: 12404.89 | AH19: 12404.89 | AI19: 12404.89 | AJ19: 12404.89 | AK19: 12404.89 | AL19: 12404.89 | AM19: 12404.89 | AN19: 12404.89 | AO19: 12404.89 | AP19: 12404.89 | AQ19: 12404.89 | AR19: 12404.89 | AS19: 12404.89 | AT19: 12404.89 | AU19: 12404.89 | AV19: 12404.89 | AW19: 12404.89 | AX19: 12404.89 | AY19: 12404.89 | AZ19: 12404.89
A21: MANAGEMENT COVER TYPE ACRES
A22: Productive Plantation Acres | B22: 8762.98 | C22: 8762.98 | D22: 8762.98 | E22: 8762.98 | F22: 8762.98 | G22: 8762.98 | H22: 8762.98 | I22: 8762.98 | J22: 8762.98 | K22: 8762.98 | L22: 8762.98 | M22: 8762.98 | N22: 8762.98 | O22: 8762.98 | P22: 8762.98 | Q22: 8762.98 | R22: 8762.98 | S22: 8762.98 | T22: 8762.98 | U22: 8762.98 | V22: 8762.98 | W22: 8762.98 | X22: 8762.98 | Y22: 8762.98 | Z22: 8762.98 | AA22: 8762.98 | AB22: 8762.98 | AC22: 8762.98 | AD22: 8762.98 | AE22: 8762.98 | AF22: 8762.98 | AG22: 8762.98 | AH22: 8762.98 | AI22: 8762.98 | AJ22: 8762.98 | AK22: 8762.98 | AL22: 8762.98 | AM22: 8762.98 | AN22: 8762.98 | AO22: 8762.98 | AP22: 8762.98 | AQ22: 8762.98 | AR22: 8762.98 | AS22: 8762.98 | AT22: 8762.98 | AU22: 8762.98 | AV22: 8762.98 | AW22: 8762.98 | AX22: 8762.98 | AY22: 8762.98 | AZ22: 8762.98
A23: Cutover | B23: 215.79 | C23: 374.34 | D23: 0 | E23: 445.02 | F23: 0 | G23: 209 | H23: 0 | I23: 550.07 | J23: 676.8 | K23: 29.47 | L23: 480.87 | M23: 345.62 | N23: 955.52 | O23: 35.53 | P23: 535.99 | Q23: 570.39 | R23: 25.51 | S23: 10.19 | T23: 159.25 | U23: 206.44 | V23: 168.46 | W23: 44.42 | X23: 249.0236 | Y23: 978.2064 | Z23: 1338.7564 | AA23: 0 | AB23: 0 | AC23: 0 | AD23: 59.25 | AE23: 206.9336 | AF23: 0 | AG23: 160.58 | AH23: 321.68 | AI23: 0 | AJ23: 456.38 | AK23: 0 | AL23: 197.64 | AM23: 0 | AN23: 550.07 | AO23: 676.8 | AP23: 29.47 | AQ23: 480.87 | AR23: 345.62 | AS23: 955.52 | AT23: 35.53 | AU23: 535.99 | AV23: 570.39 | AW23: 25.51 | AX23: 10.19 | AY23: 1474.0464 | AZ23: 1500
A24: Site Prepped | B24: 0 | C24: 215.79 | D24: 374.34 | E24: 0 | F24: 445.02 | G24: 0 | H24: 209 | I24: 0 | J24: 550.07 | K24: 676.8 | L24: 29.47 | M24: 480.87 | N24: 345.62 | O24: 955.52 | P24: 35.53 | Q24: 535.99 | R24: 570.39 | S24: 25.51 | T24: 10.19 | U24: 159.25 | V24: 206.44 | W24: 168.46 | X24: 44.42 | Y24: 249.0236 | Z24: 978.2064 | AA24: 1338.7564 | AB24: 0 | AC24: 0 | AD24: 0 | AE24: 59.25 | AF24: 206.9336 | AG24: 0 | AH24: 160.58 | AI24: 321.68 | AJ24: 0 | AK24: 456.38 | AL24: 0 | AM24: 197.64 | AN24: 0 | AO24: 550.07 | AP24: 676.8 | AQ24: 29.47 | AR24: 480.87 | AS24: 345.62 | AT24: 955.52 | AU24: 35.53 | AV24: 535.99 | AW24: 570.39 | AX24: 25.51 | AY24: 10.19 | AZ24: 1474.0464
A25: Pine Plantation | B25: 8516.96 | C25: 8144.01 | D25: 8359.8 | E25: 8314.73 | F25: 8314.73 | G25: 8550.75 | H25: 8550.75 | I25: 8209.68 | J25: 7532.88 | K25: 8053.48 | L25: 8249.41 | M25: 7933.26 | N25: 7458.61 | O25: 7768.7 | P25: 8188.23 | Q25: 7653.37 | R25: 8167.08 | S25: 8727.28 | T25: 8593.54 | U25: 8397.29 | V25: 8388.08 | W25: 8550.1 | X25: 8469.5364 | Y25: 7535.75 | Z25: 6446.0172 | AA25: 7424.2236 | AB25: 8762.98 | AC25: 8762.98 | AD25: 8703.73 | AE25: 8496.7964 | AF25: 8556.0464 | AG25: 8602.4 | AH25: 8280.72 | AI25: 8441.3 | AJ25: 8306.6 | AK25: 8306.6 | AL25: 8565.34 | AM25: 8565.34 | AN25: 8212.91 | AO25: 7536.11 | AP25: 8056.71 | AQ25: 8252.64 | AR25: 7936.49 | AS25: 7461.84 | AT25: 7771.93 | AU25: 8191.46 | AV25: 7656.6 | AW25: 8167.08 | AX25: 8727.28 | AY25: 7278.7436 | AZ25: 5788.9336
A26: Hardwood Plantation | B26: 30.23 | C26: 28.84 | D26: 28.84 | E26: 3.23 | F26: 3.23 | G26: 3.23 | H26: 3.23 | I26: 3.23 | J26: 3.23 | K26: 3.23 | L26: 3.23 | M26: 3.23 | N26: 3.23 | O26: 3.23 | P26: 3.23 | Q26: 3.23 | R26: 0 | S26: 0 | T26: 0 | U26: 0 | V26: 0 | W26: 0 | X26: 0 | Y26: 0 | Z26: 0 | AA26: 0 | AB26: 0 | AC26: 0 | AD26: 0 | AE26: 0 | AF26: 0 | AG26: 0 | AH26: 0 | AI26: 0 | AJ26: 0 | AK26: 0 | AL26: 0 | AM26: 0 | AN26: 0 | AO26: 0 | AP26: 0 | AQ26: 0 | AR26: 0 | AS26: 0 | AT26: 0 | AU26: 0 | AV26: 0 | AW26: 0 | AX26: 0 | AY26: 0 | AZ26: 0
A27: Natural Convertible Acres | B27: 611.17 | C27: 611.17 | D27: 611.17 | E27: 611.17 | F27: 611.17 | G27: 611.17 | H27: 611.17 | I27: 611.17 | J27: 611.17 | K27: 611.17 | L27: 611.17 | M27: 611.17 | N27: 611.17 | O27: 611.17 | P27: 611.17 | Q27: 611.17 | R27: 611.17 | S27: 611.17 | T27: 611.17 | U27: 611.17 | V27: 611.17 | W27: 611.17 | X27: 611.17 | Y27: 611.17 | Z27: 611.17 | AA27: 611.17 | AB27: 611.17 | AC27: 611.17 | AD27: 611.17 | AE27: 611.17 | AF27: 611.17 | AG27: 611.17 | AH27: 611.17 | AI27: 611.17 | AJ27: 611.17 | AK27: 611.17 | AL27: 611.17 | AM27: 611.17 | AN27: 611.17 | AO27: 611.17 | AP27: 611.17 | AQ27: 611.17 | AR27: 611.17 | AS27: 611.17 | AT27: 611.17 | AU27: 611.17 | AV27: 611.17 | AW27: 611.17 | AX27: 611.17 | AY27: 611.17 | AZ27: 611.17
A28: Pine | B28: 223.7 | C28: 223.7 | D28: 223.7 | E28: 223.7 | F28: 223.7 | G28: 223.7 | H28: 223.7 | I28: 223.7 | J28: 223.7 | K28: 223.7 | L28: 223.7 | M28: 223.7 | N28: 223.7 | O28: 223.7 | P28: 223.7 | Q28: 223.7 | R28: 223.7 | S28: 223.7 | T28: 223.7 | U28: 223.7 | V28: 223.7 | W28: 223.7 | X28: 223.7 | Y28: 223.7 | Z28: 223.7 | AA28: 223.7 | AB28: 223.7 | AC28: 223.7 | AD28: 223.7 | AE28: 223.7 | AF28: 223.7 | AG28: 223.7 | AH28: 223.7 | AI28: 223.7 | AJ28: 223.7 | AK28: 223.7 | AL28: 223.7 | AM28: 223.7 | AN28: 223.7 | AO28: 223.7 | AP28: 223.7 | AQ28: 223.7 | AR28: 223.7 | AS28: 223.7 | AT28: 223.7 | AU28: 223.7 | AV28: 223.7 | AW28: 223.7 | AX28: 223.7 | AY28: 223.7 | AZ28: 223.7
A29: Hardwood/Cypress | B29: 387.47 | C29: 387.47 | D29: 387.47 | E29: 387.47 | F29: 387.47 | G29: 387.47 | H29: 387.47 | I29: 387.47 | J29: 387.47 | K29: 387.47 | L29: 387.47 | M29: 387.47 | N29: 387.47 | O29: 387.47 | P29: 387.47 | Q29: 387.47 | R29: 387.47 | S29: 387.47 | T29: 387.47 | U29: 387.47 | V29: 387.47 | W29: 387.47 | X29: 387.47 | Y29: 387.47 | Z29: 387.47 | AA29: 387.47 | AB29: 387.47 | AC29: 387.47 | AD29: 387.47 | AE29: 387.47 | AF29: 387.47 | AG29: 387.47 | AH29: 387.47 | AI29: 387.47 | AJ29: 387.47 | AK29: 387.47 | AL29: 387.47 | AM29: 387.47 | AN29: 387.47 | AO29: 387.47 | AP29: 387.47 | AQ29: 387.47 | AR29: 387.47 | AS29: 387.47 | AT29: 387.47 | AU29: 387.47 | AV29: 387.47 | AW29: 387.47 | AX29: 387.47 | AY29: 387.47 | AZ29: 387.47
A30: Non-Converitble Acres | B30: 3030.74 | C30: 3030.74 | D30: 3030.74 | E30: 3030.74 | F30: 3030.74 | G30: 3030.74 | H30: 3030.74 | I30: 3030.74 | J30: 3030.74 | K30: 3030.74 | L30: 3030.74 | M30: 3030.74 | N30: 3030.74 | O30: 3030.74 | P30: 3030.74 | Q30: 3030.74 | R30: 3030.74 | S30: 3030.74 | T30: 3030.74 | U30: 3030.74 | V30: 3030.74 | W30: 3030.74 | X30: 3030.74 | Y30: 3030.74 | Z30: 3030.74 | AA30: 3030.74 | AB30: 3030.74 | AC30: 3030.74 | AD30: 3030.74 | AE30: 3030.74 | AF30: 3030.74 | AG30: 3030.74 | AH30: 3030.74 | AI30: 3030.74 | AJ30: 3030.74 | AK30: 3030.74 | AL30: 3030.74 | AM30: 3030.74 | AN30: 3030.74 | AO30: 3030.74 | AP30: 3030.74 | AQ30: 3030.74 | AR30: 3030.74 | AS30: 3030.74 | AT30: 3030.74 | AU30: 3030.74 | AV30: 3030.74 | AW30: 3030.74 | AX30: 3030.74 | AY30: 3030.74 | AZ30: 3030.74
A31: Open - Roads, Water, etc. | B31: 530.29 | C31: 530.29 | D31: 530.29 | E31: 530.29 | F31: 530.29 | G31: 530.29 | H31: 530.29 | I31: 530.29 | J31: 530.29 | K31: 530.29 | L31: 530.29 | M31: 530.29 | N31: 530.29 | O31: 530.29 | P31: 530.29 | Q31: 530.29 | R31: 530.29 | S31: 530.29 | T31: 530.29 | U31: 530.29 | V31: 530.29 | W31: 530.29 | X31: 530.29 | Y31: 530.29 | Z31: 530.29 | AA31: 530.29 | AB31: 530.29 | AC31: 530.29 | AD31: 530.29 | AE31: 530.29 | AF31: 530.29 | AG31: 530.29 | AH31: 530.29 | AI31: 530.29 | AJ31: 530.29 | AK31: 530.29 | AL31: 530.29 | AM31: 530.29 | AN31: 530.29 | AO31: 530.29 | AP31: 530.29 | AQ31: 530.29 | AR31: 530.29 | AS31: 530.29 | AT31: 530.29 | AU31: 530.29 | AV31: 530.29 | AW31: 530.29 | AX31: 530.29 | AY31: 530.29 | AZ31: 530.29
A32: Natural Nonconvertible - Available | B32: 2500.45 | C32: 2500.45 | D32: 2500.45 | E32: 2500.45 | F32: 2500.45 | G32: 2500.45 | H32: 2500.45 | I32: 2500.45 | J32: 2500.45 | K32: 2500.45 | L32: 2500.45 | M32: 2500.45 | N32: 2500.45 | O32: 2500.45 | P32: 2500.45 | Q32: 2500.45 | R32: 2500.45 | S32: 2500.45 | T32: 2500.45 | U32: 2500.45 | V32: 2500.45 | W32: 2500.45 | X32: 2500.45 | Y32: 2500.45 | Z32: 2500.45 | AA32: 2500.45 | AB32: 2500.45 | AC32: 2500.45 | AD32: 2500.45 | AE32: 2500.45 | AF32: 2500.45 | AG32: 2500.45 | AH32: 2500.45 | AI32: 2500.45 | AJ32: 2500.45 | AK32: 2500.45 | AL32: 2500.45 | AM32: 2500.45 | AN32: 2500.45 | AO32: 2500.45 | AP32: 2500.45 | AQ32: 2500.45 | AR32: 2500.45 | AS32: 2500.45 | AT32: 2500.45 | AU32: 2500.45 | AV32: 2500.45 | AW32: 2500.45 | AX32: 2500.45 | AY32: 2500.45 | AZ32: 2500.45
A33: Natural Nonconvertible - Unavailable | B33: 0 | C33: 0 | D33: 0 | E33: 0 | F33: 0 | G33: 0 | H33: 0 | I33: 0 | J33: 0 | K33: 0 | L33: 0 | M33: 0 | N33: 0 | O33: 0 | P33: 0 | Q33: 0 | R33: 0 | S33: 0 | T33: 0 | U33: 0 | V33: 0 | W33: 0 | X33: 0 | Y33: 0 | Z33: 0 | AA33: 0 | AB33: 0 | AC33: 0 | AD33: 0 | AE33: 0 | AF33: 0 | AG33: 0 | AH33: 0 | AI33: 0 | AJ33: 0 | AK33: 0 | AL33: 0 | AM33: 0 | AN33: 0 | AO33: 0 | AP33: 0 | AQ33: 0 | AR33: 0 | AS33: 0 | AT33: 0 | AU33: 0 | AV33: 0 | AW33: 0 | AX33: 0 | AY33: 0 | AZ33: 0
A34: Total Acres | B34: 12404.89 | C34: 12404.89 | D34: 12404.89 | E34: 12404.89 | F34: 12404.89 | G34: 12404.89 | H34: 12404.89 | I34: 12404.89 | J34: 12404.89 | K34: 12404.89 | L34: 12404.89 | M34: 12404.89 | N34: 12404.89 | O34: 12404.89 | P34: 12404.89 | Q34: 12404.89 | R34: 12404.89 | S34: 12404.89 | T34: 12404.89 | U34: 12404.89 | V34: 12404.89 | W34: 12404.89 | X34: 12404.89 | Y34: 12404.89 | Z34: 12404.89 | AA34: 12404.89 | AB34: 12404.89 | AC34: 12404.89 | AD34: 12404.89 | AE34: 12404.89 | AF34: 12404.89 | AG34: 12404.89 | AH34: 12404.89 | AI34: 12404.89 | AJ34: 12404.89 | AK34: 12404.89 | AL34: 12404.89 | AM34: 12404.89 | AN34: 12404.89 | AO34: 12404.89 | AP34: 12404.89 | AQ34: 12404.89 | AR34: 12404.89 | AS34: 12404.89 | AT34: 12404.89 | AU34: 12404.89 | AV34: 12404.89 | AW34: 12404.89 | AX34: 12404.89 | AY34: 12404.89 | AZ34: 12404.89
A36: =CONCATENATE("Premech Plt Acres (ages 1-",'Model Assumptions'!B19-1,")",) -> Premech Plt Acres (ages 1-11) | B36: 3494.56 | C36: 3063.81 | D36: 3078.91 | E36: 3358.85 | F36: 3358.85 | G36: 3368.53 | H36: 2587.07 | I36: 2583.34 | J36: 2583.34 | K36: 2865.44 | L36: 2915.96 | M36: 2500.49 | N36: 2981.36 | O36: 3111.19 | P36: 3692.37 | Q36: 3727.9 | R36: 3818.87 | S36: 4389.26 | T36: 4205.77 | U36: 4215.96 | V36: 3825.14 | W36: 3354.78 | X36: 3493.77 | Y36: 3057.32 | Z36: 2960.7236 | AA36: 2983.41 | AB36: 4286.6364 | AC36: 3750.6464 | AD36: 3180.2564 | AE36: 3154.7464 | AF36: 3203.8064 | AG36: 3251.49 | AH36: 3045.05 | AI36: 3037.17 | AJ36: 3314.43 | AK36: 3065.4064 | AL36: 2543.58 | AM36: 1204.8236 | AN36: 1402.4636 | AO36: 1402.4636 | AP36: 1952.5336 | AQ36: 2570.0836 | AR36: 2392.62 | AS36: 2873.49 | AT36: 3058.53 | AU36: 3692.37 | AV36: 3727.9 | AW36: 3807.51 | AX36: 4377.9 | AY36: 4205.77 | AZ36: 4215.96
A38: Residual Inventory (tons)
A39: Plantation Management
A40: Merchantable Acres | B40: 5052.63 | C40: 5109.04 | D40: 5309.73 | E40: 4959.11 | F40: 4959.11 | G40: 5185.45 | H40: 5966.91 | I40: 5629.57 | J40: 4952.77 | K40: 5191.27 | L40: 5336.68 | M40: 5436 | N40: 4480.48 | O40: 4660.74 | P40: 4499.09 | Q40: 3928.7 | R40: 4348.21 | S40: 4338.02 | T40: 4387.77 | U40: 4181.33 | V40: 4562.94 | W40: 5195.32 | X40: 4975.7664 | Y40: 4478.43 | Z40: 3485.2936 | AA40: 4440.8136 | AB40: 4476.3436 | AC40: 5012.3336 | AD40: 5523.4736 | AE40: 5342.05 | AF40: 5352.24 | AG40: 5350.91 | AH40: 5235.67 | AI40: 5404.13 | AJ40: 4992.17 | AK40: 5241.1936 | AL40: 6021.76 | AM40: 7360.5164 | AN40: 6810.4464 | AO40: 6133.6464 | AP40: 6104.1764 | AQ40: 5682.5564 | AR40: 5543.87 | AS40: 4588.35 | AT40: 4713.4 | AU40: 4499.09 | AV40: 3928.7 | AW40: 4359.57 | AX40: 4349.38 | AY40: 3072.9736 | AZ40: 1572.9736
A41: =CONCATENATE("Merchantable Tons (Age ",'Model Assumptions'!B19,"+)") -> Merchantable Tons (Age 12+)
A42: Pine Large Saw Timber | B42: 3867.6801 | C42: 4083.8374 | D42: 5220.8023 | E42: 2837.1511 | F42: 3579.794 | G42: 4382.9353 | H42: 5771.1605 | I42: 4860.5845 | J42: 5684.616 | K42: 7029.0076 | L42: 8474.5451 | M42: 10263.306 | N42: 2569.295 | O42: 4329.1934 | P42: 6265.88 | Q42: 8172.019 | R42: 10294.199 | S42: 12975.608 | T42: 16256.41 | U42: 17785.784 | V42: 21709.54 | W42: 25990.858 | X42: 30888.599 | Y42: 36240.939 | Z42: 4470.3279 | AA42: 6732.4984 | AB42: 9395.5857 | AC42: 12464.163 | AD42: 14183.729 | AE42: 12712.365 | AF42: 16761.823 | AG42: 19380.219 | AH42: 20533.05 | AI42: 25034.944 | AJ42: 12058.707 | AK42: 15655.888 | AL42: 17899.939 | AM42: 21017.936 | AN42: 10599.987 | AO42: 6171.4744 | AP42: 7874.0942 | AQ42: 9381.3815 | AR42: 10837.867 | AS42: 1964.3522 | AT42: 2738.1973 | AU42: 2744.3888 | AV42: 4025.7941 | AW42: 5294.524 | AX42: 7256.0718 | AY42: 4423.2888 | AZ42: 351.61404
A43: Pine Saw Timber | B43: 4383.4702 | C43: 5119.8863 | D43: 6540.9553 | E43: 7040.9206 | F43: 9070.2985 | G43: 11805.872 | H43: 15248.438 | I43: 16836.257 | J43: 19134.488 | K43: 24739.454 | L43: 29681.696 | M43: 31569.25 | N43: 29334.842 | O43: 34564.934 | P43: 32765.899 | Q43: 18846.335 | R43: 23654.955 | S43: 31303.989 | T43: 38362.928 | U43: 46089.885 | V43: 51659.145 | W43: 56357.915 | X43: 44882.625 | Y43: 31028.548 | Z43: 1662.8869 | AA43: 2290.9955 | AB43: 2923.8227 | AC43: 4109.0079 | AD43: 5582.4595 | AE43: 3549.5219 | AF43: 5480.8108 | AG43: 8716.5113 | AH43: 10933.425 | AI43: 16610.82 | AJ43: 24803.723 | AK43: 34923.963 | AL43: 45048.011 | AM43: 55518.573 | AN43: 58818.374 | AO43: 37656.077 | AP43: 47356.491 | AQ43: 42927.611 | AR43: 39246.692 | AS43: 34480.193 | AT43: 39379.847 | AU43: 38626.744 | AV43: 7846.2544 | AW43: 10752.081 | AX43: 14366.555 | AY43: 6172.8724 | AZ43: 343.96306
A44: Pine Chip-N-Saw | B44: 197565.16 | C44: 197804.69 | D44: 223598.69 | E44: 215340.92 | F44: 230438.65 | G44: 259554.79 | H44: 315034.98 | I44: 305733.22 | J44: 280043.01 | K44: 286321.39 | L44: 272993.93 | M44: 265019.6 | N44: 217620.91 | O44: 262616.34 | P44: 236218.14 | Q44: 211921.56 | R44: 220512.63 | S44: 232280.9 | T44: 237559.44 | U44: 219737.56 | V44: 234370.63 | W44: 279985.99 | X44: 290638.34 | Y44: 244604.16 | Z44: 170519.83 | AA44: 194168.67 | AB44: 208387.51 | AC44: 227841.55 | AD44: 270406.42 | AE44: 290934.81 | AF44: 295140.84 | AG44: 262539.54 | AH44: 277086.37 | AI44: 287753.67 | AJ44: 274070.16 | AK44: 267551.77 | AL44: 274441.91 | AM44: 296320.98 | AN44: 270509.65 | AO44: 264609.61 | AP44: 269718.43 | AQ44: 269456.1 | AR44: 271778.12 | AS44: 225475.33 | AT44: 238805.38 | AU44: 198602.21 | AV44: 189164.39 | AW44: 221636.5 | AX44: 237753.26 | AY44: 162940.18 | AZ44: 54187.194
A45: Pine Pulpwood | B45: 140623.44 | C45: 145275.48 | D45: 150148.38 | E45: 135730.62 | F45: 124351.41 | G45: 140438.57 | H45: 199500.97 | I45: 203687.46 | J45: 173742.39 | K45: 143289.37 | L45: 125751.98 | M45: 136037.19 | N45: 137967.34 | O45: 156136.32 | P45: 133150.51 | Q45: 118492.47 | R45: 123000.48 | S45: 117182.35 | T45: 121254.99 | U45: 107099.02 | V45: 132773.34 | W45: 160187.23 | X45: 156552.79 | Y45: 134353.77 | Z45: 80407.811 | AA45: 126600.93 | AB45: 122171.39 | AC45: 142176.37 | AD45: 140305.83 | AE45: 135003.01 | AF45: 119038.43 | AG45: 109480.19 | AH45: 110181.73 | AI45: 120152.43 | AJ45: 97118.616 | AK45: 104453.56 | AL45: 136361.56 | AM45: 197941.36 | AN45: 173635.04 | AO45: 137450.68 | AP45: 110310.37 | AQ45: 102844.81 | AR45: 105115.14 | AS45: 82430.983 | AT45: 85611.925 | AU45: 79458.107 | AV45: 72050.072 | AW45: 91565.335 | AX45: 88485.339 | AY45: 66385.404 | AZ45: 27898.992
A46: Total Pine Tons | B46: =SUM(B42:B45) -> 346439.76 | C46: =SUM(C42:C45) -> 352283.89 | D46: =SUM(D42:D45) -> 385508.83 | E46: =SUM(E42:E45) -> 360949.6 | F46: =SUM(F42:F45) -> 367440.15 | G46: =SUM(G42:G45) -> 416182.17 | H46: =SUM(H42:H45) -> 535555.55 | I46: =SUM(I42:I45) -> 531117.52 | ... AZ46: =SUM(AZ42:AZ45) -> 82781.763
A47: HW Saw Timber | B47: 1123.4785 | C47: 869.72976 | D47: 961.12483 | E47: 455.90613 | F47: 416.09158 | G47: 384.31369 | H47: 423.19658 | I47: 226.06471 | J47: 217.13405 | K47: 222.28893 | L47: 214.35843 | M47: 206.77485 | N47: 94.314681 | O47: 102.54389 | P47: 93.278662 | Q47: 80.501171 | R47: 85.515951 | S47: 93.876562 | T47: 40.5762 | U47: 45.7572 | V47: 0 | W47: 0 | X47: 0 | Y47: 0 | Z47: 0 | AA47: 0 | AB47: 0 | AC47: 0 | AD47: 0 | AE47: 0 | AF47: 0 | AG47: 0 | AH47: 0 | AI47: 0 | AJ47: 0 | AK47: 0 | AL47: 0 | AM47: 0 | AN47: 0 | AO47: 0 | AP47: 0 | AQ47: 0 | AR47: 0 | AS47: 0 | AT47: 0 | AU47: 0 | AV47: 0 | AW47: 0 | AX47: 0 | AY47: 0 | AZ47: 0
A48: HW Pulpwood | B48: 13560.394 | C48: 10274.94 | D48: 10232.518 | E48: 6253.8774 | F48: 5326.4592 | G48: 4931.657 | H48: 5145.7434 | I48: 3694.8284 | J48: 3495.534 | K48: 3536.4245 | L48: 3584.7372 | M48: 3533.5642 | N48: 602.4383 | O48: 624.74174 | P48: 606.63967 | Q48: 574.98657 | R48: 586.62718 | S48: 611.92393 | T48: 522.02598 | U48: 549.04298 | V48: 0 | W48: 0 | X48: 0 | Y48: 0 | Z48: 0 | AA48: 0 | AB48: 0 | AC48: 0 | AD48: 0 | AE48: 0 | AF48: 0 | AG48: 0 | AH48: 0 | AI48: 0 | AJ48: 0 | AK48: 0 | AL48: 0 | AM48: 0 | AN48: 0 | AO48: 0 | AP48: 0 | AQ48: 0 | AR48: 0 | AS48: 0 | AT48: 0 | AU48: 0 | AV48: 0 | AW48: 0 | AX48: 0 | AY48: 0 | AZ48: 0
A49: Total Hardwood Tons | B49: =SUM(B47:B48) -> 14683.873 | C49: =SUM(C47:C48) -> 11144.669 | D49: =SUM(D47:D48) -> 11193.643 | E49: =SUM(E47:E48) -> 6709.7835 | F49: =SUM(F47:F48) -> 5742.5508 | G49: =SUM(G47:G48) -> 5315.9707 | H49: =SUM(H47:H48) -> 5568.94 | I49: =SUM(I47:I48) -> 3920.8931 | ... AZ49: =SUM(AZ47:AZ48) -> 0
A50: % Pine Sawtimber | B50: =SUM(B43)/B46 -> 0.012652907 | C50: =SUM(C43)/C46 -> 0.01453341 | D50: =SUM(D43)/D46 -> 0.01696707 | E50: =SUM(E43)/E46 -> 0.019506659 | F50: =SUM(F43)/F46 -> 0.024685104 | G50: =SUM(G43)/G46 -> 0.028367078 | H50: =SUM(H43)/H46 -> 0.028472187 | I50: =SUM(I43)/I46 -> 0.031699683 | ... AZ50: =SUM(AZ43)/AZ46 -> 0.0041550584
A51: % Pine Chip and Saw | B51: =B44/B46 -> 0.57027278 | C51: =C44/C46 -> 0.56149229 | D51: =D44/D46 -> 0.58000926 | E51: =E44/E46 -> 0.59659552 | F51: =F44/F46 -> 0.62714607 | G51: =G44/G46 -> 0.62365668 | H51: =H44/H46 -> 0.5882396 | I51: =I44/I46 -> 0.57564138 | ... AZ51: =AZ44/AZ46 -> 0.65457889
A52: % Pine Pulpwood | B52: =1-SUM(B50:B51) -> 0.41707431 | C52: =1-SUM(C50:C51) -> 0.4239743 | D52: =1-SUM(D50:D51) -> 0.40302367 | E52: =1-SUM(E50:E51) -> 0.38389782 | F52: =1-SUM(F50:F51) -> 0.34816882 | G52: =1-SUM(G50:G51) -> 0.34797624 | H52: =1-SUM(H50:H51) -> 0.38328822 | I52: =1-SUM(I50:I51) -> 0.39265894 | ... AZ52: =1-SUM(AZ50:AZ51) -> 0.34126606
A54: Natural Management
A55: Natural Acres | B55: 3111.62 | C55: 3111.62 | D55: 3111.62 | E55: 3111.62 | F55: 3111.62 | G55: 3111.62 | H55: 3111.62 | I55: 3111.62 | J55: 3111.62 | K55: 3111.62 | L55: 3111.62 | M55: 3111.62 | N55: 3111.62 | O55: 3111.62 | P55: 3111.62 | Q55: 3111.62 | R55: 3111.62 | S55: 3111.62 | T55: 3111.62 | U55: 3111.62 | V55: 3111.62 | W55: 3111.62 | X55: 3111.62 | Y55: 3111.62 | Z55: 3111.62 | AA55: 3111.62 | AB55: 3111.62 | AC55: 3111.62 | AD55: 3111.62 | AE55: 3111.62 | AF55: 3111.62 | AG55: 3111.62 | AH55: 3111.62 | AI55: 3111.62 | AJ55: 3111.62 | AK55: 3111.62 | AL55: 3111.62 | AM55: 3111.62 | AN55: 3111.62 | AO55: 3111.62 | AP55: 3111.62 | AQ55: 3111.62 | AR55: 3111.62 | AS55: 3111.62 | AT55: 3111.62 | AU55: 3111.62 | AV55: 3111.62 | AW55: 3111.62 | AX55: 3111.62 | AY55: 3111.62 | AZ55: 3111.62
A56: Pine Large Saw Timber | B56: 5167.2569 | C56: 5741.2862 | D56: 6273.7188 | E56: 6771.241 | F56: 7240.9984 | G56: 7632.5232 | H56: 8046.4462 | I56: 8444.4375 | J56: 8847.7019 | K56: 9230.6049 | L56: 9624.264 | M56: 9858.413 | N56: 9890.3173 | O56: 10239.36 | P56: 10308.366 | Q56: 10437.538 | R56: 10775.503 | S56: 11102.872 | T56: 11430.206 | U56: 11750.889 | V56: 12060.457 | W56: 12060.457 | X56: 12060.457 | Y56: 12060.457 | Z56: 12060.457 | AA56: 12060.457 | AB56: 12060.457 | AC56: 12060.457 | AD56: 12060.457 | AE56: 12060.457 | AF56: 12060.457 | AG56: 12060.457 | AH56: 12060.457 | AI56: 12060.457 | AJ56: 12060.457 | AK56: 12060.457 | AL56: 12060.457 | AM56: 12147.631 | AN56: 12346.796 | AO56: 12378.239 | AP56: 12536.353 | AQ56: 12569.288 | AR56: 12601.796 | AS56: 12632.95 | AT56: 12663.906 | AU56: 12694.727 | AV56: 12579.389 | AW56: 12593.059 | AX56: 12614.502 | AY56: 12060.457 | AZ56: 12060.457
A57: Pine Saw Timber | B57: 22623.229 | C57: 24888.155 | D57: 27054.14 | E57: 28683.102 | F57: 30496.696 | G57: 32192.421 | H57: 33798.014 | I57: 34746.518 | J57: 36124.778 | K57: 37503.532 | L57: 38725.643 | M57: 40049.004 | N57: 41387.287 | O57: 42698.183 | P57: 43961.508 | Q57: 45249.769 | R57: 46363.299 | S57: 47517.352 | T57: 48762.86 | U57: 49958.935 | V57: 51072.476 | W57: 51063.42 | X57: 51012.65 | Y57: 50937.503 | Z57: 50937.503 | AA57: 50937.503 | AB57: 50937.503 | AC57: 50937.503 | AD57: 50937.658 | AE57: 50937.928 | AF57: 50938.199 | AG57: 50939.488 | AH57: 50940.778 | AI57: 50942.067 | AJ57: 50941.581 | AK57: 50984.056 | AL57: 51282.519 | AM57: 51326.493 | AN57: 51047.009 | AO57: 51026.617 | AP57: 51458.759 | AQ57: 51496.927 | AR57: 51279.965 | AS57: 51068.518 | AT57: 51080.903 | AU57: 51088.646 | AV57: 51097.671 | AW57: 51106.82 | AX57: 51106.82 | AY57: 51106.82 | AZ57: 51106.82
A58: Pine Chip-N-Saw | B58: 65023.21 | C58: 66060.19 | D58: 67088.005 | E58: 67777.87 | F58: 68514.25 | G58: 68965.439 | H58: 69509.485 | I58: 69871.051 | J58: 70015.449 | K58: 70473.186 | L58: 70682.908 | M58: 70892.17 | N58: 70880.11 | O58: 71201.181 | P58: 71418.615 | Q58: 71496.794 | R58: 71839.29 | S58: 72091.346 | T58: 72160.818 | U58: 72219.212 | V58: 72186.946 | W58: 72158.055 | X58: 71996.092 | Y58: 71756.36 | Z58: 71756.36 | AA58: 71756.36 | AB58: 71756.36 | AC58: 71765.85 | AD58: 71773.934 | AE58: 71775.68 | AF58: 71839.737 | AG58: 71848.249 | AH58: 71856.275 | AI58: 71864.236 | AJ58: 71844.594 | AK58: 72120.412 | AL58: 72231.428 | AM58: 72483.654 | AN58: 72703.64 | AO58: 72571.753 | AP58: 73136.986 | AQ58: 73143.797 | AR58: 73015.519 | AS58: 72710.81 | AT58: 72704.208 | AU58: 72700.701 | AV58: 72615.797 | AW58: 72605.042 | AX58: 72598.354 | AY58: 72296.511 | AZ58: 72296.511
A59: Pine Pulpwood | B59: 54383.581 | C59: 54807.477 | D59: 55213.459 | E59: 55376.6 | F59: 55628.26 | G59: 55721.03 | H59: 55893.618 | I59: 55803.638 | J59: 55738.186 | K59: 55781.609 | L59: 55665.137 | M59: 55707.006 | N59: 55336.398 | O59: 55347.239 | P59: 55201.418 | Q59: 55038.626 | R59: 55099.066 | S59: 55162.697 | T59: 55272.05 | U59: 55404.803 | V59: 55458.373 | W59: 55440.418 | X59: 55339.761 | Y59: 55190.773 | Z59: 55190.773 | AA59: 55190.773 | AB59: 55190.773 | AC59: 55223.481 | AD59: 55247.933 | AE59: 55248.152 | AF59: 55463.237 | AG59: 55464.456 | AH59: 55465.01 | AI59: 55465.441 | AJ59: 55407.914 | AK59: 55629.056 | AL59: 55599.538 | AM59: 55789.071 | AN59: 55938.261 | AO59: 55833.986 | AP59: 56403.589 | AQ59: 56421.246 | AR59: 56304.721 | AS59: 56055.977 | AT59: 56069.816 | AU59: 56081.363 | AV59: 55973.147 | AW59: 55969.452 | AX59: 55969.64 | AY59: 55526.466 | AZ59: 55526.466
A60: Total Pine Tons | B60: =SUM(B56:B59) -> 147197.28 | C60: =SUM(C56:C59) -> 151497.11 | D60: =SUM(D56:D59) -> 155629.32 | E60: =SUM(E56:E59) -> 158608.81 | F60: =SUM(F56:F59) -> 161880.2 | G60: =SUM(G56:G59) -> 164511.41 | H60: =SUM(H56:H59) -> 167247.56 | I60: =SUM(I56:I59) -> 168865.64 | ... AZ60: =SUM(AZ56:AZ59) -> 190990.25
A61: HW Saw Timber | B61: 15213.504 | C61: 16409.348 | D61: 17516.426 | E61: 18521.766 | F61: 19462.967 | G61: 20288.997 | H61: 21107.951 | I61: 21841.225 | J61: 22554.44 | K61: 23243.13 | L61: 23930.461 | M61: 24402.776 | N61: 24652.798 | O61: 25266.792 | P61: 25518.183 | Q61: 26123.497 | R61: 26749.422 | S61: 27359.582 | T61: 27949.607 | U61: 28517.225 | V61: 29050.032 | W61: 29049.457 | X61: 29046.237 | Y61: 29041.469 | Z61: 29041.469 | AA61: 29041.469 | AB61: 29041.469 | AC61: 29041.945 | AD61: 29042.313 | AE61: 29042.339 | AF61: 29045.494 | AG61: 29045.612 | AH61: 29045.734 | AI61: 29045.853 | AJ61: 29044.976 | AK61: 29045.317 | AL61: 29059.505 | AM61: 29161.009 | AN61: 29370.777 | AO61: 29410.156 | AP61: 29628.768 | AQ61: 29674.432 | AR61: 29702.738 | AS61: 29715.571 | AT61: 29754.227 | AU61: 29791.649 | AV61: 29657.842 | AW61: 29672.285 | AX61: 29698.966 | AY61: 29052.211 | AZ61: 29052.211
A62: HW Pulpwood | B62: 63639.851 | C62: 65076.094 | D62: 66385.595 | E62: 67336.661 | F62: 68401.253 | G62: 69244.041 | H62: 70102.598 | I62: 70575.144 | J62: 70987.342 | K62: 71681.942 | L62: 72158.676 | M62: 72490.926 | N62: 72381.27 | O62: 72876.175 | P62: 73001.167 | Q62: 73411.786 | R62: 73802.281 | S62: 74175.951 | T62: 74516.255 | U62: 74850.399 | V62: 75146.881 | W62: 75133.913 | X62: 75061.213 | Y62: 74953.605 | Z62: 74953.605 | AA62: 74953.605 | AB62: 74953.605 | AC62: 74955.123 | AD62: 74956.438 | AE62: 74956.758 | AF62: 74967.05 | AG62: 74968.588 | AH62: 74970.08 | AI62: 74971.533 | AJ62: 74968.32 | AK62: 75103.283 | AL62: 75332.097 | AM62: 75667.518 | AN62: 76088.306 | AO62: 76040.503 | AP62: 77006.204 | AQ62: 77039.751 | AR62: 76881.917 | AS62: 76514.093 | AT62: 76524.521 | AU62: 76532.312 | AV62: 76262.621 | AW62: 76250.723 | AX62: 76241.321 | AY62: 75196.061 | AZ62: 75196.061
A63: Total Hardwood Tons | B63: =SUM(B61:B62) -> 78853.355 | C63: =SUM(C61:C62) -> 81485.442 | D63: =SUM(D61:D62) -> 83902.021 | E63: =SUM(E61:E62) -> 85858.428 | F63: =SUM(F61:F62) -> 87864.22 | G63: =SUM(G61:G62) -> 89533.038 | H63: =SUM(H61:H62) -> 91210.549 | I63: =SUM(I61:I62) -> 92416.369 | ... AZ63: =SUM(AZ61:AZ62) -> 104248.27
A65: Total Residual Inventory
A66: Pine Large Saw Timber | B66: =B42+B56 -> 9034.937 | C66: =C42+C56 -> 9825.1237 | D66: =D42+D56 -> 11494.521 | E66: =E42+E56 -> 9608.3921 | F66: =F42+F56 -> 10820.792 | G66: =G42+G56 -> 12015.458 | H66: =H42+H56 -> 13817.607 | I66: =I42+I56 -> 13305.022 | ... AZ66: =AZ42+AZ56 -> 12412.071
A67: Pine Saw Timber | B67: =B43+B57 -> 27006.699 | C67: =C43+C57 -> 30008.041 | D67: =D43+D57 -> 33595.095 | E67: =E43+E57 -> 35724.023 | F67: =F43+F57 -> 39566.995 | G67: =G43+G57 -> 43998.293 | H67: =H43+H57 -> 49046.452 | I67: =I43+I57 -> 51582.775 | ... AZ67: =AZ43+AZ57 -> 51450.783
A68: Pine Chip-N-Saw | B68: =B44+B58 -> 262588.37 | C68: =C44+C58 -> 263864.88 | D68: =D44+D58 -> 290686.7 | E68: =E44+E58 -> 283118.79 | F68: =F44+F58 -> 298952.9 | G68: =G44+G58 -> 328520.23 | H68: =H44+H58 -> 384544.47 | I68: =I44+I58 -> 375604.27 | ... AZ68: =AZ44+AZ58 -> 126483.71
A69: Pine Pulpwood | B69: =B45+B59 -> 195007.02 | C69: =C45+C59 -> 200082.95 | D69: =D45+D59 -> 205361.84 | E69: =E45+E59 -> 191107.22 | F69: =F45+F59 -> 179979.67 | G69: =G45+G59 -> 196159.6 | H69: =H45+H59 -> 255394.59 | I69: =I45+I59 -> 259491.1 | ... AZ69: =AZ45+AZ59 -> 83425.457
A70: Total Pine Tons | B70: =SUM(B66:B69) -> 493637.03 | C70: =SUM(C66:C69) -> 503781 | D70: =SUM(D66:D69) -> 541138.16 | E70: =SUM(E66:E69) -> 519558.42 | F70: =SUM(F66:F69) -> 529320.36 | G70: =SUM(G66:G69) -> 580693.58 | H70: =SUM(H66:H69) -> 702803.12 | I70: =SUM(I66:I69) -> 699983.17 | ... AZ70: =SUM(AZ66:AZ69) -> 273772.02
A71: HW Saw Timber | B71: =B61+B47 -> 16336.983 | C71: =C61+C47 -> 17279.078 | D71: =D61+D47 -> 18477.551 | E71: =E61+E47 -> 18977.672 | F71: =F61+F47 -> 19879.059 | G71: =G61+G47 -> 20673.311 | H71: =H61+H47 -> 21531.148 | I71: =I61+I47 -> 22067.29 | ... AZ71: =AZ61+AZ47 -> 29052.211
A72: HW Pulpwood | B72: =B62+B48 -> 77200.246 | C72: =C62+C48 -> 75351.034 | D72: =D62+D48 -> 76618.113 | E72: =E62+E48 -> 73590.539 | F72: =F62+F48 -> 73727.712 | G72: =G62+G48 -> 74175.698 | H72: =H62+H48 -> 75248.341 | I72: =I62+I48 -> 74269.973 | ... AZ72: =AZ62+AZ48 -> 75196.061
A73: Total Hardwood Tons | B73: =SUM(B71:B72) -> 93537.228 | C73: =SUM(C71:C72) -> 92630.111 | D73: =SUM(D71:D72) -> 95095.664 | E73: =SUM(E71:E72) -> 92568.211 | F73: =SUM(F71:F72) -> 93606.771 | G73: =SUM(G71:G72) -> 94849.008 | H73: =SUM(H71:H72) -> 96779.489 | I73: =SUM(I71:I72) -> 96337.262 | ... AZ73: =SUM(AZ71:AZ72) -> 104248.27
A74: Total Tons, All Products | B74: =B73+B70 -> 587174.26 | C74: =C73+C70 -> 596411.11 | D74: =D73+D70 -> 636233.82 | E74: =E73+E70 -> 612126.63 | F74: =F73+F70 -> 622927.13 | G74: =G73+G70 -> 675542.59 | H74: =H73+H70 -> 799582.61 | I74: =I73+I70 -> 796320.43 | ... AZ74: =AZ73+AZ70 -> 378020.29
A76: Tons Per Acre
A77: Total Residual Inventory Tons/Acre
A78: Pine Large Saw Timber | B78: =B66/B$9 -> 0.72833673 | C78: =C66/C$9 -> 0.79203634 | D78: =D66/D$9 -> 0.9266121 | E78: =E66/E$9 -> 0.77456488 | F78: =F66/F$9 -> 0.87230055 | G78: =G66/G$9 -> 0.96860661 | H78: =H66/H$9 -> 1.1138839 | I78: =I66/I$9 -> 1.0725627 | ... AZ78: =AZ66/AZ$9 -> 1.0005788
A79: Pine Saw Timber | B79: =B67/B$9 -> 2.1771011 | C79: =C67/C$9 -> 2.4190494 | D79: =D67/D$9 -> 2.7082138 | E79: =E67/E$9 -> 2.8798339 | F79: =F67/F$9 -> 3.1896288 | G79: =G67/G$9 -> 3.5468507 | H79: =H67/H$9 -> 3.9537998 | I79: =I67/I$9 -> 4.1582614 | ... AZ79: =AZ67/AZ$9 -> 4.1476211
A80: Pine Chip-N-Saw | B80: =B68/B$9 -> 21.168134 | C80: =C68/C$9 -> 21.271037 | D80: =D68/D$9 -> 23.433235 | E80: =E68/E$9 -> 22.82316 | F80: =F68/F$9 -> 24.099601 | G80: =G68/G$9 -> 26.483123 | H80: =H68/H$9 -> 30.999426 | I80: =I68/I$9 -> 30.278727 | ... AZ80: =AZ68/AZ$9 -> 10.196278
A81: Pine Pulpwood | B81: =B69/B$9 -> 15.720174 | C81: =C69/C$9 -> 16.129361 | D81: =D69/D$9 -> 16.55491 | E81: =E69/E$9 -> 15.405797 | F81: =F69/F$9 -> 14.508768 | G81: =G69/G$9 -> 15.813087 | H81: =H69/H$9 -> 20.588219 | I81: =I69/I$9 -> 20.918452 | ... AZ81: =AZ69/AZ$9 -> 6.7252074
A82: Total Pine Tons | B82: =B70/B$9 -> 39.793745 | C82: =C70/C$9 -> 40.611484 | D82: =D70/D$9 -> 43.622971 | E82: =E70/E$9 -> 41.883355 | F82: =F70/F$9 -> 42.670298 | G82: =G70/G$9 -> 46.811667 | H82: =H70/H$9 -> 56.655329 | I82: =I70/I$9 -> 56.428003 | ... AZ82: =AZ70/AZ$9 -> 22.069685
A83: HW Saw Timber | B83: =B71/B$9 -> 1.3169792 | C83: =C71/C$9 -> 1.3929247 | D83: =D71/D$9 -> 1.4895377 | E83: =E71/E$9 -> 1.5298541 | F83: =F71/F$9 -> 1.602518 | G83: =G71/G$9 -> 1.6665453 | H83: =H71/H$9 -> 1.7356984 | I83: =I71/I$9 -> 1.7789186 | ... AZ83: =AZ71/AZ$9 -> 2.3419966
A84: HW Pulpwood | B84: =B72/B$9 -> 6.2233721 | C84: =C72/C$9 -> 6.0743008 | D84: =D72/D$9 -> 6.1764444 | E84: =E72/E$9 -> 5.9323814 | F84: =F72/F$9 -> 5.9434394 | G84: =G72/G$9 -> 5.979553 | H84: =H72/H$9 -> 6.0660225 | I84: =I72/I$9 -> 5.9871529 | ... AZ84: =AZ72/AZ$9 -> 6.0618079
A85: Total Hardwood Tons | B85: =B73/B$9 -> 7.5403513 | C85: =C73/C$9 -> 7.4672255 | D85: =D73/D$9 -> 7.6659821 | E85: =E73/E$9 -> 7.4622356 | F85: =F73/F$9 -> 7.5459574 | G85: =G73/G$9 -> 7.6460983 | H85: =H73/H$9 -> 7.8017209 | I85: =I73/I$9 -> 7.7660715 | ... AZ85: =AZ73/AZ$9 -> 8.4038046
A86: Total Tons, All Products | B86: =B74/B$9 -> 47.334097 | C86: =C74/C$9 -> 48.07871 | D86: =D74/D$9 -> 51.288953 | E86: =E74/E$9 -> 49.345591 | F86: =F74/F$9 -> 50.216256 | G86: =G74/G$9 -> 54.457765 | H86: =H74/H$9 -> 64.457049 | I86: =I74/I$9 -> 64.194074 | ... AZ86: =AZ74/AZ$9 -> 30.47349
A88: Plantation Merchantable Standing Inventory Tons/Acre
A89: Pine Large Saw Timber | B89: =B42/B$40 -> 0.76547859 | C89: =C42/C$40 -> 0.79933558 | D89: =D42/D$40 -> 0.98325194 | E89: =E42/E$40 -> 0.57210892 | F89: =F42/F$40 -> 0.72186218 | G89: =G42/G$40 -> 0.84523721 | H89: =H42/H$40 -> 0.96719416 | I89: =I42/I$40 -> 0.86340244 | ... AZ89: =AZ42/AZ$40 -> 0.22353461
A90: Pine Saw Timber | B90: =B43/B$40 -> 0.86756208 | C90: =C43/C$40 -> 1.002123 | D90: =D43/D$40 -> 1.231881 | E90: =E43/E$40 -> 1.4197952 | F90: =F43/F$40 -> 1.8290174 | G90: =G43/G$40 -> 2.2767305 | H90: =H43/H$40 -> 2.5554999 | I90: =I43/I$40 -> 2.9906826 | ... AZ90: =AZ43/AZ$40 -> 0.21867059
A91: Pine Chip-N-Saw | B91: =B44/B$40 -> 39.101451 | C91: =C44/C$40 -> 38.716606 | D91: =D44/D$40 -> 42.111123 | E91: =E44/E$40 -> 43.423299 | F91: =F44/F$40 -> 46.467743 | G91: =G44/G$40 -> 50.054438 | H91: =H44/H$40 -> 52.797006 | I91: =I44/I$40 -> 54.30845 | ... AZ91: =AZ44/AZ$40 -> 34.44889
A92: Pine Pulpwood | B92: =B45/B$40 -> 27.831732 | C92: =C45/C$40 -> 28.434985 | D92: =D45/D$40 -> 28.277969 | E92: =E45/E$40 -> 27.369955 | F92: =F45/F$40 -> 25.075349 | G92: =G45/G$40 -> 27.083198 | H92: =H45/H$40 -> 33.434554 | I92: =I45/I$40 -> 36.181708 | ... AZ92: =AZ45/AZ$40 -> 17.736465
A93: Total Pine Tons | B93: =B46/B$40 -> 68.566223 | C93: =C46/C$40 -> 68.953049 | D93: =D46/D$40 -> 72.604225 | E93: =E46/E$40 -> 72.785158 | F93: =F46/F$40 -> 74.093971 | G93: =G46/G$40 -> 80.259605 | H93: =H46/H$40 -> 89.754254 | I93: =I46/I$40 -> 94.344243 | ... AZ93: =AZ46/AZ$40 -> 52.627561
A94: HW Saw Timber | B94: =B47/B$40 -> 0.22235519 | C94: =C47/C$40 -> 0.1702335 | D94: =D47/D$40 -> 0.181012 | E94: =E47/E$40 -> 0.091933054 | F94: =F47/F$40 -> 0.083904487 | G94: =G47/G$40 -> 0.074113854 | H94: =H47/H$40 -> 0.070923909 | I94: =I47/I$40 -> 0.040156657 | ... AZ94: =AZ47/AZ$40 -> 0
A95: HW Pulpwood | B95: =B48/B$40 -> 2.6838289 | C95: =C48/C$40 -> 2.0111292 | D95: =D48/D$40 -> 1.9271259 | E95: =E48/E$40 -> 1.2610887 | F95: =F48/F$40 -> 1.0740756 | G95: =G48/G$40 -> 0.9510567 | H95: =H48/H$40 -> 0.86237993 | I95: =I48/I$40 -> 0.65632515 | ... AZ95: =AZ48/AZ$40 -> 0
A96: Total Hardwood Tons | B96: =B49/B$40 -> 2.9061841 | C96: =C49/C$40 -> 2.1813627 | D96: =D49/D$40 -> 2.1081379 | E96: =E49/E$40 -> 1.3530217 | F96: =F49/F$40 -> 1.1579801 | G96: =G49/G$40 -> 1.0251706 | H96: =H49/H$40 -> 0.93330383 | I96: =I49/I$40 -> 0.69648181 | ... AZ96: =AZ49/AZ$40 -> 0
A98: Natural Standing Inventory Tons/Acre
A99: Pine Large Saw Timber | B99: =B56/B$55 -> 1.6606324 | C99: =C56/C$55 -> 1.8451116 | D99: =D56/D$55 -> 2.0162227 | E99: =E56/E$55 -> 2.1761144 | F99: =F56/F$55 -> 2.3270831 | G99: =G56/G$55 -> 2.4529098 | H99: =H56/H$55 -> 2.5859347 | I99: =I56/I$55 -> 2.7138396 | ... AZ99: =AZ56/AZ$55 -> 3.8759413
A100: Pine Saw Timber | B100: =B57/B$55 -> 7.2705629 | C100: =C57/C$55 -> 7.9984557 | D100: =D57/D$55 -> 8.6945513 | E100: =E57/E$55 -> 9.2180608 | F100: =F57/F$55 -> 9.8009064 | G100: =G57/G$55 -> 10.345872 | H100: =H57/H$55 -> 10.861871 | I100: =I57/I$55 -> 11.166697 | ... AZ100: =AZ57/AZ$55 -> 16.424506
A101: Pine Chip-N-Saw | B101: =B58/B$55 -> 20.896899 | C101: =C58/C$55 -> 21.23016 | D101: =D58/D$55 -> 21.560475 | E101: =E58/E$55 -> 21.782181 | F101: =F58/F$55 -> 22.018836 | G101: =G58/G$55 -> 22.163837 | H101: =H58/H$55 -> 22.33868 | I101: =I58/I$55 -> 22.454879 | ... AZ101: =AZ58/AZ$55 -> 23.234364
A102: Pine Pulpwood | B102: =B59/B$55 -> 17.477578 | C102: =C59/C$55 -> 17.613808 | D102: =D59/D$55 -> 17.744281 | E102: =E59/E$55 -> 17.79671 | F102: =F59/F$55 -> 17.877588 | G102: =G59/G$55 -> 17.907402 | H102: =H59/H$55 -> 17.962868 | I102: =I59/I$55 -> 17.93395 | ... AZ102: =AZ59/AZ$55 -> 17.844874
A103: Total Pine Tons | B103: =B60/B$55 -> 47.305672 | C103: =C60/C$55 -> 48.687535 | D103: =D60/D$55 -> 50.01553 | E103: =E60/E$55 -> 50.973066 | F103: =F60/F$55 -> 52.024413 | G103: =G60/G$55 -> 52.87002 | H103: =H60/H$55 -> 53.749354 | I103: =I60/I$55 -> 54.269366 | ... AZ103: =AZ60/AZ$55 -> 61.379684
A104: HW Saw Timber | B104: =B61/B$55 -> 4.8892551 | C104: =C61/C$55 -> 5.2735707 | D104: =D61/D$55 -> 5.6293591 | E104: =E61/E$55 -> 5.9524512 | F104: =F61/F$55 -> 6.2549307 | G104: =G61/G$55 -> 6.5203968 | H104: =H61/H$55 -> 6.783589 | I104: =I61/I$55 -> 7.0192456 | ... AZ104: =AZ61/AZ$55 -> 9.3366834
A105: HW Pulpwood | B105: =B62/B$55 -> 20.452321 | C105: =C62/C$55 -> 20.913895 | D105: =D62/D$55 -> 21.334737 | E105: =E62/E$55 -> 21.640387 | F105: =F62/F$55 -> 21.982521 | G105: =G62/G$55 -> 22.253373 | H105: =H62/H$55 -> 22.529293 | I105: =I62/I$55 -> 22.681158 | ... AZ105: =AZ62/AZ$55 -> 24.166209
A106: Total Hardwood Tons | B106: =B63/B$55 -> 25.341576 | C106: =C63/C$55 -> 26.187466 | D106: =D63/D$55 -> 26.964096 | E106: =E63/E$55 -> 27.592838 | F106: =F63/F$55 -> 28.237452 | G106: =G63/G$55 -> 28.77377 | H106: =H63/H$55 -> 29.312882 | I106: =I63/I$55 -> 29.700403 | ... AZ106: =AZ63/AZ$55 -> 33.502893

Sheet Carbon Report
A1: DISCOUNTED CASH FLOW ANALYSIS
A2: Carbon Report
A3: =CONCATENATE('Model Assumptions'!B2, " - ",'Model Assumptions'!B3 ) -> IWC - Boot Hill
A4: ='Model Assumptions'!B5 -> IWC - Boothill - HSM
B5: ='Finance Report'!B6 -> Model Year 0 | C5: 2026 | D5: =C5+1 -> 2027 | E5: =D5+1 -> 2028 | F5: =E5+1 -> 2029 | G5: =F5+1 -> 2030 | H5: =G5+1 -> 2031 | I5: =H5+1 -> 2032 | J5: =I5+1 -> 2033 | K5: =J5+1 -> 2034 | ... AZ5: =AY5+1 -> 2075
A8: Total Acres | B8: 12404.89 | C8: 12404.89 | D8: 12404.89 | E8: 12404.89 | F8: 12404.89 | G8: 12404.89 | H8: 12404.89 | I8: 12404.89 | J8: 12404.89 | K8: 12404.89 | L8: 12404.89 | M8: 12404.89 | N8: 12404.89 | O8: 12404.89 | P8: 12404.89 | Q8: 12404.89 | R8: 12404.89 | S8: 12404.89 | T8: 12404.89 | U8: 12404.89 | V8: 12404.89 | W8: 12404.89 | X8: 12404.89 | Y8: 12404.89 | Z8: 12404.89 | AA8: 12404.89 | AB8: 12404.89 | AC8: 12404.89 | AD8: 12404.89 | AE8: 12404.89 | AF8: 12404.89 | AG8: 12404.89 | AH8: 12404.89 | AI8: 12404.89 | AJ8: 12404.89 | AK8: 12404.89 | AL8: 12404.89 | AM8: 12404.89 | AN8: 12404.89 | AO8: 12404.89 | AP8: 12404.89 | AQ8: 12404.89 | AR8: 12404.89 | AS8: 12404.89 | AT8: 12404.89 | AU8: 12404.89 | AV8: 12404.89 | AW8: 12404.89 | AX8: 12404.89 | AY8: 12404.89 | AZ8: 12404.89
A9: Productive Plantation Acres | B9: 8762.98 | C9: 8762.98 | D9: 8762.98 | E9: 8762.98 | F9: 8762.98 | G9: 8762.98 | H9: 8762.98 | I9: 8762.98 | J9: 8762.98 | K9: 8762.98 | L9: 8762.98 | M9: 8762.98 | N9: 8762.98 | O9: 8762.98 | P9: 8762.98 | Q9: 8762.98 | R9: 8762.98 | S9: 8762.98 | T9: 8762.98 | U9: 8762.98 | V9: 8762.98 | W9: 8762.98 | X9: 8762.98 | Y9: 8762.98 | Z9: 8762.98 | AA9: 8762.98 | AB9: 8762.98 | AC9: 8762.98 | AD9: 8762.98 | AE9: 8762.98 | AF9: 8762.98 | AG9: 8762.98 | AH9: 8762.98 | AI9: 8762.98 | AJ9: 8762.98 | AK9: 8762.98 | AL9: 8762.98 | AM9: 8762.98 | AN9: 8762.98 | AO9: 8762.98 | AP9: 8762.98 | AQ9: 8762.98 | AR9: 8762.98 | AS9: 8762.98 | AT9: 8762.98 | AU9: 8762.98 | AV9: 8762.98 | AW9: 8762.98 | AX9: 8762.98 | AY9: 8762.98 | AZ9: 8762.98
A10: Natural Convertible Acres | B10: 611.17 | C10: 611.17 | D10: 611.17 | E10: 611.17 | F10: 611.17 | G10: 611.17 | H10: 611.17 | I10: 611.17 | J10: 611.17 | K10: 611.17 | L10: 611.17 | M10: 611.17 | N10: 611.17 | O10: 611.17 | P10: 611.17 | Q10: 611.17 | R10: 611.17 | S10: 611.17 | T10: 611.17 | U10: 611.17 | V10: 611.17 | W10: 611.17 | X10: 611.17 | Y10: 611.17 | Z10: 611.17 | AA10: 611.17 | AB10: 611.17 | AC10: 611.17 | AD10: 611.17 | AE10: 611.17 | AF10: 611.17 | AG10: 611.17 | AH10: 611.17 | AI10: 611.17 | AJ10: 611.17 | AK10: 611.17 | AL10: 611.17 | AM10: 611.17 | AN10: 611.17 | AO10: 611.17 | AP10: 611.17 | AQ10: 611.17 | AR10: 611.17 | AS10: 611.17 | AT10: 611.17 | AU10: 611.17 | AV10: 611.17 | AW10: 611.17 | AX10: 611.17 | AY10: 611.17 | AZ10: 611.17
A11: Non-Converitble Acres | B11: 3030.74 | C11: 3030.74 | D11: 3030.74 | E11: 3030.74 | F11: 3030.74 | G11: 3030.74 | H11: 3030.74 | I11: 3030.74 | J11: 3030.74 | K11: 3030.74 | L11: 3030.74 | M11: 3030.74 | N11: 3030.74 | O11: 3030.74 | P11: 3030.74 | Q11: 3030.74 | R11: 3030.74 | S11: 3030.74 | T11: 3030.74 | U11: 3030.74 | V11: 3030.74 | W11: 3030.74 | X11: 3030.74 | Y11: 3030.74 | Z11: 3030.74 | AA11: 3030.74 | AB11: 3030.74 | AC11: 3030.74 | AD11: 3030.74 | AE11: 3030.74 | AF11: 3030.74 | AG11: 3030.74 | AH11: 3030.74 | AI11: 3030.74 | AJ11: 3030.74 | AK11: 3030.74 | AL11: 3030.74 | AM11: 3030.74 | AN11: 3030.74 | AO11: 3030.74 | AP11: 3030.74 | AQ11: 3030.74 | AR11: 3030.74 | AS11: 3030.74 | AT11: 3030.74 | AU11: 3030.74 | AV11: 3030.74 | AW11: 3030.74 | AX11: 3030.74 | AY11: 3030.74 | AZ11: 3030.74
A13: Property Carbon Sequestration (MtCO2e)
A14: Annual Sequestered Carbon (growth) | C14: =C83-B83+C194 -> 74820.926 | D14: =D83-C83+D194 -> 77423.029 | E14: =E83-D83+E194 -> 74564.567 | F14: =F83-E83+F194 -> 75039.033 | G14: =G83-F83+G194 -> 86678.133 | H14: =H83-G83+H194 -> 91701.632 | I14: =I83-H83+I194 -> 86770.039 | J14: =J83-I83+J194 -> 77275.056 | ... AZ14: =AZ83-AY83+AZ194 -> -25910.36
A15: Sequestered Carbon post harvests | C15: =C83-B83 -> 11720.519 | D15: =D83-C83 -> 71508.954 | E15: =E83-D83 -> -12553.941 | F15: =F83-E83 -> 49162.145 | G15: =G83-F83 -> 58722.198 | H15: =H83-G83 -> 88014.818 | I15: =I83-H83 -> -12326.423 | J15: =J83-I83 -> -38443.283 | ... AZ15: =AZ83-AY83 -> -223258.08
A17: Total Carbon (Living Tree + HWP) | B17: =B83+B270 -> 844985.21 | C17: =C83+C270 -> 856705.73 | D17: =D83+D270 -> 928214.68 | E17: =E83+E270 -> 915660.74 | F17: =F83+F270 -> 964822.88 | G17: =G83+G270 -> 1023545.1 | H17: =H83+H270 -> 1111559.9 | I17: =I83+I270 -> 1099233.5 | ... AZ17: =AZ83+AZ270 -> 318673.61 | BB17: =MAX(C17:AZ17) -> 1286285
A18: Annual Carbon Change | C18: =C14+C270 -> 74820.926 | D18: =D14+(D270-C270) -> 77423.029 | E18: =E14+(E270-D270) -> 74564.567 | F18: =F14+(F270-E270) -> 75039.033 | G18: =G14+(G270-F270) -> 86678.133 | H18: =H14+(H270-G270) -> 91701.632 | I18: =I14+(I270-H270) -> 86770.039 | J18: =J14+(J270-I270) -> 77275.056 | K18: =K14+(K270-J270) -> 78202.718 | ... AZ18: =AZ14+(AZ270-AY270) -> -25910.36
A20: Carbon Stored in Residual Inventory (MtCO2e)
A22: Plantation Management
A23: Planted Acres | B23: 8547.19 | C23: 8172.85 | D23: 8388.64 | E23: 8317.96 | F23: 8317.96 | G23: 8553.98 | H23: 8553.98 | I23: 8212.91 | J23: 7536.11 | K23: 8056.71 | L23: 8252.64 | M23: 7936.49 | N23: 7461.84 | O23: 7771.93 | P23: 8191.46 | Q23: 7656.6 | R23: 8167.08 | S23: 8727.28 | T23: 8593.54 | U23: 8397.29 | V23: 8388.08 | W23: 8550.1 | X23: 8469.5364 | Y23: 7535.75 | Z23: 6446.0172 | AA23: 7424.2236 | AB23: 8762.98 | AC23: 8762.98 | AD23: 8703.73 | AE23: 8496.7964 | AF23: 8556.0464 | AG23: 8602.4 | AH23: 8280.72 | AI23: 8441.3 | AJ23: 8306.6 | AK23: 8306.6 | AL23: 8565.34 | AM23: 8565.34 | AN23: 8212.91 | AO23: 7536.11 | AP23: 8056.71 | AQ23: 8252.64 | AR23: 7936.49 | AS23: 7461.84 | AT23: 7771.93 | AU23: 8191.46 | AV23: 7656.6 | AW23: 8167.08 | AX23: 8727.28 | AY23: 7278.7436 | AZ23: 5788.9336
A24: Softwood Carbon (MtCO2e)
A25: Merchantable Stem
A26: Pine Large Saw Timber | B26: 0 | C26: 0 | D26: 0 | E26: 0 | F26: 0 | G26: 0 | H26: 0 | I26: 0 | J26: 0 | K26: 0 | L26: 0 | M26: 0 | N26: 0 | O26: 0 | P26: 0 | Q26: 0 | R26: 0 | S26: 0 | T26: 0 | U26: 0 | V26: 0 | W26: 0 | X26: 0 | Y26: 0 | Z26: 0 | AA26: 0 | AB26: 0 | AC26: 0 | AD26: 0 | AE26: 0 | AF26: 0 | AG26: 0 | AH26: 0 | AI26: 0 | AJ26: 0 | AK26: 0 | AL26: 0 | AM26: 0 | AN26: 0 | AO26: 0 | AP26: 0 | AQ26: 0 | AR26: 0 | AS26: 0 | AT26: 0 | AU26: 0 | AV26: 0 | AW26: 0 | AX26: 0 | AY26: 0 | AZ26: 0
A27: Pine Saw Timber | B27: 12879.014 | C27: 14176.54 | D27: 18238.458 | E27: 15090.807 | F27: 19623.044 | G27: 25473.414 | H27: 33430.783 | I27: 34763.052 | J27: 40366.346 | K27: 52017.305 | L27: 63091.981 | M27: 69035.708 | N27: 53510.078 | O27: 66733.191 | P27: 69334.026 | Q27: 51285.677 | R27: 65808.048 | S27: 87702.573 | T27: 111358.89 | U27: 135505.63 | V27: 159452.91 | W27: 182649.85 | X27: 172541.39 | Y27: 156606.34 | Z27: 9525.1196 | AA27: 14202.162 | AB27: 19552.014 | AC27: 26509.545 | AD27: 31960.427 | AE27: 25556.02 | AF27: 35231.235 | AG27: 44359.459 | AH27: 50376.334 | AI27: 67323.421 | AJ27: 57820.854 | AK27: 80753.02 | AL27: 102227.73 | AM27: 125442.43 | AN27: 114350.01 | AO27: 70304.793 | AP27: 89167.856 | AQ27: 83305.269 | AR27: 80297.899 | AS27: 59226.995 | AT27: 68958.483 | AU27: 68965.378 | AV27: 17543.747 | AW27: 24123.503 | AX27: 32949.823 | AY27: 15995.236 | AZ27: 1020.4798
A28: Pine Chip-N-Saw | B28: 261857.81 | C28: 260088.67 | D28: 308310.77 | E28: 310547.41 | F28: 350169.67 | G28: 392789.36 | H28: 445724.17 | I28: 429190.95 | J28: 408038.19 | K28: 424784.19 | L28: 417649.59 | M28: 416585.05 | N28: 351669.02 | O28: 422508.1 | P28: 391730.68 | Q28: 355403.91 | R28: 349217.01 | S28: 369497.87 | T28: 384279.3 | U28: 364018.01 | V28: 383684.72 | W28: 439742.86 | X28: 449679.17 | Y28: 380761.77 | Z28: 233534.86 | AA28: 263482.67 | AB28: 285932.24 | AC28: 317426.09 | AD28: 374217.43 | AE28: 405251.74 | AF28: 415050.27 | AG28: 365753.55 | AH28: 385938.93 | AI28: 404769.58 | AJ28: 384313.09 | AK28: 378362.74 | AL28: 392950.96 | AM28: 424986.71 | AN28: 378147.64 | AO28: 361798.42 | AP28: 373417.42 | AQ28: 375197.91 | AR28: 376263.57 | AS28: 305003.72 | AT28: 327184.25 | AU28: 269684.26 | AV28: 252180.25 | AW28: 298037.56 | AX28: 325697.93 | AY28: 225147.08 | AZ28: 71338.803
A29: Pine Pulpwood | B29: 159636.99 | C29: 168599.9 | D29: 183530.97 | E29: 180918.98 | F29: 191077.92 | G29: 208344.03 | H29: 233386.64 | I29: 237984.28 | J29: 216742.02 | K29: 173514.97 | L29: 157858.69 | M29: 173310.53 | N29: 169329.25 | O29: 196492.61 | P29: 178093.16 | Q29: 162390.93 | R29: 158520.95 | S29: 158132.91 | T29: 171046.02 | U29: 163564.53 | V29: 198653.42 | W29: 238546.54 | X29: 238554.52 | Y29: 217746.22 | Z29: 95343.309 | AA29: 140293.11 | AB29: 141185.94 | AC29: 162780.08 | AD29: 167412.91 | AE29: 164621.87 | AF29: 155197.95 | AG29: 143406.52 | AH29: 144197.37 | AI29: 158906.38 | AJ29: 125773.38 | AK29: 135813.09 | AL29: 165197.29 | AM29: 225393.57 | AN29: 194662.16 | AO29: 157173.25 | AP29: 135712.91 | AQ29: 130068.8 | AR29: 134914.29 | AS29: 102769.43 | AT29: 110054.25 | AU29: 99641.105 | AV29: 88927.234 | AW29: 111779.89 | AX29: 113282.02 | AY29: 83885.045 | AZ29: 32768.17
A30: Total Merch Pine | B30: 434373.81 | C30: 442865.11 | D30: 510080.2 | E30: 506557.2 | F30: 560870.64 | G30: 626606.8 | H30: 712541.59 | I30: 701938.27 | J30: 665146.55 | K30: 650316.46 | L30: 638600.26 | M30: 658931.29 | N30: 574508.35 | O30: 685733.91 | P30: 639157.87 | Q30: 569080.51 | R30: 573546 | S30: 615333.35 | T30: 666684.21 | U30: 663088.17 | V30: 741791.05 | W30: 860939.25 | X30: 860775.08 | Y30: 755114.32 | Z30: 338403.29 | AA30: 417977.95 | AB30: 446670.19 | AC30: 506715.71 | AD30: 573590.76 | AE30: 595429.63 | AF30: 605479.46 | AG30: 553519.53 | AH30: 580512.63 | AI30: 630999.38 | AJ30: 567907.32 | AK30: 594928.85 | AL30: 660375.99 | AM30: 775822.7 | AN30: 687159.81 | AO30: 589276.46 | AP30: 598298.18 | AQ30: 588571.98 | AR30: 591475.75 | AS30: 467000.15 | AT30: 506196.98 | AU30: 438290.74 | AV30: 358651.24 | AW30: 433940.96 | AX30: 471929.77 | AY30: 325027.37 | AZ30: 105127.45
A31: Unmerchantable Portions | B31: 65044.338 | C31: 63889.157 | D31: 58828.766 | E31: 49452.875 | F31: 39014.605 | G31: 27684.417 | H31: 23654.655 | I31: 20726.334 | J31: 15774.378 | K31: 15101.184 | L31: 11357.299 | M31: 13301.033 | N31: 19856.633 | O31: 20420.297 | P31: 19599.192 | Q31: 17548.377 | R31: 21714.632 | S31: 18169.906 | T31: 15620.682 | U31: 11283.527 | V31: 17622.132 | W31: 24911.871 | X31: 20589.528 | Y31: 18681.829 | Z31: 18216.505 | AA31: 28860.44 | AB31: 25611.294 | AC31: 29574.057 | AD31: 33269.111 | AE31: 29766.004 | AF31: 23262.51 | AG31: 22285.187 | AH31: 23844.871 | AI31: 23146.024 | AJ31: 20348.866 | AK31: 20501.478 | AL31: 29747.842 | AM31: 46113.536 | AN31: 42782.844 | AO31: 34990.168 | AP31: 27718.239 | AQ31: 24093.889 | AR31: 24769.679 | AS31: 21749.784 | AT31: 18833.512 | AU31: 17638.342 | AV31: 14532.554 | AW31: 17582.072 | AX31: 14003.873 | AY31: 11501.874 | AZ31: 8143.7082
A32: Total Softwood Carbon | B32: 499418.15 | C32: 506754.27 | D32: 568908.96 | E32: 556010.07 | F32: 599885.24 | G32: 654291.22 | H32: 736196.25 | I32: 722664.61 | J32: 680920.93 | K32: 665417.65 | L32: 649957.56 | M32: 672232.32 | N32: 594364.98 | O32: 706154.2 | P32: 658757.06 | Q32: 586628.89 | R32: 595260.63 | S32: 633503.26 | T32: 682304.89 | U32: 674371.7 | V32: 759413.18 | W32: 885851.12 | X32: 881364.61 | Y32: 773796.15 | Z32: 356619.79 | AA32: 446838.39 | AB32: 472281.49 | AC32: 536289.77 | AD32: 606859.87 | AE32: 625195.63 | AF32: 628741.97 | AG32: 575804.72 | AH32: 604357.5 | AI32: 654145.4 | AJ32: 588256.19 | AK32: 615430.33 | AL32: 690123.83 | AM32: 821936.24 | AN32: 729942.66 | AO32: 624266.63 | AP32: 626016.42 | AQ32: 612665.87 | AR32: 616245.43 | AS32: 488749.93 | AT32: 525030.5 | AU32: 455929.08 | AV32: 373183.79 | AW32: 451523.03 | AX32: 485933.64 | AY32: 336529.24 | AZ32: 113271.16
A33: Hardwood Carbon (MtCO2e)
A34: Merchantable Stem
A35: HW Saw Timber | B35: 1081.0691 | C35: 791.66615 | D35: 871.81786 | E35: 342.67545 | F35: 313.31725 | G35: 297.37335 | H35: 324.06325 | I35: 149.85378 | J35: 146.61044 | K35: 149.13788 | L35: 142.46116 | M35: 135.35436 | N35: 70.764439 | O35: 77.119953 | P35: 70.813062 | Q35: 59.704578 | R35: 64.028547 | S35: 70.105448 | T35: 30.1524 | U35: 34.1478 | V35: 0 | W35: 0 | X35: 0 | Y35: 0 | Z35: 0 | AA35: 0 | AB35: 0 | AC35: 0 | AD35: 0 | AE35: 0 | AF35: 0 | AG35: 0 | AH35: 0 | AI35: 0 | AJ35: 0 | AK35: 0 | AL35: 0 | AM35: 0 | AN35: 0 | AO35: 0 | AP35: 0 | AQ35: 0 | AR35: 0 | AS35: 0 | AT35: 0 | AU35: 0 | AV35: 0 | AW35: 0 | AX35: 0 | AY35: 0 | AZ35: 0
A36: HW Pulpwood | B36: 11781.712 | C36: 8747.5751 | D36: 8672.4341 | E36: 5078.44 | F36: 4287.5127 | G36: 3969.7431 | H36: 4137.9567 | I36: 2886.3872 | J36: 2733.2444 | K36: 2757.3632 | L36: 2781.1018 | M36: 2725.8883 | N36: 460.03272 | O36: 474.27549 | P36: 450.47811 | Q36: 411.57149 | R36: 416.51265 | S36: 431.19304 | T36: 365.11708 | U36: 380.76091 | V36: 0 | W36: 0 | X36: 0 | Y36: 0 | Z36: 0 | AA36: 0 | AB36: 0 | AC36: 0 | AD36: 0 | AE36: 0 | AF36: 0 | AG36: 0 | AH36: 0 | AI36: 0 | AJ36: 0 | AK36: 0 | AL36: 0 | AM36: 0 | AN36: 0 | AO36: 0 | AP36: 0 | AQ36: 0 | AR36: 0 | AS36: 0 | AT36: 0 | AU36: 0 | AV36: 0 | AW36: 0 | AX36: 0 | AY36: 0 | AZ36: 0
A37: Total Merch Hardwood | B37: 12862.782 | C37: 9539.2413 | D37: 9544.252 | E37: 5421.1154 | F37: 4600.83 | G37: 4267.1164 | H37: 4462.02 | I37: 3036.2409 | J37: 2879.8549 | K37: 2906.5011 | L37: 2923.563 | M37: 2861.2426 | N37: 530.79716 | O37: 551.39544 | P37: 521.29117 | Q37: 471.27607 | R37: 480.5412 | S37: 501.29848 | T37: 395.26948 | U37: 414.90871 | V37: 0 | W37: 0 | X37: 0 | Y37: 0 | Z37: 0 | AA37: 0 | AB37: 0 | AC37: 0 | AD37: 0 | AE37: 0 | AF37: 0 | AG37: 0 | AH37: 0 | AI37: 0 | AJ37: 0 | AK37: 0 | AL37: 0 | AM37: 0 | AN37: 0 | AO37: 0 | AP37: 0 | AQ37: 0 | AR37: 0 | AS37: 0 | AT37: 0 | AU37: 0 | AV37: 0 | AW37: 0 | AX37: 0 | AY37: 0 | AZ37: 0
A38: Unmerchantable Portions | B38: 12176.571 | C38: 9652.828 | D38: 9371.2288 | E38: 6757.6627 | F38: 5631.8925 | G38: 4574.1245 | H38: 4733.9054 | I38: 4020.8268 | J38: 3871.2726 | K38: 3849.819 | L38: 3904.4583 | M38: 3825.7189 | N38: 1960.7907 | O38: 2044.9325 | P38: 2082.0957 | Q38: 2124.4264 | R38: 2064.6946 | S38: 2141.2851 | T38: 1030.6649 | U38: 1061.9844 | V38: 0 | W38: 0 | X38: 0 | Y38: 0 | Z38: 0 | AA38: 0 | AB38: 0 | AC38: 0 | AD38: 0 | AE38: 0 | AF38: 0 | AG38: 0 | AH38: 0 | AI38: 0 | AJ38: 0 | AK38: 0 | AL38: 0 | AM38: 0 | AN38: 0 | AO38: 0 | AP38: 0 | AQ38: 0 | AR38: 0 | AS38: 0 | AT38: 0 | AU38: 0 | AV38: 0 | AW38: 0 | AX38: 0 | AY38: 0 | AZ38: 0
A39: Total Hardwood Carbon | B39: 25039.352 | C39: 19192.069 | D39: 18915.481 | E39: 12178.778 | F39: 10232.722 | G39: 8841.241 | H39: 9195.9254 | I39: 7057.0677 | J39: 6751.1275 | K39: 6756.3201 | L39: 6828.0212 | M39: 6686.9615 | N39: 2491.5879 | O39: 2596.3279 | P39: 2603.3869 | Q39: 2595.7025 | R39: 2545.2358 | S39: 2642.5836 | T39: 1425.9344 | U39: 1476.8931 | V39: 0 | W39: 0 | X39: 0 | Y39: 0 | Z39: 0 | AA39: 0 | AB39: 0 | AC39: 0 | AD39: 0 | AE39: 0 | AF39: 0 | AG39: 0 | AH39: 0 | AI39: 0 | AJ39: 0 | AK39: 0 | AL39: 0 | AM39: 0 | AN39: 0 | AO39: 0 | AP39: 0 | AQ39: 0 | AR39: 0 | AS39: 0 | AT39: 0 | AU39: 0 | AV39: 0 | AW39: 0 | AX39: 0 | AY39: 0 | AZ39: 0
A41: Total Living Tree Carbon | B41: =B39+B32 -> 524457.5 | C41: =C39+C32 -> 525946.33 | D41: =D39+D32 -> 587824.44 | E41: =E39+E32 -> 568188.85 | F41: =F39+F32 -> 610117.97 | G41: =G39+G32 -> 663132.46 | H41: =H39+H32 -> 745392.17 | I41: =I39+I32 -> 729721.68 | ... AZ41: =AZ39+AZ32 -> 113271.16
A43: Natural Management
A44: Natural Acres | B44: 3111.62 | C44: 3111.62 | D44: 3111.62 | E44: 3111.62 | F44: 3111.62 | G44: 3111.62 | H44: 3111.62 | I44: 3111.62 | J44: 3111.62 | K44: 3111.62 | L44: 3111.62 | M44: 3111.62 | N44: 3111.62 | O44: 3111.62 | P44: 3111.62 | Q44: 3111.62 | R44: 3111.62 | S44: 3111.62 | T44: 3111.62 | U44: 3111.62 | V44: 3111.62 | W44: 3111.62 | X44: 3111.62 | Y44: 3111.62 | Z44: 3111.62 | AA44: 3111.62 | AB44: 3111.62 | AC44: 3111.62 | AD44: 3111.62 | AE44: 3111.62 | AF44: 3111.62 | AG44: 3111.62 | AH44: 3111.62 | AI44: 3111.62 | AJ44: 3111.62 | AK44: 3111.62 | AL44: 3111.62 | AM44: 3111.62 | AN44: 3111.62 | AO44: 3111.62 | AP44: 3111.62 | AQ44: 3111.62 | AR44: 3111.62 | AS44: 3111.62 | AT44: 3111.62 | AU44: 3111.62 | AV44: 3111.62 | AW44: 3111.62 | AX44: 3111.62 | AY44: 3111.62 | AZ44: 3111.62
A45: Softwood Carbon (MtCO2e)
A46: Merchantable Stem
A47: Pine Large Saw Timber | B47: 0 | C47: 0 | D47: 0 | E47: 0 | F47: 0 | G47: 0 | H47: 0 | I47: 0 | J47: 0 | K47: 0 | L47: 0 | M47: 0 | N47: 0 | O47: 0 | P47: 0 | Q47: 0 | R47: 0 | S47: 0 | T47: 0 | U47: 0 | V47: 0 | W47: 0 | X47: 0 | Y47: 0 | Z47: 0 | AA47: 0 | AB47: 0 | AC47: 0 | AD47: 0 | AE47: 0 | AF47: 0 | AG47: 0 | AH47: 0 | AI47: 0 | AJ47: 0 | AK47: 0 | AL47: 0 | AM47: 0 | AN47: 0 | AO47: 0 | AP47: 0 | AQ47: 0 | AR47: 0 | AS47: 0 | AT47: 0 | AU47: 0 | AV47: 0 | AW47: 0 | AX47: 0 | AY47: 0 | AZ47: 0
A48: Pine Saw Timber | B48: 43948.138 | C48: 48540.649 | D48: 52952.109 | E48: 56323.314 | F48: 59878.324 | G48: 63073.45 | H48: 66146.555 | I48: 68142.031 | J48: 70854.472 | K48: 73564.117 | L48: 76095.683 | M48: 78520.627 | N48: 80635.39 | O48: 83234.789 | P48: 85303.472 | Q48: 87456.038 | R48: 87386.794 | S48: 89675.387 | T48: 92072.66 | U48: 94390.147 | V48: 96570.496 | W48: 96557.621 | X48: 96485.442 | Y48: 96378.606 | Z48: 96378.606 | AA48: 84556.353 | AB48: 69577.517 | AC48: 66366.582 | AD48: 66115.487 | AE48: 66115.886 | AF48: 66116.285 | AG48: 66118.19 | AH48: 66007.913 | AI48: 65999.875 | AJ48: 65999.157 | AK48: 66059.939 | AL48: 65331.535 | AM48: 55051.434 | AN48: 54920.216 | AO48: 47119.058 | AP48: 48063.133 | AQ48: 47622.178 | AR48: 47326.253 | AS48: 46888.24 | AT48: 46954.953 | AU48: 47014.821 | AV48: 32750.783 | AW48: 32123.421 | AX48: 31304.09 | AY48: 30403.282 | AZ48: 30403.282
A49: Pine Chip-N-Saw | B49: 101066.66 | C49: 103175.34 | D49: 105143.7 | E49: 106417.8 | F49: 107647.14 | G49: 108352.35 | H49: 109099.51 | I49: 109488.31 | J49: 109542.47 | K49: 110080.29 | L49: 110234.81 | M49: 110408.14 | N49: 110277.12 | O49: 110676.07 | P49: 110945.47 | Q49: 110971.34 | R49: 104845.57 | S49: 105148.71 | T49: 105211.38 | U49: 105262.2 | V49: 105198.39 | W49: 105158.3 | X49: 104933.57 | Y49: 104600.92 | Z49: 104600.92 | AA49: 81857.823 | AB49: 60468.978 | AC49: 57712.523 | AD49: 57671.157 | AE49: 57673.747 | AF49: 57764.678 | AG49: 57777.586 | AH49: 57458.347 | AI49: 57463.689 | AJ49: 57435.653 | AK49: 57837.021 | AL49: 55454.34 | AM49: 50497.116 | AN49: 50805.383 | AO49: 43810.544 | AP49: 44710.889 | AQ49: 43902.357 | AR49: 43695.537 | AS49: 42904.676 | AT49: 42888.454 | AU49: 42878.183 | AV49: 29078.585 | AW49: 27827.899 | AX49: 26525.641 | AY49: 26051.119 | AZ49: 26051.119
A50: Pine Pulpwood | B50: 69525.607 | C50: 70280.161 | D50: 70939.114 | E50: 71305.202 | F50: 71583.646 | G50: 71610.221 | H50: 71731.652 | I50: 71461.784 | J50: 71204.522 | K50: 71132.144 | L50: 70831.375 | M50: 70769.573 | N50: 70106.519 | O50: 69953.893 | P50: 69589.787 | Q50: 69114.563 | R50: 66122.008 | S50: 66104.087 | T50: 66158.149 | U50: 66268.002 | V50: 66286.018 | W50: 66265.821 | X50: 66152.592 | Y50: 65984.994 | Z50: 65984.994 | AA50: 51050.685 | AB50: 38538.899 | AC50: 37310.261 | AD50: 37287.001 | AE50: 37287.648 | AF50: 37580.469 | AG50: 37583.904 | AH50: 37461.151 | AI50: 37460.396 | AJ50: 37381.273 | AK50: 37648.313 | AL50: 35606.974 | AM50: 33315.941 | AN50: 33533.781 | AO50: 30806.346 | AP50: 31568.506 | AQ50: 31228.915 | AR50: 31085.81 | AS50: 30590.663 | AT50: 30611.732 | AU50: 30628.879 | AV50: 19246.722 | AW50: 18869.383 | AX50: 17878.38 | AY50: 17200.343 | AZ50: 17200.343
A51: Total Merch Pine | B51: 214540.41 | C51: 221996.15 | D51: 229034.92 | E51: 234046.32 | F51: 239109.11 | G51: 243036.02 | H51: 246977.72 | I51: 249092.13 | J51: 251601.46 | K51: 254776.55 | L51: 257161.87 | M51: 259698.34 | N51: 261019.03 | O51: 263864.75 | P51: 265838.73 | Q51: 267541.94 | R51: 258354.37 | S51: 260928.19 | T51: 263442.19 | U51: 265920.35 | V51: 268054.9 | W51: 267981.74 | X51: 267571.6 | Y51: 266964.52 | Z51: 266964.52 | AA51: 217464.86 | AB51: 168585.39 | AC51: 161389.37 | AD51: 161073.64 | AE51: 161077.28 | AF51: 161461.43 | AG51: 161479.68 | AH51: 160927.41 | AI51: 160923.96 | AJ51: 160816.08 | AK51: 161545.27 | AL51: 156392.85 | AM51: 138864.49 | AN51: 139259.38 | AO51: 121735.95 | AP51: 124342.53 | AQ51: 122753.45 | AR51: 122107.6 | AS51: 120383.58 | AT51: 120455.14 | AU51: 120521.88 | AV51: 81076.09 | AW51: 78820.703 | AX51: 75708.111 | AY51: 73654.744 | AZ51: 73654.744
A52: Unmerchantable Portions | B52: 1466.205 | C52: 1362.472 | D52: 1312.5351 | E52: 1295.4138 | F52: 1287.1743 | G52: 1272.9959 | H52: 1267.328 | I52: 1252.8204 | J52: 1223.5215 | K52: 1216.1289 | L52: 1209.8317 | M52: 1205.237 | N52: 1201.2232 | O52: 1195.8018 | P52: 1186.9786 | Q52: 1183.8529 | R52: 1129.3684 | S52: 1118.0933 | T52: 1118.9119 | U52: 1119.1098 | V52: 1116.8158 | W52: 1116.1227 | X52: 1112.2375 | Y52: 1106.4866 | Z52: 1106.4866 | AA52: 897.00453 | AB52: 573.0076 | AC52: 563.51881 | AD52: 560.20059 | AE52: 560.20447 | AF52: 560.20809 | AG52: 560.22657 | AH52: 559.69305 | AI52: 559.70912 | AJ52: 559.70226 | AK52: 570.47971 | AL52: 550.75247 | AM52: 524.67879 | AN52: 533.59185 | AO52: 507.62746 | AP52: 515.08276 | AQ52: 512.82537 | AR52: 511.42978 | AS52: 499.77953 | AT52: 499.26187 | AU52: 498.91868 | AV52: 340.10155 | AW52: 329.64964 | AX52: 311.41327 | AY52: 305.90884 | AZ52: 305.90884
A53: Total Softwood Carbon | B53: 216006.61 | C53: 223358.63 | D53: 230347.45 | E53: 235341.73 | F53: 240396.29 | G53: 244309.01 | H53: 248245.05 | I53: 250344.95 | J53: 252824.98 | K53: 255992.68 | L53: 258371.7 | M53: 260903.58 | N53: 262220.25 | O53: 265060.55 | P53: 267025.71 | Q53: 268725.79 | R53: 259483.74 | S53: 262046.28 | T53: 264561.1 | U53: 267039.46 | V53: 269171.72 | W53: 269097.87 | X53: 268683.84 | Y53: 268071.01 | Z53: 268071.01 | AA53: 218361.87 | AB53: 169158.4 | AC53: 161952.88 | AD53: 161633.85 | AE53: 161637.49 | AF53: 162021.64 | AG53: 162039.91 | AH53: 161487.1 | AI53: 161483.67 | AJ53: 161375.79 | AK53: 162115.75 | AL53: 156943.6 | AM53: 139389.17 | AN53: 139792.97 | AO53: 122243.58 | AP53: 124857.61 | AQ53: 123266.28 | AR53: 122619.03 | AS53: 120883.36 | AT53: 120954.4 | AU53: 121020.8 | AV53: 81416.192 | AW53: 79150.353 | AX53: 76019.524 | AY53: 73960.653 | AZ53: 73960.653
A54: Hardwood Carbon (MtCO2e)
A55: Merchantable Stem
A56: HW Saw Timber | B56: 13946.459 | C56: 15122.635 | D56: 16198.615 | E56: 17168.897 | F56: 18035.976 | G56: 18782.635 | H56: 19524.528 | I56: 20180.965 | J56: 20815.701 | K56: 21425.913 | L56: 22046.057 | M56: 22457.044 | N56: 22657.541 | O56: 23212.955 | P56: 23413.216 | Q56: 23962.035 | R56: 24533.773 | S56: 25089.028 | T56: 25626.344 | U56: 26141.282 | V56: 26623.899 | W56: 26623.411 | X56: 26620.676 | Y56: 26616.627 | Z56: 26616.627 | AA56: 26616.627 | AB56: 26616.627 | AC56: 26616.846 | AD56: 26617.014 | AE56: 26617.024 | AF56: 26618.471 | AG56: 26618.517 | AH56: 26618.568 | AI56: 26618.614 | AJ56: 26618.213 | AK56: 26618.384 | AL56: 26628.436 | AM56: 26728.404 | AN56: 26942.244 | AO56: 26982.298 | AP56: 27188.573 | AQ56: 27233.633 | AR56: 27265.674 | AS56: 27283.624 | AT56: 27320.007 | AU56: 27354.717 | AV56: 27222.074 | AW56: 27234.886 | AX56: 27260.278 | AY56: 26625.75 | AZ56: 26625.75
A57: HW Pulpwood | B57: 58044.297 | C57: 59425.193 | D57: 60647.402 | E57: 61524.437 | F57: 62437.115 | G57: 63124.493 | H57: 63787.631 | I57: 64089.465 | J57: 64317.704 | K57: 64801.697 | L57: 65086.237 | M57: 65248.543 | N57: 65015.157 | O57: 65339.191 | P57: 65353.345 | Q57: 65609.283 | R57: 65856.815 | S57: 66103.224 | T57: 66323.125 | U57: 66545.337 | V57: 66745.774 | W57: 66734.637 | X57: 66672.198 | Y57: 66579.779 | Z57: 66579.779 | AA57: 66579.779 | AB57: 66579.779 | AC57: 66580.996 | AD57: 66582.063 | AE57: 66582.345 | AF57: 66590.613 | AG57: 66591.958 | AH57: 66593.27 | AI57: 66594.533 | AJ57: 66591.917 | AK57: 66711.451 | AL57: 66926.925 | AM57: 67235.159 | AN57: 67615.614 | AO57: 67574.258 | AP57: 68464.258 | AQ57: 68496.965 | AR57: 68345.382 | AS57: 68004.022 | AT57: 68008.247 | AU57: 68008.882 | AV57: 67759.15 | AW57: 67743.62 | AX57: 67730.462 | AY57: 66788.012 | AZ57: 66788.012
A58: Total Merch Hardwood | B58: 71990.756 | C58: 74547.828 | D58: 76846.017 | E58: 78693.334 | F58: 80473.091 | G58: 81907.128 | H58: 83312.158 | I58: 84270.43 | J58: 85133.405 | K58: 86227.61 | L58: 87132.294 | M58: 87705.587 | N58: 87672.698 | O58: 88552.146 | P58: 88766.562 | Q58: 89571.318 | R58: 90390.588 | S58: 91192.252 | T58: 91949.469 | U58: 92686.619 | V58: 93369.673 | W58: 93358.048 | X58: 93292.874 | Y58: 93196.407 | Z58: 93196.407 | AA58: 93196.407 | AB58: 93196.407 | AC58: 93197.842 | AD58: 93199.077 | AE58: 93199.369 | AF58: 93209.084 | AG58: 93210.475 | AH58: 93211.838 | AI58: 93213.147 | AJ58: 93210.13 | AK58: 93329.835 | AL58: 93555.361 | AM58: 93963.563 | AN58: 94557.858 | AO58: 94556.556 | AP58: 95652.831 | AQ58: 95730.599 | AR58: 95611.056 | AS58: 95287.647 | AT58: 95328.254 | AU58: 95363.599 | AV58: 94981.224 | AW58: 94978.506 | AX58: 94990.74 | AY58: 93413.762 | AZ58: 93413.762
A59: Unmerchantable Portions | B59: 32530.338 | C59: 32852.937 | D59: 33196.764 | E59: 33436.821 | F59: 33835.541 | G59: 34196.485 | H59: 34610.522 | I59: 34896.422 | J59: 35159.75 | K59: 35558.744 | L59: 35833.126 | M59: 36058.406 | N59: 36079.154 | O59: 36382.735 | P59: 36465.777 | Q59: 36739.485 | R59: 37009.56 | S59: 37271.809 | T59: 37534.305 | U59: 37787.13 | V59: 37988.41 | W59: 37977.961 | X59: 37919.384 | Y59: 37832.679 | Z59: 37832.679 | AA59: 37832.679 | AB59: 37832.679 | AC59: 37835.28 | AD59: 37837.248 | AE59: 37837.308 | AF59: 37854.449 | AG59: 37854.762 | AH59: 37855.01 | AI59: 37855.266 | AJ59: 37850.646 | AK59: 37964.573 | AL59: 38054.838 | AM59: 38222.467 | AN59: 38436.137 | AO59: 38386.444 | AP59: 38822.77 | AQ59: 38833.486 | AR59: 38771.385 | AS59: 38601.549 | AT59: 38615.381 | AU59: 38629.748 | AV59: 38513.065 | AW59: 38514.019 | AX59: 38518.586 | AY59: 38028.036 | AZ59: 38028.036
A60: Total Hardwood Carbon | B60: 104521.09 | C60: 107400.77 | D60: 110042.78 | E60: 112130.16 | F60: 114308.63 | G60: 116103.61 | H60: 117922.68 | I60: 119166.85 | J60: 120293.15 | K60: 121786.35 | L60: 122965.42 | M60: 123763.99 | N60: 123751.85 | O60: 124934.88 | P60: 125232.34 | Q60: 126310.8 | R60: 127400.15 | S60: 128464.06 | T60: 129483.77 | U60: 130473.75 | V60: 131358.08 | W60: 131336.01 | X60: 131212.26 | Y60: 131029.09 | Z60: 131029.09 | AA60: 131029.09 | AB60: 131029.09 | AC60: 131033.12 | AD60: 131036.33 | AE60: 131036.68 | AF60: 131063.53 | AG60: 131065.24 | AH60: 131066.85 | AI60: 131068.41 | AJ60: 131060.78 | AK60: 131294.41 | AL60: 131610.2 | AM60: 132186.03 | AN60: 132994 | AO60: 132943 | AP60: 134475.6 | AQ60: 134564.08 | AR60: 134382.44 | AS60: 133889.2 | AT60: 133943.63 | AU60: 133993.35 | AV60: 133494.29 | AW60: 133492.52 | AX60: 133509.33 | AY60: 131441.8 | AZ60: 131441.8
A62: Total Living Tree Carbon | B62: =B60+B53 -> 320527.71 | C62: =C60+C53 -> 330759.39 | D62: =D60+D53 -> 340390.24 | E62: =E60+E53 -> 347471.89 | F62: =F60+F53 -> 354704.92 | G62: =G60+G53 -> 360412.63 | H62: =H60+H53 -> 366167.73 | I62: =I60+I53 -> 369511.8 | ... AZ62: =AZ60+AZ53 -> 205402.45
A65: Total Standing Live Carbon
A66: Softwood Carbon (MtCO2e)
A67: Merchantable Stem
A68: Pine Large Saw Timber | B68: 0 | C68: 0 | D68: 0 | E68: 0
A69: Pine Saw Timber | B69: 56827.152 | C69: 62717.188 | D69: 71190.567 | E69: 71414.121 | F69: 79501.369 | G69: 88546.863 | H69: 99577.338 | I69: 102905.08 | J69: 111220.82 | K69: 125581.42 | L69: 139187.66 | M69: 147556.33 | N69: 134145.47 | O69: 149967.98 | P69: 154637.5 | Q69: 138741.72 | R69: 153194.84 | S69: 177377.96 | T69: 203431.55 | U69: 229895.78 | V69: 256023.4 | W69: 279207.47 | X69: 269026.83 | Y69: 252984.94 | Z69: 105903.73 | AA69: 98758.515 | AB69: 89129.531 | AC69: 92876.127 | AD69: 98075.913 | AE69: 91671.906 | AF69: 101347.52 | AG69: 110477.65 | AH69: 116384.25 | AI69: 133323.3 | AJ69: 123820.01 | AK69: 146812.96 | AL69: 167559.27 | AM69: 180493.86 | AN69: 169270.23 | AO69: 117423.85 | AP69: 137230.99 | AQ69: 130927.45 | AR69: 127624.15 | AS69: 106115.23 | AT69: 115913.44 | AU69: 115980.2 | AV69: 50294.529 | AW69: 56246.924 | AX69: 64253.913 | AY69: 46398.518 | AZ69: 31423.762
A70: Pine Chip-N-Saw | B70: 362924.47 | C70: 363264.02 | D70: 413454.47 | E70: 416965.21 | F70: 457816.81 | G70: 501141.7 | H70: 554823.68 | I70: 538679.26 | J70: 517580.65 | K70: 534864.48 | L70: 527884.4 | M70: 526993.19 | N70: 461946.14 | O70: 533184.17 | P70: 502676.15 | Q70: 466375.25 | R70: 454062.57 | S70: 474646.58 | T70: 489490.68 | U70: 469280.21 | V70: 488883.11 | W70: 544901.17 | X70: 554612.74 | Y70: 485362.69 | Z70: 338135.78 | AA70: 345340.5 | AB70: 346401.22 | AC70: 375138.62 | AD70: 431888.59 | AE70: 462925.49 | AF70: 472814.95 | AG70: 423531.13 | AH70: 443397.28 | AI70: 462233.27 | AJ70: 441748.74 | AK70: 436199.76 | AL70: 448405.3 | AM70: 475483.82 | AN70: 428953.02 | AO70: 405608.96 | AP70: 418128.31 | AQ70: 419100.26 | AR70: 419959.1 | AS70: 347908.4 | AT70: 370072.7 | AU70: 312562.44 | AV70: 281258.84 | AW70: 325865.46 | AX70: 352223.57 | AY70: 251198.2 | AZ70: 97389.922
A71: Pine Pulpwood | B71: 229162.6 | C71: 238880.06 | D71: 254470.08 | E71: 252224.18 | F71: 262661.57 | G71: 279954.25 | H71: 305118.29 | I71: 309446.06 | J71: 287946.54 | K71: 244647.11 | L71: 228690.07 | M71: 244080.1 | N71: 239435.77 | O71: 266446.5 | P71: 247682.94 | Q71: 231505.49 | R71: 224642.96 | S71: 224237 | T71: 237204.17 | U71: 229832.53 | V71: 264939.44 | W71: 304812.36 | X71: 304707.12 | Y71: 283731.22 | Z71: 161328.3 | AA71: 191343.8 | AB71: 179724.84 | AC71: 200090.34 | AD71: 204699.91 | AE71: 201909.51 | AF71: 192778.42 | AG71: 180990.43 | AH71: 181658.52 | AI71: 196366.78 | AJ71: 163154.65 | AK71: 173461.41 | AL71: 200804.27 | AM71: 258709.51 | AN71: 228195.94 | AO71: 187979.6 | AP71: 167281.41 | AQ71: 161297.72 | AR71: 166000.1 | AS71: 133360.09 | AT71: 140665.99 | AU71: 130269.98 | AV71: 108173.96 | AW71: 130649.27 | AX71: 131160.4 | AY71: 101085.39 | AZ71: 49968.512
A72: Total Merch Pine | B72: 648914.22 | C72: 664861.26 | D72: 739115.12 | E72: 740603.52 | F72: 799979.75 | G72: 869642.81 | H72: 959519.31 | I72: 951030.4 | J72: 916748.01 | K72: 905093.02 | L72: 895762.13 | M72: 918629.63 | N72: 835527.38 | O72: 949598.66 | P72: 904996.59 | Q72: 836622.45 | R72: 831900.37 | S72: 876261.54 | T72: 930126.4 | U72: 929008.52 | V72: 1009846 | W72: 1128921 | X72: 1128346.7 | Y72: 1022078.8 | Z72: 605367.81 | AA72: 635442.81 | AB72: 615255.59 | AC72: 668105.08 | AD72: 734664.41 | AE72: 756506.91 | AF72: 766940.89 | AG72: 714999.21 | AH72: 741440.04 | AI72: 791923.34 | AJ72: 728723.41 | AK72: 756474.12 | AL72: 816768.84 | AM72: 914687.19 | AN72: 826419.19 | AO72: 711012.41 | AP72: 722640.71 | AQ72: 711325.43 | AR72: 713583.35 | AS72: 587383.72 | AT72: 626652.12 | AU72: 558812.62 | AV72: 439727.33 | AW72: 512761.66 | AX72: 547637.88 | AY72: 398682.11 | AZ72: 178782.2
A73: Unmerchantable Portions | B73: 66510.543 | C73: 65251.629 | D73: 60141.301 | E73: 50748.289 | F73: 40301.779 | G73: 28957.413 | H73: 24921.982 | I73: 21979.155 | J73: 16997.899 | K73: 16317.313 | L73: 12567.13 | M73: 14506.27 | N73: 21057.856 | O73: 21616.098 | P73: 20786.171 | Q73: 18732.23 | R73: 22844 | S73: 19287.999 | T73: 16739.594 | U73: 12402.637 | V73: 18738.948 | W73: 26027.993 | X73: 21701.765 | Y73: 19788.316 | Z73: 19322.992 | AA73: 29757.445 | AB73: 26184.302 | AC73: 30137.576 | AD73: 33829.312 | AE73: 30326.208 | AF73: 23822.718 | AG73: 22845.413 | AH73: 24404.564 | AI73: 23705.733 | AJ73: 20908.568 | AK73: 21071.958 | AL73: 30298.594 | AM73: 46638.214 | AN73: 43316.436 | AO73: 35497.796 | AP73: 28233.321 | AQ73: 24606.714 | AR73: 25281.109 | AS73: 22249.564 | AT73: 19332.774 | AU73: 18137.26 | AV73: 14872.655 | AW73: 17911.722 | AX73: 14315.287 | AY73: 11807.783 | AZ73: 8449.617
A74: Total Softwood Carbon | B74: 715424.76 | C74: 730112.89 | D74: 799256.42 | E74: 791351.8 | F74: 840281.53 | G74: 898600.23 | H74: 984441.29 | I74: 973009.56 | J74: 933745.91 | K74: 921410.33 | L74: 908329.26 | M74: 933135.9 | N74: 856585.24 | O74: 971214.76 | P74: 925782.76 | Q74: 855354.68 | R74: 854744.37 | S74: 895549.54 | T74: 946865.99 | U74: 941411.16 | V74: 1028584.9 | W74: 1154949 | X74: 1150048.5 | Y74: 1041867.2 | Z74: 624690.8 | AA74: 665200.25 | AB74: 641439.89 | AC74: 698242.66 | AD74: 768493.72 | AE74: 786833.12 | AF74: 790763.61 | AG74: 737844.63 | AH74: 765844.61 | AI74: 815629.07 | AJ74: 749631.97 | AK74: 777546.08 | AL74: 847067.43 | AM74: 961325.41 | AN74: 869735.63 | AO74: 746510.2 | AP74: 750874.03 | AQ74: 735932.14 | AR74: 738864.46 | AS74: 609633.29 | AT74: 645984.9 | AU74: 576949.89 | AV74: 454599.98 | AW74: 530673.38 | AX74: 561953.17 | AY74: 410489.89 | AZ74: 187231.81
A75: Hardwood Carbon (MtCO2e)
A76: Merchantable Stem
A77: HW Saw Timber | B77: 15027.528 | C77: 15914.301 | D77: 17070.433 | E77: 17511.573 | F77: 18349.293 | G77: 19080.008 | H77: 19848.591 | I77: 20330.819 | J77: 20962.311 | K77: 21575.051 | L77: 22188.518 | M77: 22592.398 | N77: 22728.305 | O77: 23290.075 | P77: 23484.029 | Q77: 24021.74 | R77: 24597.802 | S77: 25159.133 | T77: 25656.496 | U77: 26175.429 | V77: 26623.899 | W77: 26623.411 | X77: 26620.676 | Y77: 26616.627 | Z77: 26616.627 | AA77: 26616.627 | AB77: 26616.627 | AC77: 26616.846 | AD77: 26617.014 | AE77: 26617.024 | AF77: 26618.471 | AG77: 26618.517 | AH77: 26618.568 | AI77: 26618.614 | AJ77: 26618.213 | AK77: 26618.384 | AL77: 26628.436 | AM77: 26728.404 | AN77: 26942.244 | AO77: 26982.298 | AP77: 27188.573 | AQ77: 27233.633 | AR77: 27265.674 | AS77: 27283.624 | AT77: 27320.007 | AU77: 27354.717 | AV77: 27222.074 | AW77: 27234.886 | AX77: 27260.278 | AY77: 26625.75 | AZ77: 26625.75
A78: HW Pulpwood | B78: 69826.009 | C78: 68172.768 | D78: 69319.836 | E78: 66602.877 | F78: 66724.628 | G78: 67094.236 | H78: 67925.587 | I78: 66975.852 | J78: 67050.949 | K78: 67559.06 | L78: 67867.339 | M78: 67974.432 | N78: 65475.19 | O78: 65813.466 | P78: 65803.823 | Q78: 66020.854 | R78: 66273.327 | S78: 66534.417 | T78: 66688.242 | U78: 66926.098 | V78: 66745.774 | W78: 66734.637 | X78: 66672.198 | Y78: 66579.779 | Z78: 66579.779 | AA78: 66579.779 | AB78: 66579.779 | AC78: 66580.996 | AD78: 66582.063 | AE78: 66582.345 | AF78: 66590.613 | AG78: 66591.958 | AH78: 66593.27 | AI78: 66594.533 | AJ78: 66591.917 | AK78: 66711.451 | AL78: 66926.925 | AM78: 67235.159 | AN78: 67615.614 | AO78: 67574.258 | AP78: 68464.258 | AQ78: 68496.965 | AR78: 68345.382 | AS78: 68004.022 | AT78: 68008.247 | AU78: 68008.882 | AV78: 67759.15 | AW78: 67743.62 | AX78: 67730.462 | AY78: 66788.012 | AZ78: 66788.012
A79: Total Merch Hardwood | B79: 84853.537 | C79: 84087.069 | D79: 86390.269 | E79: 84114.45 | F79: 85073.92 | G79: 86174.244 | H79: 87774.178 | I79: 87306.671 | J79: 88013.26 | K79: 89134.111 | L79: 90055.857 | M79: 90566.83 | N79: 88203.495 | O79: 89103.541 | P79: 89287.853 | Q79: 90042.594 | R79: 90871.129 | S79: 91693.551 | T79: 92344.738 | U79: 93101.528 | V79: 93369.673 | W79: 93358.048 | X79: 93292.874 | Y79: 93196.407 | Z79: 93196.407 | AA79: 93196.407 | AB79: 93196.407 | AC79: 93197.842 | AD79: 93199.077 | AE79: 93199.369 | AF79: 93209.084 | AG79: 93210.475 | AH79: 93211.838 | AI79: 93213.147 | AJ79: 93210.13 | AK79: 93329.835 | AL79: 93555.361 | AM79: 93963.563 | AN79: 94557.858 | AO79: 94556.556 | AP79: 95652.831 | AQ79: 95730.599 | AR79: 95611.056 | AS79: 95287.647 | AT79: 95328.254 | AU79: 95363.599 | AV79: 94981.224 | AW79: 94978.506 | AX79: 94990.74 | AY79: 93413.762 | AZ79: 93413.762
A80: Unmerchantable Portions | B80: 44706.909 | C80: 42505.765 | D80: 42567.993 | E80: 40194.484 | F80: 39467.433 | G80: 38770.61 | H80: 39344.427 | I80: 38917.249 | J80: 39031.022 | K80: 39408.563 | L80: 39737.585 | M80: 39884.125 | N80: 38039.944 | O80: 38427.667 | P80: 38547.873 | Q80: 38863.911 | R80: 39074.254 | S80: 39413.094 | T80: 38564.97 | U80: 38849.114 | V80: 37988.41 | W80: 37977.961 | X80: 37919.384 | Y80: 37832.679 | Z80: 37832.679 | AA80: 37832.679 | AB80: 37832.679 | AC80: 37835.28 | AD80: 37837.248 | AE80: 37837.308 | AF80: 37854.449 | AG80: 37854.762 | AH80: 37855.01 | AI80: 37855.266 | AJ80: 37850.646 | AK80: 37964.573 | AL80: 38054.838 | AM80: 38222.467 | AN80: 38436.137 | AO80: 38386.444 | AP80: 38822.77 | AQ80: 38833.486 | AR80: 38771.385 | AS80: 38601.549 | AT80: 38615.381 | AU80: 38629.748 | AV80: 38513.065 | AW80: 38514.019 | AX80: 38518.586 | AY80: 38028.036 | AZ80: 38028.036
A81: Total Hardwood Carbon | B81: 129560.45 | C81: 126592.83 | D81: 128958.26 | E81: 124308.93 | F81: 124541.35 | G81: 124944.85 | H81: 127118.61 | I81: 126223.92 | J81: 127044.28 | K81: 128542.67 | L81: 129793.44 | M81: 130450.95 | N81: 126243.44 | O81: 127531.21 | P81: 127835.73 | Q81: 128906.51 | R81: 129945.38 | S81: 131106.64 | T81: 130909.71 | U81: 131950.64 | V81: 131358.08 | W81: 131336.01 | X81: 131212.26 | Y81: 131029.09 | Z81: 131029.09 | AA81: 131029.09 | AB81: 131029.09 | AC81: 131033.12 | AD81: 131036.33 | AE81: 131036.68 | AF81: 131063.53 | AG81: 131065.24 | AH81: 131066.85 | AI81: 131068.41 | AJ81: 131060.78 | AK81: 131294.41 | AL81: 131610.2 | AM81: 132186.03 | AN81: 132994 | AO81: 132943 | AP81: 134475.6 | AQ81: 134564.08 | AR81: 134382.44 | AS81: 133889.2 | AT81: 133943.63 | AU81: 133993.35 | AV81: 133494.29 | AW81: 133492.52 | AX81: 133509.33 | AY81: 131441.8 | AZ81: 131441.8
A83: Total Living Tree Carbon | B83: 844985.21 | C83: 856705.73 | D83: 928214.68 | E83: 915660.74 | F83: 964822.88 | G83: 1023545.1 | H83: 1111559.9 | I83: 1099233.5 | J83: 1060790.2 | K83: 1049953 | L83: 1038122.7 | M83: 1063586.9 | N83: 982828.68 | O83: 1098746 | P83: 1053618.5 | Q83: 984261.18 | R83: 984689.75 | S83: 1026656.2 | T83: 1077775.7 | U83: 1073361.8 | V83: 1159943 | W83: 1286285 | X83: 1281260.7 | Y83: 1172896.2 | Z83: 755719.89 | AA83: 796229.34 | AB83: 772468.97 | AC83: 829275.78 | AD83: 899530.04 | AE83: 917869.8 | AF83: 921827.14 | AG83: 868909.86 | AH83: 896911.45 | AI83: 946697.49 | AJ83: 880692.75 | AK83: 908840.49 | AL83: 978677.63 | AM83: 1093511.4 | AN83: 1002729.6 | AO83: 879453.2 | AP83: 885349.63 | AQ83: 870496.23 | AR83: 873246.9 | AS83: 743522.48 | AT83: 779928.53 | AU83: 710943.23 | AV83: 588094.27 | AW83: 664165.91 | AX83: 695462.49 | AY83: 541931.69 | AZ83: 318673.61
